Workbook
Name LCATS: #REF!

Sheet 2025+ Revenue Projections
A1: Year | B1: 2025 | N1: 2026 | Z1: 2027
A2: Month | B2: 1 | C2: 2 | D2: 3 | E2: 4 | F2: 5 | G2: 6 | H2: 7 | I2: 8 | J2: 9 | K2: 10 | L2: 11 | M2: 12 | N2: 1 | O2: 2 | P2: 3 | Q2: 4 | R2: 5 | S2: 6 | T2: 7 | U2: 8 | V2: 9 | W2: 10 | X2: 11 | Y2: 12 | Z2: 1 | AA2: 2 | AB2: 3 | AC2: 4 | AD2: 5 | AE2: 6 | AF2: 7 | AG2: 8 | AH2: 9 | AI2: 10 | AJ2: 11 | AK2: 12
A3: Prime Contracts
A4: AMRIID II | B4: ='AMRIID 2.1'!J140 -> 31889.44 | C4: ='AMRIID 2.1'!K140 -> 31889.44 | D4: ='AMRIID 2.1'!L140 -> 31889.44 | E4: ='AMRIID 2.1'!M140 -> 31889.44 | F4: ='AMRIID 2.1'!N140 -> 31889.44 | G4: ='AMRIID 2.1'!O140 -> 31889.44 | H4: ='AMRIID 2.1'!P140 -> 31889.44 | I4: ='AMRIID 2.1'!Q140 -> 31889.44 | J4: ='AMRIID 2.1'!R140 -> 31889.44
A5: DHS FLETF | B5: ='DHS FLETF'!J109 -> 121462.58 | C5: ='DHS FLETF'!K109 -> 121462.58 | D5: ='DHS FLETF'!L109 -> 121462.58 | E5: ='DHS FLETF'!M109 -> 121462.58 | F5: ='DHS FLETF'!N109 -> 121462.58 | G5: ='DHS FLETF'!O109 -> 121462.58 | H5: ='DHS FLETF'!P109 -> 121462.58
A6: DOT CTS | B6: 33333.33 | C6: 33333.33 | D6: 33333.33 | E6: 33333.33 | F6: 33333.33 | G6: 33333.33 | H6: 33333.33 | I6: 33333.33 | J6: 33333.33
A7: AO Call 1.4 - RAE Support | B7: ='AO Call 1.4'!J116 -> 415263.2 | C7: ='AO Call 1.4'!K116 -> 394609.28
A8: AO Call 2.2 - EA Support | B8: ='AO Call 2.2'!J104 -> 261904 | C8: ='AO Call 2.2'!K104 -> 261904 | D8: ='AO Call 2.2'!L104 -> 261904 | E8: ='AO Call 2.2'!M104 -> 261904 | F8: ='AO Call 2.2'!N104 -> 261904 | G8: ='AO Call 2.2'!O104 -> 246537.6 | H8: ='AO Call 2.2'!P104 -> 264651.2 | I8: ='AO Call 2.2'!Q104 -> 264651.2 | ... V8: ='AO Call 2.2'!AD104 -> 266016.72
A9: AO Call 4.1 - MFA Support | B9: ='AO Call 4.1'!N110 -> 163292.64 | C9: ='AO Call 4.1'!O110 -> 147740.96 | D9: ='AO Call 4.1'!P110 -> 155516.8 | E9: ='AO Call 4.1'!Q110 -> 147740.96 | F9: ='AO Call 4.1'!R110 -> 163292.64 | G9: ='AO Call 4.1'!S110 -> 163292.64 | H9: ='AO Call 4.1'!T110 -> 147740.96 | I9: ='AO Call 4.1'!U110 -> 171068.48 | ... AC9: ='AO Call 4.1'!AO110 -> 147740.96
A10: AO Call 5.1 - Cloud | B10: ='AO Call 5.1'!M110 -> 174456.48 | C10: ='AO Call 5.1'!N110 -> 158596.8 | D10: ='AO Call 5.1'!O110 -> 166526.64 | E10: ='AO Call 5.1'!P110 -> 166526.64
A11: AO Call 6.1 - Cloud DevSecOps | B11: ='AO Call 6.1'!N110 -> 67956.16 | C11: ='AO Call 6.1'!O110 -> 71532.8 | D11: ='AO Call 6.1'!P110 -> 57222.4 | E11: ='AO Call 6.1'!Q110 -> 50064 | F11: ='AO Call 6.1'!R110 -> 50064 | G11: ='AO Call 6.1'!S110 -> 45296 | H11: ='AO Call 6.1'!T110 -> 52448 | I11: ='AO Call 6.1'!U110 -> 42912 | ... R11: ='AO Call 6.1'!AD110 -> 50064
A12: AO Call 8 - GovBoard Support | B12: ='AO Call 8'!Q129 -> 14426.2
A13: AO Call 8.1 - GovBoard Support | C13: ='AO Call 8.1'!F129 -> 11908.8 | D13: ='AO Call 8.1'!G129 -> 11908.8 | E13: ='AO Call 8.1'!H129 -> 11908.8 | F13: ='AO Call 8.1'!I129 -> 11908.8 | G13: ='AO Call 8.1'!J129 -> 11908.8 | H13: ='AO Call 8.1'!K129 -> 11908.8 | I13: ='AO Call 8.1'!L129 -> 11908.8 | J13: ='AO Call 8.1'!M129 -> 11908.8 | ... AK13: ='AO Call 8.1'!AN129 -> 11908.8
A14: AO Call 10 - External File Sharing | B14: ='AO Call 10.1'!I109 -> 39494.4
A15: AO Call 12 - EITPM | B15: ='AO Call 12'!J179 -> 123431.18 | C15: ='AO Call 12'!K179 -> 11667.48 | D15: ='AO Call 12'!L179 -> 170372.28 | E15: ='AO Call 12'!M179 -> 109435.36 | F15: ='AO Call 12'!N179 -> 125167.68 | G15: ='AO Call 12'!O179 -> 102409.92 | H15: ='AO Call 12'!P179 -> 125167.68
A16: AO Call 13 - DevSecOps | B16: ='AO Call 13'!J110 -> 92120 | C16: ='AO Call 13'!K110 -> 87514 | D16: ='AO Call 13'!L110 -> 92120 | E16: ='AO Call 13'!M110 -> 96726 | F16: ='AO Call 13'!N110 -> 128066.4 | G16: ='AO Call 13'!O110 -> 148528.8 | H16: ='AO Call 13'!P110 -> 181535.2 | I16: ='AO Call 13'!Q110 -> 173283.6 | ... AK16: ='AO Call 13'!AS110 -> 110602.8
A17: AO Call 14 - ICAM | B17: ='AO Call 14'!J169 -> 162360.8 | C17: ='AO Call 14'!K169 -> 271172.36 | D17: ='AO Call 14'!L169 -> 16860.9 | E17: ='AO Call 14'!M169 -> 16860.9 | F17: ='AO Call 14'!N169 -> 32634 | G17: ='AO Call 14'!O169 -> 40792.5 | H17: ='AO Call 14'!P169 -> 40792.5
A18: AO Call 15 - R&I | B18: ='AO Call 15'!J110 -> 152105.6 | C18: ='AO Call 15'!K110 -> 139025.28 | D18: ='AO Call 15'!L110 -> 146342.4 | E18: ='AO Call 15'!M110 -> 173827.92 | F18: ='AO Call 15'!N110 -> 182105.44 | G18: ='AO Call 15'!O110 -> 148010.4 | H18: ='AO Call 15'!P110 -> 180901.6 | I18: ='AO Call 15'!Q110 -> 172678.8 | ... AH18: ='AO Call 15'!AP110 -> 129289.76
A20: USCIS RIVER | F20: 574793.48 | G20: 574793.48 | H20: 574793.48 | I20: 574793.48 | J20: 574793.48 | K20: 574793.48 | L20: 574793.48 | M20: 574793.48 | N20: 574793.48 | O20: 574793.48 | P20: 574793.48 | Q20: 574793.48 | R20: 589152.68 | S20: 589152.68 | T20: 589152.68 | U20: 589152.68 | V20: 589152.68 | W20: 589152.68 | X20: 589152.68 | Y20: 589152.68 | Z20: 589152.68 | AA20: 589152.68 | AB20: 589152.68 | AC20: 589152.68 | AD20: 603882.48 | AE20: 603882.48 | AF20: 603882.48 | AG20: 603882.48 | AH20: 603882.48 | AI20: 603882.48 | AJ20: 603882.48 | AK20: 603882.48
A22: Subcontracts
A23: IAE | B23: =IAE!E76 -> 91915 | C23: =IAE!F76 -> 91915 | D23: =IAE!G76 -> 91915 | E23: =IAE!H76 -> 91915 | F23: =IAE!I76 -> 91915 | G23: =IAE!J76 -> 91915 | H23: =IAE!K76 -> 91915 | I23: =IAE!L76 -> 91915 | J23: =IAE!M76 -> 91915
A24: ODOS III | B24: =ODOS!E91 -> 233670.4 | C24: =ODOS!F91 -> 0 | D24: =ODOS!G91 -> 0 | E24: =ODOS!H91 -> 0 | F24: =ODOS!I91 -> 0 | G24: =ODOS!J91 -> 0 | H24: =ODOS!K91 -> 0
A25: FDA CAEMS | B25: 14496 | C25: 14496 | D25: 17504.73 | E25: 14496 | F25: 14496 | G25: 17504.73 | H25: 14496 | I25: 14496 | J25: 17504.73 | K25: 14496 | L25: 14496 | M25: 17504.73
A26: FEMA | B26: =FEMA!E91 -> 70160 | C26: =FEMA!F91 -> 63144 | D26: =FEMA!G91 -> 70160 | E26: =FEMA!H91 -> 73668 | F26: =FEMA!I91 -> 70160 | G26: =FEMA!J91 -> 66652
A27: DHS - Entity List | B27: 121462.58 | C27: 121462.58 | D27: 121462.58 | E27: 121462.58 | F27: 121462.58 | G27: 121462.58 | H27: 121462.58 | I27: 121462.58 | J27: 121462.58 | K27: 124907.22 | L27: 124907.22 | M27: 124907.22 | N27: 124907.22 | O27: 124907.22 | P27: 124907.22 | Q27: 124907.22 | R27: 124907.22 | S27: 124907.22 | T27: 124907.22 | U27: 124907.22 | V27: 124907.22 | W27: 128607.05 | X27: 128607.05 | Y27: 128607.05 | Z27: 128607.05 | AA27: 128607.05 | AB27: 128607.05 | AC27: 128607.05 | AD27: 128607.05 | AE27: 128607.05 | AF27: 128607.05 | AG27: 128607.05 | AH27: 128607.05
A28: GAO TIS | H28: =95*160*30 -> 456000 | I28: =95*160*30 -> 456000 | J28: =95*160*30 -> 456000 | K28: =95*160*30 -> 456000 | L28: =95*160*30 -> 456000 | M28: =95*160*30 -> 456000 | N28: =95*160*30 -> 456000 | O28: =95*160*30 -> 456000 | ... S28: =95*160*30 -> 456000 | T28: =97.38*160*30 -> 467424 | U28: =97.38*160*30 -> 467424 | V28: =97.38*160*30 -> 467424 | W28: =97.38*160*30 -> 467424 | X28: =97.38*160*30 -> 467424 | Y28: =97.38*160*30 -> 467424 | Z28: =97.38*160*30 -> 467424 | AA28: =97.38*160*30 -> 467424 | ... AE28: =97.38*160*30 -> 467424 | AF28: =99.81*160*30 -> 479088 | AG28: =99.81*160*30 -> 479088 | AH28: =99.81*160*30 -> 479088 | AI28: =99.81*160*30 -> 479088 | AJ28: =99.81*160*30 -> 479088 | AK28: =99.81*160*30 -> 479088
A30: Summary - All Projects
A31: Year | B31: 2025 | N31: 2026 | Z31: 2027
A32: Month | B32: 1 | C32: 2 | D32: 3 | E32: 4 | F32: 5 | G32: 6 | H32: 7 | I32: 8 | J32: 9 | K32: 10 | L32: 11 | M32: 12 | N32: 1 | O32: 2 | P32: 3 | Q32: 4 | R32: 5 | S32: 6 | T32: 7 | U32: 8 | V32: 9 | W32: 10 | X32: 11 | Y32: 12 | Z32: 1 | AA32: 2 | AB32: 3 | AC32: 4 | AD32: 5 | AE32: 6 | AF32: 7 | AG32: 8 | AH32: 9 | AI32: 10 | AJ32: 11 | AK32: 12
A33: Forecast Rev | B33: =SUM(B4:B22)+SUM(B23:B29) -> 2385200 | C33: =SUM(C4:C22)+SUM(C23:C29) -> 2033374.7 | D33: =SUM(D4:D22)+SUM(D23:D29) -> 1566501.9 | E33: =SUM(E4:E22)+SUM(E23:E29) -> 1523221.5 | F33: =SUM(F4:F22)+SUM(F23:F29) -> 2014655.4 | G33: =SUM(G4:G22)+SUM(G23:G29) -> 1965789.8 | H33: =SUM(H4:H22)+SUM(H23:H29) -> 2450498.4 | I33: =SUM(I4:I22)+SUM(I23:I29) -> 2160392.7 | ... AK33: =SUM(AK4:AK22)+SUM(AK23:AK29) -> 1205482.1
K35: 2025 Year End Summary
B36: Total Backlog: | C36: =SUM(B33:AK33) -> 63741788 | L36: Prime Contract Rev | M36: =SUM(B4:M21) -> 18249303
L37: SubK Rev | M37: =SUM(B23:M29) -> 5864721.2
M38: =SUM(M36:M37) -> 24114024 | AE38: 95
AE39: =AE38*1.025 -> 97.375
AE40: =AE39*1.025 -> 99.809375

Sheet Do not use - Summary
A1: Summary - Prime Contracts
A2: Year | B2: 2022 | F2: 2023 | R2: 2024 | AD2: 2025
A3: Month | B3: 9 | C3: 10 | D3: 11 | E3: 12 | F3: 1 | G3: 2 | H3: 3 | I3: 4 | J3: 5 | K3: 6 | L3: 7 | M3: 8 | N3: 9 | O3: 10 | P3: 11 | Q3: 12 | R3: 1 | S3: 2 | T3: 3 | U3: 4 | V3: 5 | W3: 6 | X3: 7 | Y3: 8 | Z3: 9 | AA3: 10 | AB3: 11 | AC3: 12 | AD3: 1 | AE3: 2 | AF3: 3 | AG3: 4 | AH3: 5 | AI3: 6 | AJ3: 7 | AK3: 8 | AL3: 9 | AM3: 10 | AN3: 11 | AO3: 12 | AP3: 2 | AQ3: 3 | AR3: 4 | AS3: 5 | AT3: 6 | AU3: 7 | AV3: 8 | AW3: 9 | AX3: 10 | AY3: 11 | AZ3: 12
A4: Working Days | I4: 20 | J4: 22 | K4: 22 | L4: 20 | M4: 23 | N4: 19 | O4: 21 | P4: 20 | Q4: 20
A5: DHS CRCL | AP5: All Periods | AQ5: CY2023 | AR5: CY2024
A6: Charged | B6: ='DHS CRCL'!E83 -> 2080 | C6: ='DHS CRCL'!F83 -> 45618 | D6: ='DHS CRCL'!G83 -> 79599.57 | E6: ='DHS CRCL'!H83 -> 99689.66 | F6: ='DHS CRCL'!I83 -> 114470.18 | G6: ='DHS CRCL'!J83 -> 103617.85 | H6: ='DHS CRCL'!K83 -> 129372.31 | I6: ='DHS CRCL'!L83 -> 122164.97 | ... N6: ='DHS CRCL'!Q83 -> 100546.61 | AP6: =SUM(B6:AD6) -> 1283326.3 | AQ6: =SUM(F6:Q6) -> 1056339.1
A7: Revenue | B7: ='DHS CRCL'!E105 -> 2080 | C7: ='DHS CRCL'!F105 -> 45618 | D7: ='DHS CRCL'!G105 -> 78207.5 | E7: ='DHS CRCL'!H105 -> 106678.77 | F7: ='DHS CRCL'!I105 -> 104269.51 | G7: ='DHS CRCL'!J105 -> 105333.69 | H7: ='DHS CRCL'!K105 -> 129372.31 | I7: ='DHS CRCL'!L105 -> 122164.97 | ... N7: ='DHS CRCL'!Q105 -> 100546.61 | AP7: =SUM(B7:AD7) -> 1280438.5 | AQ7: =SUM(F7:Q7) -> 1047854.2
O8: DHS CRCL OP1 | AP8: All Periods | AQ8: CY2023 | AR8: CY2024
A9: Charged | O9: ='DHS CRCL OP1'!F182 -> 2307.3 | P9: ='DHS CRCL OP1'!G182 -> 128340.84 | Q9: ='DHS CRCL OP1'!H182 -> 136521.19 | R9: ='DHS CRCL OP1'!I182 -> 120057.15 | S9: ='DHS CRCL OP1'!J182 -> 137099.47 | T9: ='DHS CRCL OP1'!K182 -> 107300.02 | U9: ='DHS CRCL OP1'!L182 -> 95743.5 | V9: ='DHS CRCL OP1'!M182 -> 104251.49 | ... Z9: ='DHS CRCL OP1'!Q182 -> 110506.96 | AP9: =SUM(B9:AD9) -> 1282900 | AQ9: =SUM(F9:Q9) -> 267169.33 | AR9: =SUM(R9:AC9) -> 1015730.7
A10: Forecast Rev | R10: ='DHS CRCL OP1'!J138 -> 124150.78 | S10: ='DHS CRCL OP1'!K138 -> 123720.49 | T10: ='DHS CRCL OP1'!L138 -> 118767.42 | U10: ='DHS CRCL OP1'!M138 -> 115249.56 | V10: ='DHS CRCL OP1'!N138 -> 115249.56 | W10: ='DHS CRCL OP1'!O138 -> 109759.92 | X10: ='DHS CRCL OP1'!P138 -> 115249.56 | Y10: ='DHS CRCL OP1'!Q138 -> 110506.96 | Z10: ='DHS CRCL OP1'!R138 -> 118603.8 | AP10: =SUM(B10:AD10) -> 1051258.1 | AQ10: =SUM(F10:Q10) -> 0 | AR10: =SUM(R10:AC10) -> 1051258.1
A11: Revenue | O11: ='DHS CRCL OP1'!F247 -> 0 | P11: ='DHS CRCL OP1'!G247 -> 128340.84 | Q11: ='DHS CRCL OP1'!H247 -> 136521.19 | R11: ='DHS CRCL OP1'!I247 -> 122308.33 | S11: ='DHS CRCL OP1'!J247 -> 137099.47 | T11: ='DHS CRCL OP1'!K247 -> 107300.02 | U11: ='DHS CRCL OP1'!L247 -> 95743.5 | V11: ='DHS CRCL OP1'!M247 -> 104251.49 | ... Z11: ='DHS CRCL OP1'!Q247 -> 110506.96 | AP11: =SUM(B11:AD11) -> 1291112.7 | AQ11: =SUM(F11:Q11) -> 264862.03 | AR11: =SUM(R11:AC11) -> 1026250.7
A12: DHS HSI | AP12: All Periods | AQ12: CY2023 | AR12: CY2024
A13: Forecast Rev | AP13: =SUM(B13:AD13) -> 0 | AQ13: =SUM(F13:Q13) -> 0
A14: Revenue | B14: ='DHS HSI'!E96 -> 0 | C14: ='DHS HSI'!F96 -> 81837 | D14: ='DHS HSI'!G96 -> 81837 | E14: ='DHS HSI'!H96 -> 81837 | F14: ='DHS HSI'!I96 -> 81837 | G14: ='DHS HSI'!J96 -> 81837 | H14: ='DHS HSI'!K96 -> 81837 | I14: ='DHS HSI'!L96 -> 81837 | ... N14: ='DHS HSI'!Q96 -> 81837 | AP14: =SUM(B14:AD14) -> 982044 | AQ14: =SUM(F14:Q14) -> 736533
O15: DHS HSI OP1 | AP15: All Periods | AQ15: CY2023 | AR15: CY2024
A16: Forecast Rev | R16: ='DHS HSI OP1'!J167 -> 167345.93 | S16: ='DHS HSI OP1'!K167 -> 167345.93 | T16: ='DHS HSI OP1'!L167 -> 167345.93 | U16: ='DHS HSI OP1'!M167 -> 167345.93 | V16: ='DHS HSI OP1'!N167 -> 167345.93 | W16: ='DHS HSI OP1'!O167 -> 167345.93 | X16: ='DHS HSI OP1'!P167 -> 167345.93 | Y16: ='DHS HSI OP1'!Q167 -> 167345.92 | Z16: ='DHS HSI OP1'!R167 -> 167345.93 | AP16: =SUM(B16:AD16) -> 1506113.3 | AQ16: =SUM(F16:Q16) -> 0 | AR16: =SUM(R16:AC16) -> 1506113.3
A17: Revenue | O17: ='DHS HSI OP1'!F187 -> 0 | P17: ='DHS HSI OP1'!G187 -> 167345.93 | Q17: ='DHS HSI OP1'!H187 -> 167345.93 | R17: ='DHS HSI OP1'!I187 -> 167345.93 | S17: ='DHS HSI OP1'!J187 -> 167345.93 | T17: ='DHS HSI OP1'!K187 -> 167345.93 | U17: ='DHS HSI OP1'!L187 -> 167345.93 | V17: ='DHS HSI OP1'!M187 -> 167345.93 | ... Z17: ='DHS HSI OP1'!Q187 -> 167345.93 | AP17: =SUM(B17:AD17) -> 1840805.2 | AQ17: =SUM(F17:Q17) -> 334691.85 | AR17: =SUM(R17:AC17) -> 1506113.3
A18: DOI | AP18: All Periods | AQ18: CY2023 | AR18: CY2024
A19: Charged | D19: =DOI!E80 -> 0 | E19: =DOI!F80 -> 6799.31 | F19: =DOI!G80 -> 28450.775 | G19: =DOI!H80 -> 91421.922 | H19: =DOI!I80 -> 140162.23 | I19: =DOI!J80 -> 88017.95 | J19: =DOI!K80 -> 66947.54 | K19: =DOI!L80 -> 56544.185 | ... P19: =DOI!Q80 -> 0 | AP19: =SUM(B19:AD19) -> 643154.51 | AQ19: =SUM(F19:Q19) -> 636355.2
A20: Revenue | D20: =DOI!E99 -> 0 | E20: =DOI!F99 -> 6799.31 | F20: =DOI!G99 -> 28450.16 | G20: =DOI!H99 -> 91417.95 | H20: =DOI!I99 -> 140154.81 | I20: =DOI!J99 -> 88129.64 | J20: =DOI!K99 -> 66947.54 | K20: =DOI!L99 -> 56544.185 | ... P20: =DOI!Q99 -> 0 | AP20: =SUM(B20:AD20) -> 643254.2 | AQ20: =SUM(F20:Q20) -> 636454.89
A21: DOJ ICITAP | AP21: All Periods | AQ21: CY2023 | AR21: CY2024
A22: Charged | E22: ='DOJ ICITAP'!H78 -> 0 | F22: ='DOJ ICITAP'!I78 -> 11589.44 | G22: ='DOJ ICITAP'!J78 -> 11774.725 | H22: ='DOJ ICITAP'!K78 -> 31861.38 | I22: ='DOJ ICITAP'!L78 -> 7186.625 | J22: ='DOJ ICITAP'!M78 -> 8528.45 | K22: ='DOJ ICITAP'!N78 -> 9773.6 | AP22: =SUM(B22:AD22) -> 80714.22 | AQ22: =SUM(F22:Q22) -> 80714.22
A23: Revenue | E23: ='DOJ ICITAP'!H97 -> 0 | F23: ='DOJ ICITAP'!I97 -> 11589.44 | G23: ='DOJ ICITAP'!J97 -> 11774.73 | H23: ='DOJ ICITAP'!K97 -> 29388.6 | I23: ='DOJ ICITAP'!L97 -> 7186.63 | J23: ='DOJ ICITAP'!M97 -> 8528.45 | K23: ='DOJ ICITAP'!N97 -> 9773.6 | AP23: =SUM(B23:AD23) -> 78241.45 | AQ23: =SUM(F23:Q23) -> 78241.45
A24: AMRIID | AP24: All Periods | AQ24: CY2023 | AR24: CY2024
A25: Forecast Rev | AP25: =SUM(B25:AD25) -> 0 | AQ25: =SUM(F25:Q25) -> 0
A26: Revenue | B26: =AMRIID!E93 -> 0 | C26: =AMRIID!F93 -> 61797.13 | D26: =AMRIID!G93 -> 61797.13 | E26: =AMRIID!H93 -> 61797.13 | F26: =AMRIID!I93 -> 61797.13 | G26: =AMRIID!J93 -> 61797.13 | H26: =AMRIID!K93 -> 61797.13 | I26: =AMRIID!L93 -> 61797.13 | ... N26: =AMRIID!Q93 -> 61797.13 | AP26: =SUM(B26:AD26) -> 741565.56 | AQ26: =SUM(F26:Q26) -> 556174.17
N27: AMRIID II | AP27: All Periods | AQ27: CY2023 | AR27: CY2024
A28: Forecast Rev | R28: ='AMRIID 2'!J143 -> 30811.32 | S28: ='AMRIID 2'!K143 -> 30811.32 | T28: ='AMRIID 2'!L143 -> 30811.32 | U28: ='AMRIID 2'!M143 -> 30811.32 | V28: ='AMRIID 2'!N143 -> 30811.32 | W28: ='AMRIID 2'!O143 -> 30811.32 | X28: ='AMRIID 2'!P143 -> 30811.32 | Y28: ='AMRIID 2'!Q143 -> 30811.32 | Z28: ='AMRIID 2'!R143 -> 30811.32 | AP28: =SUM(B28:AD28) -> 277301.88 | AQ28: =SUM(F28:Q28) -> 0 | AR28: =SUM(R28:AC28) -> 277301.88
A29: Revenue | N29: ='AMRIID 2'!F173 -> 0 | O29: ='AMRIID 2'!G173 -> 30811.32 | P29: ='AMRIID 2'!H173 -> 30811.32 | Q29: ='AMRIID 2'!I173 -> 30811.32 | R29: ='AMRIID 2'!J173 -> 30811.32 | S29: ='AMRIID 2'!K173 -> 30811.32 | T29: ='AMRIID 2'!L173 -> 30811.32 | U29: ='AMRIID 2'!M173 -> 30811.32 | ... Z29: ='AMRIID 2'!R173 -> 30811.32 | AP29: =SUM(B29:AD29) -> 369735.84 | AQ29: =SUM(F29:Q29) -> 92433.96 | AR29: =SUM(R29:AC29) -> 277301.88
AA30: AMRIID II.1
A31: Forecast Rev | AA31: ='AMRIID 2.1'!G140 -> 31889.44 | AB31: ='AMRIID 2.1'!H140 -> 31889.44 | AC31: ='AMRIID 2.1'!I140 -> 31889.44 | AD31: ='AMRIID 2.1'!J140 -> 31889.44 | AE31: ='AMRIID 2.1'!K140 -> 31889.44 | AF31: ='AMRIID 2.1'!L140 -> 31889.44 | AG31: ='AMRIID 2.1'!M140 -> 31889.44 | AH31: ='AMRIID 2.1'!N140 -> 31889.44 | ... AL31: ='AMRIID 2.1'!R140 -> 31889.44
A32: Revenue | AA32: ='AMRIID 2.1'!G170 -> 31889.44 | AB32: ='AMRIID 2.1'!H170 -> 31889.44 | AC32: ='AMRIID 2.1'!I170 -> 31889.44
B33: AO Call 1 - RAE Support | AP33: All Periods | AQ33: CY2023 | AR33: CY2024
A34: Charged | B34: ='AO Call 1'!E87 -> 43685.84 | C34: ='AO Call 1'!F87 -> 245030.08 | D34: ='AO Call 1'!G87 -> 251775.76 | E34: ='AO Call 1'!H87 -> 238611.17 | F34: ='AO Call 1'!I87 -> 239007.24 | G34: ='AO Call 1'!J87 -> 243722.59 | H34: ='AO Call 1'!K87 -> 310145.34 | I34: ='AO Call 1'!L87 -> 303822.22 | ... M34: ='AO Call 1'!P87 -> 299461.23 | AP34: =SUM(B34:AD34) -> 3083848.8 | AQ34: =SUM(F34:Q34) -> 2304746
A35: Revenue | B35: ='AO Call 1'!E113 -> 32005.84 | C35: ='AO Call 1'!F113 -> 245030.08 | D35: ='AO Call 1'!G113 -> 250935.76 | E35: ='AO Call 1'!H113 -> 238611.17 | F35: ='AO Call 1'!I113 -> 239007.24 | G35: ='AO Call 1'!J113 -> 241981.63 | H35: ='AO Call 1'!K113 -> 310145.3 | I35: ='AO Call 1'!L113 -> 304110.62 | ... M35: ='AO Call 1'!P113 -> 299461.23 | AP35: =SUM(B35:AD35) -> 3069951.5 | AQ35: =SUM(F35:Q35) -> 2303368.6
M36: AO Call 1.2 - RAE Support | AP36: All Periods | AQ36: CY2023 | AR36: CY2024
A37: Charged | M37: ='AO Call 1.2'!E162 -> 64936.92 | N37: ='AO Call 1.2'!F162 -> 320935.74 | O37: ='AO Call 1.2'!G162 -> 310916.13 | P37: ='AO Call 1.2'!H162 -> 271701.47 | Q37: ='AO Call 1.2'!I162 -> 276832.88 | R37: ='AO Call 1.2'!J162 -> 358178.78 | S37: ='AO Call 1.2'!K162 -> 293879.61 | AP37: =SUM(B37:AD37) -> 1897381.5 | AQ37: =SUM(F37:Q37) -> 1245323.1 | AR37: =SUM(R37:AC37) -> 652058.39
A38: Forecast Rev | R38: ='AO Call 1.2'!J119 -> 341375 | S38: ='AO Call 1.2'!K119 -> 293653.84 | AP38: =SUM(B38:AD38) -> 635028.84 | AQ38: =SUM(F38:Q38) -> 0 | AR38: =SUM(R38:AC38) -> 635028.84
A39: Revenue | M39: ='AO Call 1.2'!E188 -> 64936.92 | N39: ='AO Call 1.2'!F188 -> 320935.74 | O39: ='AO Call 1.2'!G188 -> 310916.13 | P39: ='AO Call 1.2'!H188 -> 271701.47 | Q39: ='AO Call 1.2'!I188 -> 276832.88 | R39: ='AO Call 1.2'!J188 -> 358178.78 | S39: ='AO Call 1.2'!K188 -> 293879.61 | AP39: =SUM(B39:AD39) -> 1897381.5 | AQ39: =SUM(F39:Q39) -> 1245323.1 | AR39: =SUM(R39:AC39) -> 652058.39 | AU39: =SUM(R39:AC39) -> 652058.39
M40: AO Call 1.3 - RAE Support | AP40: All Periods | AQ40: CY2023 | AR40: CY2024
A41: Charged | S41: ='AO Call 1.3'!F167 -> 79137.95 | T41: ='AO Call 1.3'!G167 -> 391536.8 | U41: ='AO Call 1.3'!H167 -> 408891.96 | V41: ='AO Call 1.3'!I167 -> 390962.36 | W41: ='AO Call 1.3'!J167 -> 319637.54 | X41: ='AO Call 1.3'!K167 -> 384451.02 | Y41: ='AO Call 1.3'!L167 -> 342094.97 | AP41: =SUM(B41:AD41) -> 2316712.6 | AR41: =SUM(R41:AC41) -> 2316712.6
A42: Forecast Rev | S42: ='AO Call 1.3'!F123 -> 79137.95 | T42: ='AO Call 1.3'!G123 -> 391412.43 | U42: ='AO Call 1.3'!H123 -> 392059.8 | V42: ='AO Call 1.3'!I123 -> 392059.8 | W42: ='AO Call 1.3'!J123 -> 394458.2 | X42: ='AO Call 1.3'!K123 -> 394458.2 | Y42: ='AO Call 1.3'!L123 -> 394458.2 | AP42: =SUM(B42:AD42) -> 2438044.6 | AR42: =SUM(R42:AC42) -> 2438044.6
A43: Revenue | S43: ='AO Call 1.3'!F193 -> 79137.95 | T43: ='AO Call 1.3'!G193 -> 391536.8 | U43: ='AO Call 1.3'!H193 -> 408891.96 | V43: ='AO Call 1.3'!I193 -> 390962.36 | W43: ='AO Call 1.3'!J193 -> 319637.54 | X43: ='AO Call 1.3'!K193 -> 384451.02 | Y43: ='AO Call 1.3'!L193 -> 342094.97 | AP43: =SUM(B43:AD43) -> 2316712.6 | AR43: =SUM(R43:AC43) -> 2316712.6 | AU43: =SUM(R43:AC43) -> 2316712.6
M44: AO Call 1.4 - RAE Support | AP44: All Periods | AQ44: CY2023 | AR44: CY2024
A45: Charged | Y45: ='AO Call 1.4'!E153 -> 109055.93 | Z45: ='AO Call 1.4'!F153 -> 413236.43 | AA45: ='AO Call 1.4'!G153 -> 406062.47 | AB45: ='AO Call 1.4'!H153 -> 349093.92 | AC45: ='AO Call 1.4'!I153 -> 308837.66 | AP45: =SUM(B45:AD45) -> 1586286.4 | AR45: =SUM(R45:AC45) -> 1586286.4
A46: Forecast Rev | Y46: ='AO Call 1.4'!E116 -> 111440.59 | Z46: ='AO Call 1.4'!F116 -> 407925.6 | AA46: ='AO Call 1.4'!G116 -> 407925.6 | AB46: ='AO Call 1.4'!H116 -> 394609.28 | AC46: ='AO Call 1.4'!I116 -> 406251.08 | AD46: 406251.08 | AE46: 406251.08 | AF46: 406251.08 | AG46: 406251.08 | AH46: 406251.08 | AI46: 406251.08 | AJ46: 406251.08 | AK46: 406251.08 | AL46: 406251.08 | AM46: 406251.08 | AN46: 406251.08 | AO46: 406251.08 | AP46: =SUM(B46:AD46) -> 2134403.2 | AR46: =SUM(R46:AC46) -> 1728152.2
A47: Revenue | Y47: ='AO Call 1.4'!#REF! -> #REF! | Z47: ='AO Call 1.4'!#REF! -> #REF! | AA47: ='AO Call 1.4'!#REF! -> #REF! | AB47: ='AO Call 1.4'!#REF! -> #REF! | AC47: ='AO Call 1.4'!#REF! -> #REF! | AP47: =SUM(B47:AD47) -> #REF! | AR47: =SUM(R47:AC47) -> #REF! | AU47: =SUM(R47:AC47) -> #REF!
A48: AO Call 2 - EA Support | AP48: All Periods | AQ48: CY2023 | AR48: CY2024
A49: Charged | B49: ='AO Call 2'!E74 -> 0 | C49: ='AO Call 2'!F74 -> 6938.48 | D49: ='AO Call 2'!G74 -> 53655.88 | E49: ='AO Call 2'!H74 -> 53815.68 | F49: ='AO Call 2'!I74 -> 50471.48 | G49: ='AO Call 2'!J74 -> 52126.9 | H49: ='AO Call 2'!K74 -> 57149.96 | I49: ='AO Call 2'!L74 -> 50036.24 | ... N49: ='AO Call 2'!Q74 -> 92338.56 | AP49: =SUM(B49:AD49) -> 761120.02 | AQ49: =SUM(F49:Q49) -> 646709.98
A50: Forecast Rev | B50: ='AO Call 2'!E74 -> 0 | C50: ='AO Call 2'!F74 -> 6938.48 | D50: ='AO Call 2'!G74 -> 53655.88 | E50: ='AO Call 2'!H74 -> 53815.68 | F50: ='AO Call 2'!I74 -> 50471.48 | G50: ='AO Call 2'!J74 -> 52126.9 | H50: ='AO Call 2'!K74 -> 57149.96 | I50: ='AO Call 2'!L74 -> 50036.24 | ... N50: ='AO Call 2'!Q74 -> 92338.56
A51: Revenue | B51: ='AO Call 2'!E95 -> 0 | C51: ='AO Call 2'!F95 -> 7376.48 | D51: ='AO Call 2'!G95 -> 53655.88 | E51: ='AO Call 2'!H95 -> 53815.68 | F51: ='AO Call 2'!I95 -> 50471.48 | G51: ='AO Call 2'!J95 -> 52017.4 | H51: ='AO Call 2'!K95 -> 57149.96 | I51: ='AO Call 2'!L95 -> 50036.24 | ... N51: ='AO Call 2'!Q95 -> 92338.56 | AP51: =SUM(B51:AD51) -> 761448.52 | AQ51: =SUM(F51:Q51) -> 646600.48 | AU51: =SUM(R51:AC51) -> 0
N52: AO Call 2.1 - EA Support | AP52: All Periods | AQ52: CY2023 | AR52: CY2024
A53: Charged | N53: ='AO Call 2.1'!F137 -> 25827.2 | O53: ='AO Call 2.1'!G137 -> 123617.72 | P53: ='AO Call 2.1'!H137 -> 66503.2 | Q53: ='AO Call 2.1'!I137 -> 87422.08 | R53: ='AO Call 2.1'!J137 -> 126061.92 | S53: ='AO Call 2.1'!K137 -> 128552.24 | T53: ='AO Call 2.1'!L137 -> 123416.8 | U53: ='AO Call 2.1'!M137 -> 131350.48 | ... Z53: ='AO Call 2.1'!R137 -> 87129.76 | AP53: =SUM(B53:AD53) -> 1411026.5 | AQ53: =SUM(F53:Q53) -> 303370.2 | AR53: =SUM(R53:AC53) -> 1107656.3
A54: Forecast Rev | R54: ='AO Call 2.1'!J105 -> 128813.16 | S54: ='AO Call 2.1'!K105 -> 122679.2 | T54: ='AO Call 2.1'!L105 -> 128813.16 | U54: ='AO Call 2.1'!M105 -> 134947.12 | V54: ='AO Call 2.1'!N105 -> 141081.08 | W54: ='AO Call 2.1'!O105 -> 116545.24 | X54: ='AO Call 2.1'!P105 -> 141081.08 | Y54: ='AO Call 2.1'!Q105 -> 134947.12 | Z54: ='AO Call 2.1'!R105 -> 110411.28 | AP54: =SUM(B54:AD54) -> 1159318.4 | AQ54: =SUM(F54:Q54) -> 0 | AR54: =SUM(R54:AC54) -> 1159318.4
A55: Revenue | N55: ='AO Call 2.1'!F158 -> 25827.2 | O55: ='AO Call 2.1'!G158 -> 123617.72 | P55: ='AO Call 2.1'!H158 -> 66503.2 | Q55: ='AO Call 2.1'!I158 -> 87422.08 | R55: ='AO Call 2.1'!J158 -> 126061.92 | S55: ='AO Call 2.1'!K158 -> 128552.24 | T55: ='AO Call 2.1'!L158 -> 123416.8 | U55: ='AO Call 2.1'!M158 -> 131350.48 | ... Z55: ='AO Call 2.1'!R158 -> 87129.76 | AP55: =SUM(B55:AD55) -> 1411026.5 | AQ55: =SUM(F55:Q55) -> 303370.2 | AR55: =SUM(R55:AC55) -> 1107656.3 | AU55: =SUM(R55:AC55) -> 1107656.3
Z56: AO Call 2.2 - EA Support | AP56: All Periods | AQ56: CY2023 | AR56: CY2024
A57: Charged | Z57: ='AO Call 2.2'!F137 -> 16112.4 | AA57: ='AO Call 2.2'!G137 -> 126413.38 | AB57: ='AO Call 2.2'!H137 -> 165787.92 | AC57: ='AO Call 2.2'!I137 -> 244661.44
A58: Forecast Rev | Z58: ='AO Call 2.2'!F104 -> 21483.2 | AA58: ='AO Call 2.2'!G104 -> 209217.6 | AB58: ='AO Call 2.2'!H104 -> 248939.2 | AC58: ='AO Call 2.2'!I104 -> 261904 | AD58: 244966.4 | AE58: 244966.4 | AF58: 244966.4 | AG58: 244966.4 | AH58: 244966.4 | AI58: 244966.4 | AJ58: 244966.4 | AK58: 244966.4 | AL58: 244966.4 | AM58: 244966.4 | AN58: 244966.4 | AO58: 244966.4 | AP58: =SUM(B58:AD58) -> 986510.4 | AQ58: =SUM(F58:Q58) -> 0 | AR58: =SUM(R58:AC58) -> 741544
A59: Revenue | Z59: ='AO Call 2.2'!F159 -> 16112.4 | AA59: ='AO Call 2.2'!G159 -> 126318.02 | AB59: ='AO Call 2.2'!H159 -> 165334.96 | AC59: ='AO Call 2.2'!I159 -> 244160.8 | AP59: =SUM(B59:AD59) -> 551926.18 | AQ59: =SUM(F59:Q59) -> 0 | AR59: =SUM(R59:AC59) -> 551926.18 | AU59: =SUM(R59:AC59) -> 551926.18
A60: AO Call 3 - ICAM | AP60: All Periods | AQ60: CY2023 | AR60: CY2024
A61: Revenue | H61: ='AO Call 3'!F128 -> 0 | I61: ='AO Call 3'!G128 -> 30744.62 | J61: ='AO Call 3'!H128 -> 0 | K61: ='AO Call 3'!I128 -> 238452.3 | L61: ='AO Call 3'!J128 -> 65292.3 | M61: ='AO Call 3'!K128 -> 0 | N61: ='AO Call 3'!L128 -> 0 | O61: ='AO Call 3'!M128 -> 342352.3 | P61: ='AO Call 3'!N128 -> 63372.3 | AP61: =SUM(B61:AD61) -> 740213.82 | AQ61: =SUM(F61:Q61) -> 740213.82 | AU61: =SUM(R61:AC61) -> 0
I62: AO Call 4 - MFA | AP62: All Periods | AQ62: CY2023 | AR62: CY2024
A63: Charged | I63: ='AO Call 4'!F111 -> 0 | J63: ='AO Call 4'!G111 -> 7592 | K63: ='AO Call 4'!H111 -> 24528 | L63: ='AO Call 4'!I111 -> 54312 | M63: ='AO Call 4'!J111 -> 77088 | N63: ='AO Call 4'!K111 -> 67160 | O63: ='AO Call 4'!L111 -> 76045.44 | P63: ='AO Call 4'!M111 -> 82387.2 | ... U63: ='AO Call 4'!R111 -> 20596.8
A64: Forecast Rev | I64: ='AO Call 4'!F111 -> 0 | J64: ='AO Call 4'!G111 -> 7592 | K64: ='AO Call 4'!H111 -> 24528 | L64: ='AO Call 4'!I111 -> 54312 | M64: ='AO Call 4'!J111 -> 77088 | N64: ='AO Call 4'!K111 -> 67160 | O64: ='AO Call 4'!L111 -> 76045.44 | P64: ='AO Call 4'!M111 -> 82387.2 | ... U64: ='AO Call 4'!R111 -> 20596.8 | AP64: =SUM(B64:AD64) -> 738640.34 | AQ64: =SUM(F64:Q64) -> 471499.84 | AR64: =SUM(R64:AC64) -> 267140.5
A65: Revenue | I65: ='AO Call 4'!F165 -> 0 | J65: ='AO Call 4'!G165 -> 7592 | K65: ='AO Call 4'!H165 -> 24528 | L65: ='AO Call 4'!I165 -> 54312 | M65: ='AO Call 4'!J165 -> 77088 | N65: ='AO Call 4'!K165 -> 67160 | O65: ='AO Call 4'!L165 -> 76045.44 | P65: ='AO Call 4'!M165 -> 82387.2 | ... U65: ='AO Call 4'!R165 -> 28835.52 | AP65: =SUM(B65:AD65) -> 755735.68 | AQ65: =SUM(F65:Q65) -> 471499.84 | AR65: =SUM(R65:AC65) -> 284235.84 | AU65: =SUM(R65:AC65) -> 284235.84
U66: AO Call 4.1 - MFA
A67: Charged | U67: ='AO Call 4.1'!E145 -> 61143.36 | V67: ='AO Call 4.1'!F145 -> 88172.96 | W67: ='AO Call 4.1'!G145 -> 90555.68 | X67: ='AO Call 4.1'!H145 -> 113883.2 | Y67: ='AO Call 4.1'!I145 -> 117457.28 | Z67: ='AO Call 4.1'!J145 -> 115010.56 | AA67: ='AO Call 4.1'!K145 -> 160346.24 | AB67: ='AO Call 4.1'!L145 -> 139401.44 | AC67: ='AO Call 4.1'!M145 -> 133316.64
A68: Forecast Rev | U68: ='AO Call 4.1'!E110 -> 61143.36 | V68: ='AO Call 4.1'!F110 -> 88172.96 | W68: ='AO Call 4.1'!G110 -> 90555.68 | X68: ='AO Call 4.1'!H110 -> 113883.2 | Y68: ='AO Call 4.1'!I110 -> 117457.28 | Z68: ='AO Call 4.1'!J110 -> 115010.56 | AA68: ='AO Call 4.1'!K110 -> 160346.24 | AB68: ='AO Call 4.1'!L110 -> 139401.44 | AC68: ='AO Call 4.1'!M110 -> 133316.64 | AD68: 133316.64 | AE68: 133316.64 | AF68: 133316.64 | AG68: 133316.64 | AH68: 133316.64 | AI68: 133316.64 | AJ68: 133316.64 | AK68: 133316.64 | AL68: 133316.64 | AM68: 133316.64 | AN68: 133316.64 | AO68: 133316.64
A69: Revenue | U69: ='AO Call 4.1'!E163 -> 61143.36 | V69: ='AO Call 4.1'!F163 -> 88172.96 | W69: ='AO Call 4.1'!G163 -> 90555.68 | X69: ='AO Call 4.1'!H163 -> 113883.2 | Y69: ='AO Call 4.1'!I163 -> 117457.28 | Z69: ='AO Call 4.1'!J163 -> 115010.56 | AA69: ='AO Call 4.1'!K163 -> 160346.24 | AB69: ='AO Call 4.1'!L163 -> 137401.44 | AC69: ='AO Call 4.1'!M163 -> 133316.64 | AU69: =SUM(R69:AC69) -> 1017287.4
A70: AO Call 5 - Cloud | AP70: All Periods | AQ70: CY2023 | AR70: CY2024
A71: Charged | J71: ='AO Call 5'!F144 -> 16360.4 | K71: ='AO Call 5'!G144 -> 49081.2 | L71: ='AO Call 5'!H144 -> 46744 | M71: ='AO Call 5'!I144 -> 53755.6 | N71: ='AO Call 5'!J144 -> 44405.6 | O71: ='AO Call 5'!K144 -> 43235.2 | P71: ='AO Call 5'!L144 -> 40899.2 | Q71: ='AO Call 5'!M144 -> 44408 | ... U71: ='AO Call 5'!Q144 -> 132093.2 | AP71: =SUM(B71:AD71) -> 687212.4 | AQ71: =SUM(F71:Q71) -> 338889.2 | AR71: =SUM(R71:AC71) -> 348323.2
A72: Forecast Rev | R72: ='AO Call 5'!N109 -> 48847.48 | S72: ='AO Call 5'!O109 -> 155480.8 | T72: ='AO Call 5'!P109 -> 163254.84 | U72: ='AO Call 5'!Q109 -> 186580.38 | AP72: =SUM(B72:AD72) -> 554163.5 | AQ72: =SUM(F72:Q72) -> 0 | AR72: =SUM(R72:AC72) -> 554163.5
A73: Revenue | J73: ='AO Call 5'!F163 -> 16360.4 | K73: ='AO Call 5'!G163 -> 49081.2 | L73: ='AO Call 5'!H163 -> 46744 | M73: ='AO Call 5'!I163 -> 53755.6 | N73: ='AO Call 5'!J163 -> 44405.6 | O73: ='AO Call 5'!K163 -> 43235.2 | P73: ='AO Call 5'!L163 -> 40899.2 | Q73: ='AO Call 5'!M163 -> 44408 | ... U73: ='AO Call 5'!Q163 -> 132093.2 | AP73: =SUM(B73:AD73) -> 687212.4 | AQ73: =SUM(F73:Q73) -> 338889.2 | AR73: =SUM(R73:AC73) -> 348323.2 | AU73: =SUM(R73:AC73) -> 348323.2
V74: AO Call 5.1 - Cloud | AP74: All Periods | AQ74: CY2023 | AR74: CY2024
A75: Charged | V75: ='AO Call 5.1'!E145 -> 134143.84 | W75: ='AO Call 5.1'!F145 -> 129979.84 | X75: ='AO Call 5.1'!G145 -> 158294.8 | Y75: ='AO Call 5.1'!H145 -> 171718.4 | Z75: ='AO Call 5.1'!I145 -> 135935.36 | AA75: ='AO Call 5.1'!J145 -> 146666.56 | AB75: ='AO Call 5.1'!K145 -> 164115.32 | AC75: ='AO Call 5.1'!L145 -> 143998.48 | AP75: =SUM(B75:AD75) -> 1184852.6 | AR75: =SUM(R75:AC75) -> 1184852.6
A76: Forecast Rev | V76: ='AO Call 5.1'!E110 -> 63200.96 | W76: ='AO Call 5.1'!F110 -> 150245.76 | X76: ='AO Call 5.1'!G110 -> 166944 | Y76: ='AO Call 5.1'!H110 -> 191985.6 | Z76: ='AO Call 5.1'!I110 -> 152632.32 | AA76: ='AO Call 5.1'!J110 -> 139512 | AB76: ='AO Call 5.1'!K110 -> 137129.28 | AC76: ='AO Call 5.1'!L110 -> 164561.28 | ... AO76: ='AO Call 5.1'!X110 -> 0 | AP76: =SUM(B76:AD76) -> 1340667.7 | AR76: =SUM(R76:AC76) -> 1166211.2
A77: Revenue | V77: ='AO Call 5.1'!E165 -> 134143.84 | W77: ='AO Call 5.1'!F165 -> 129979.84 | X77: ='AO Call 5.1'!G165 -> 158294.8 | Y77: ='AO Call 5.1'!H165 -> 171718.4 | Z77: ='AO Call 5.1'!I165 -> 135935.36 | AA77: ='AO Call 5.1'!J165 -> 317185.92 | AB77: ='AO Call 5.1'!K165 -> 164115.32 | AC77: ='AO Call 5.1'!L165 -> 143998.48 | AP77: =SUM(B77:AD77) -> 1355372 | AR77: =SUM(R77:AC77) -> 1355372 | AU77: =SUM(R77:AC77) -> 1355372
K78: AO Call 6 - Cloud DevSecOps | AP78: All Periods | AQ78: CY2023 | AR78: CY2024
A79: Charged | K79: ='AO Call 6'!G144 -> 2920 | L79: ='AO Call 6'!H144 -> 40880 | M79: ='AO Call 6'!I144 -> 63081.6 | N79: ='AO Call 6'!J144 -> 88816 | O79: ='AO Call 6'!K144 -> 94658.4 | P79: ='AO Call 6'!L144 -> 93488 | Q79: ='AO Call 6'!M144 -> 80786 | R79: ='AO Call 6'!N144 -> 96993.2 | ... V79: ='AO Call 6'!R144 -> 63115.2 | AP79: =SUM(B79:AD79) -> 886516.8 | AQ79: =SUM(F79:Q79) -> 464630 | AR79: =SUM(R79:AC79) -> 421886.8
A80: Forecast Rev | R80: ='AO Call 6'!N109 -> 97694.96 | S80: ='AO Call 6'!O109 -> 88813.6 | T80: ='AO Call 6'!P109 -> 93254.28 | U80: ='AO Call 6'!Q109 -> 93254.28 | V80: ='AO Call 6'!R109 -> 97694.96 | AP80: =SUM(B80:AD80) -> 470712.08 | AQ80: =SUM(F80:Q80) -> 0 | AR80: =SUM(R80:AC80) -> 470712.08
A81: Revenue | K81: ='AO Call 6'!G163 -> 2920 | L81: ='AO Call 6'!H163 -> 40880 | M81: ='AO Call 6'!I163 -> 63081.6 | N81: ='AO Call 6'!J163 -> 88816 | O81: ='AO Call 6'!K163 -> 94658.4 | P81: ='AO Call 6'!L163 -> 93488 | Q81: ='AO Call 6'!M163 -> 80786 | R81: ='AO Call 6'!N163 -> 96993.2 | ... V81: ='AO Call 6'!R163 -> 63115.2 | AP81: =SUM(B81:AD81) -> 886516.8 | AQ81: =SUM(F81:Q81) -> 464630 | AR81: =SUM(R81:AC81) -> 421886.8 | AU81: =SUM(R81:AC81) -> 421886.8
V82: AO Call 6.1 - Cloud DevSecOps | AP82: All Periods | AQ82: CY2023 | AR82: CY2024
A83: Charged | V83: ='AO Call 6.1'!F145 -> 14306.56 | W83: ='AO Call 6.1'!G145 -> 60806.72 | X83: ='AO Call 6.1'!H145 -> 65570.88 | Y83: ='AO Call 6.1'!I145 -> 50062.72 | Z83: ='AO Call 6.1'!J145 -> 68551.2 | AA83: ='AO Call 6.1'!K145 -> 76451 | AB83: ='AO Call 6.1'!L145 -> 66763.52 | AC83: ='AO Call 6.1'!M145 -> 67960 | AP83: =SUM(B83:AD83) -> 470472.6 | AQ83: =SUM(F83:Q83) -> 0 | AR83: =SUM(R83:AC83) -> 470472.6
A84: Forecast Rev | V84: ='AO Call 6.1'!F110 -> 14306.56 | W84: ='AO Call 6.1'!G110 -> 71532.8 | X84: ='AO Call 6.1'!H110 -> 71532.8 | Y84: ='AO Call 6.1'!I110 -> 71532.8 | Z84: ='AO Call 6.1'!J110 -> 71532.8 | AA84: ='AO Call 6.1'!K110 -> 71532.8 | AB84: ='AO Call 6.1'!L110 -> 71532.8 | AC84: ='AO Call 6.1'!M110 -> 71532.8 | AD84: 71532.8 | AE84: 71532.8 | AF84: 71532.8 | AG84: 71532.8 | AH84: 71532.8 | AI84: 71532.8 | AJ84: 71532.8 | AK84: 71532.8 | AL84: 71532.8 | AM84: 71532.8 | AN84: 71532.8 | AO84: 71532.8 | AP84: =SUM(B84:AD84) -> 586568.96 | AQ84: =SUM(F84:Q84) -> 0 | AR84: =SUM(R84:AC84) -> 515036.16
A85: Revenue | V85: ='AO Call 6.1'!F164 -> 14306.56 | W85: ='AO Call 6.1'!G164 -> 60806.72 | X85: ='AO Call 6.1'!H164 -> 65570.88 | Y85: ='AO Call 6.1'!I164 -> 50062.72 | Z85: ='AO Call 6.1'!J164 -> 68551.2 | AA85: ='AO Call 6.1'!K164 -> 76451 | AB85: ='AO Call 6.1'!L164 -> 66763.52 | AC85: ='AO Call 6.1'!M164 -> 67960 | AP85: =SUM(B85:AD85) -> 470472.6 | AQ85: =SUM(F85:Q85) -> 0 | AR85: =SUM(R85:AC85) -> 470472.6 | AU85: =SUM(R85:AC85) -> 470472.6
T86: AO Call 8 - Governance Board Support | AP86: All Periods | AQ86: CY2023 | AR86: CY2024
A87: Forecast Rev | R87: ='AO Call 8'!E129 -> 0 | S87: ='AO Call 8'!F129 -> 14426.2 | T87: ='AO Call 8'!G129 -> 14426.2 | U87: ='AO Call 8'!H129 -> 14426.2 | V87: ='AO Call 8'!I129 -> 14426.2 | W87: ='AO Call 8'!J129 -> 14426.2 | X87: ='AO Call 8'!K129 -> 14426.2 | Y87: ='AO Call 8'!L129 -> 14426.2 | ... AC87: ='AO Call 8'!P129 -> 14426.2 | AD87: ='AO Call 8'!#REF! -> #REF! | AE87: =142905.6/12 -> 11908.8 | AF87: =142905.6/12 -> 11908.8 | AG87: =142905.6/12 -> 11908.8 | AH87: =142905.6/12 -> 11908.8 | AI87: =142905.6/12 -> 11908.8 | AJ87: =142905.6/12 -> 11908.8 | AK87: =142905.6/12 -> 11908.8 | AL87: =142905.6/12 -> 11908.8 | ... AO87: =142905.6/12 -> 11908.8 | AP87: =SUM(B87:AD87) -> #REF! | AR87: =SUM(R87:AC87) -> 158688.2
A88: Revenue | R88: ='AO Call 8'!E147 -> 0 | S88: ='AO Call 8'!F147 -> 14426.2 | T88: ='AO Call 8'!G147 -> 14426.2 | U88: ='AO Call 8'!H147 -> 14426.2 | V88: ='AO Call 8'!I147 -> 14426.2 | W88: ='AO Call 8'!J147 -> 14426.2 | X88: ='AO Call 8'!K147 -> 14426.2 | Y88: ='AO Call 8'!L147 -> 14426.2 | ... AC88: ='AO Call 8'!P147 -> 14426.2 | AP88: =SUM(B88:AD88) -> 158688.2 | AR88: =SUM(R88:AC88) -> 158688.2 | AU88: =SUM(R88:AC88) -> 158688.2
U89: AO Call 9 - Zero Trust Strategy | AP89: All Periods | AQ89: CY2023 | AR89: CY2024
A90: Forecast Rev | T90: ='AO Call 9'!E129 -> 0 | U90: ='AO Call 9'!F129 -> 129337.34 | V90: ='AO Call 9'!G129 -> 0 | W90: ='AO Call 9'!H129 -> 129478.1 | X90: ='AO Call 9'!I129 -> 290021.45 | Y90: ='AO Call 9'!J129 -> 0 | Z90: ='AO Call 9'!K129 -> 0 | AP90: =SUM(B90:AD90) -> 548836.89 | AR90: =SUM(R90:AC90) -> 548836.89
A91: Revenue | T91: ='AO Call 9'!E147 -> 0 | U91: ='AO Call 9'!F147 -> 129337.34 | V91: ='AO Call 9'!G147 -> 0 | W91: ='AO Call 9'!H147 -> 129478.1 | X91: ='AO Call 9'!I147 -> 290021.45 | Y91: ='AO Call 9'!J147 -> 0 | Z91: ='AO Call 9'!K147 -> 0 | AP91: =SUM(B91:AD91) -> 548836.89 | AR91: =SUM(R91:AC91) -> 548836.89 | AU91: =SUM(R91:AC91) -> 548836.89
U92: AO Call 10 - External File Sharing | AP92: All Periods | AQ92: CY2023 | AR92: CY2024
A93: Charged | T93: ='AO Call 10'!E144 -> 0 | U93: ='AO Call 10'!F144 -> 43005.24 | V93: ='AO Call 10'!G144 -> 60655.32 | W93: ='AO Call 10'!H144 -> 52607.52 | X93: ='AO Call 10'!I144 -> 46813.92 | Y93: ='AO Call 10'!J144 -> 52148.52 | Z93: ='AO Call 10'!K144 -> 18033.6 | AP93: =SUM(B93:AD93) -> 273264.12 | AR93: =SUM(R93:AC93) -> 273264.12
A94: Forecast Rev | T94: ='AO Call 10'!E109 -> 0 | U94: ='AO Call 10'!F109 -> 28315.2 | V94: ='AO Call 10'!G109 -> 56630.4 | W94: ='AO Call 10'!H109 -> 56630.4 | X94: ='AO Call 10'!I109 -> 56630.4 | Y94: ='AO Call 10'!J109 -> 56630.4 | Z94: ='AO Call 10'!K109 -> 56630.4 | AP94: =SUM(B94:AD94) -> 311467.2 | AR94: =SUM(R94:AC94) -> 311467.2
A95: Revenue | T95: ='AO Call 10'!E163 -> 0 | U95: ='AO Call 10'!F163 -> 43005.24 | V95: ='AO Call 10'!G163 -> 60655.32 | W95: ='AO Call 10'!H163 -> 52607.52 | X95: ='AO Call 10'!I163 -> 46813.92 | Y95: ='AO Call 10'!J163 -> 52148.52 | Z95: ='AO Call 10'!K163 -> 18033.6 | AP95: =SUM(B95:AD95) -> 273264.12 | AR95: =SUM(R95:AC95) -> 273264.12 | AU95: =SUM(R95:AC95) -> 273264.12
Z96: AO Call 10.1 - External File Sharing | AP96: All Periods | AQ96: CY2023 | AR96: CY2024
A97: Charged | Z97: ='AO Call 10.1'!E144 -> 35618.4 | AA97: ='AO Call 10.1'!F144 -> 54996.36 | AB97: ='AO Call 10.1'!G144 -> 35736.72 | AC97: ='AO Call 10.1'!H144 -> 33129.6 | AD97: ='AO Call 10.1'!I144 -> 21909.6 | AP97: =SUM(B97:AD97) -> 181390.68 | AR97: =SUM(R97:AC97) -> 159481.08
A98: Forecast Rev | Z98: ='AO Call 10.1'!E109 -> 0 | AA98: ='AO Call 10.1'!F109 -> 28315.2 | AB98: ='AO Call 10.1'!G109 -> 48062.4 | AC98: ='AO Call 10.1'!H109 -> 39494.4 | AD98: ='AO Call 10.1'!I109 -> 39494.4 | AP98: =SUM(B98:AD98) -> 155366.4 | AR98: =SUM(R98:AC98) -> 115872
A99: Revenue | Z99: ='AO Call 10.1'!E163 -> 35618.4 | AA99: ='AO Call 10.1'!F163 -> 54996.36 | AB99: ='AO Call 10.1'!G163 -> 35736.72 | AC99: ='AO Call 10.1'!H163 -> 33129.6 | AD99: ='AO Call 10.1'!I163 -> 21909.6 | AP99: =SUM(B99:AD99) -> 181390.68 | AR99: =SUM(R99:AC99) -> 159481.08 | AU99: =SUM(R99:AC99) -> 159481.08
Y100: AO Call 11 - Strategic Portfolio Management
...

Sheet AMRIID 2.1
A2: Project: | B2: USAMRIID
A3: PoP: | B3: 9/30/24 - 9/29/25
A4: Funded Ceiling: | B4: 382673.28
A6: Hours Forecast | F6: Hours
F7: 2024 | J7: 2025
D8: Working Days | F8: 1 | G8: 21 | H8: 20 | I8: 20 | J8: 21 | K8: 20 | L8: 21 | M8: 22 | N8: 23 | O8: 19 | P8: 23 | Q8: 22 | R8: 20
A9: Name | B9: Company | C9: LCAT | D9: Rate | F9: 9 | G9: 10 | H9: 11 | I9: 12 | J9: 1 | K9: 2 | L9: 3 | M9: 4 | N9: 5 | O9: 6 | P9: 7 | Q9: 8 | R9: 9 | S9: Total Hrs CTD | T9: Total Hrs | U9: Rev CTD | V9: Total Rev
A10: Craig Park | B10: TechSur | C10: Program Manager III | D10: 200.61 | S10: =SUM(F10:M10) -> 0 | T10: =SUM(F10:R10) -> 0 | U10: =S10*D10 -> 0 | V10: =SUM(T10*D10) -> 0
A11: Paul Schomburg | B11: TechSur | C11: Program Manager III | D11: 200.61 | F11: 0 | G11: 1 | H11: 1 | I11: 3 | S11: =SUM(F11:M11) -> 5 | T11: =SUM(F11:R11) -> 5 | U11: =S11*D11 -> 1003.05 | V11: =SUM(T11*D11) -> 1003.05
A12: Jonathan Cohodas | B12: TechSur | C12: Data Analyst | D12: 121.78 | F12: 160 | G12: 160 | H12: 160 | I12: 160 | J12: 160 | K12: 160 | L12: 160 | M12: 160 | N12: 160 | O12: 160 | P12: 160 | Q12: 160 | R12: 160 | S12: =SUM(F12:K12) -> 960 | T12: =SUM(F12:R12) -> 2080 | U12: =S12*D12 -> 116908.8 | V12: =SUM(T12*D12) -> 253302.4
S13: =SUM(F13:K13) -> 0 | T13: =SUM(F13:R13) -> 0 | U13: =S13*D13 -> 0 | V13: =SUM(T13*D13) -> 0
S14: =SUM(F14:K14) -> 0 | T14: =SUM(F14:R14) -> 0 | U14: =S14*D14 -> 0 | V14: =SUM(T14*D14) -> 0
S15: =SUM(F15:K15) -> 0 | T15: =SUM(F15:R15) -> 0 | U15: =S15*D15 -> 0 | V15: =SUM(T15*D15) -> 0
S16: =SUM(F16:K16) -> 0 | T16: =SUM(F16:R16) -> 0 | U16: =S16*D16 -> 0 | V16: =SUM(T16*D16) -> 0
S17: =SUM(F17:K17) -> 0 | T17: =SUM(F17:R17) -> 0 | U17: =S17*D17 -> 0 | V17: =SUM(T17*D17) -> 0
S18: =SUM(F18:K18) -> 0 | T18: =SUM(F18:R18) -> 0 | U18: =S18*D18 -> 0 | V18: =SUM(T18*D18) -> 0
S19: =SUM(F19:K19) -> 0 | T19: =SUM(F19:R19) -> 0 | U19: =S19*D19 -> 0 | V19: =SUM(T19*D19) -> 0
S20: =SUM(F20:K20) -> 0 | T20: =SUM(F20:R20) -> 0 | U20: =S20*D20 -> 0 | V20: =SUM(T20*D20) -> 0
S21: =SUM(F21:K21) -> 0 | T21: =SUM(F21:R21) -> 0 | U21: =S21*D21 -> 0 | V21: =SUM(T21*D21) -> 0
S22: =SUM(F22:K22) -> 0 | T22: =SUM(F22:R22) -> 0 | U22: =S22*D22 -> 0 | V22: =SUM(T22*D22) -> 0
S23: =SUM(F23:K23) -> 0 | T23: =SUM(F23:R23) -> 0 | U23: =S23*D23 -> 0 | V23: =SUM(T23*D23) -> 0
S24: =SUM(F24:K24) -> 0 | T24: =SUM(F24:R24) -> 0 | U24: =S24*D24 -> 0 | V24: =SUM(T24*D24) -> 0
... S38: =SUM(F38:K38) -> 0 | T38: =SUM(F38:R38) -> 0 | U38: =S38*D38 -> 0 | V38: =SUM(T38*D38) -> 0
F39: =SUM(F10:F38) -> 160 | G39: =SUM(G10:G38) -> 161 | H39: =SUM(H10:H38) -> 161 | I39: =SUM(I10:I38) -> 163 | J39: =SUM(J10:J38) -> 160 | K39: =SUM(K10:K38) -> 160 | L39: =SUM(L10:L38) -> 160 | M39: =SUM(M10:M38) -> 160 | ... V39: =SUM(V10:V38) -> 254305.45
A41: Hours Actual | F41: Hours
F42: 2024 | J42: 2025
A43: Name | B43: Company | C43: LCAT | D43: Rate | F43: 9 | G43: 10 | H43: 11 | I43: 12 | J43: 1 | K43: 2 | L43: 3 | M43: 4 | N43: 5 | O43: 6 | P43: 7 | Q43: 8 | R43: 9 | S43: Total Hrs CTD | T43: Total Hrs | U43: Rev CTD | V43: Total Rev
A44: Craig Park | B44: TechSur | C44: Program Manager III | D44: 200.61 | S44: =SUM(F44:M44) -> 0 | T44: =SUM(F44:R44) -> 0 | U44: =S44*D44 -> 0 | V44: =SUM(T44*D44) -> 0
A45: Paul Schomburg | B45: TechSur | C45: Program Manager III | D45: 200.61 | F45: 0 | G45: 0 | H45: 1 | I45: 3 | J45: 4 | N45: 4 | O45: 2 | Q45: 1 | S45: =SUM(F45:M45) -> 8 | T45: =SUM(F45:R45) -> 15 | U45: =S45*D45 -> 1604.88 | V45: =SUM(T45*D45) -> 3009.15
A46: Jonathan Cohodas | B46: TechSur | C46: Data Analyst | D46: 121.78 | F46: 160 | G46: 128 | H46: 160 | I46: 160 | J46: 160 | K46: 160 | L46: 160 | M46: 160 | N46: 156 | O46: 152 | P46: 160 | Q46: 136 | R46: 160 | S46: =SUM(F46:K46) -> 928 | T46: =SUM(F46:R46) -> 2012 | U46: =S46*D46 -> 113011.84 | V46: =SUM(T46*D46) -> 245021.36
S47: =SUM(F47:K47) -> 0 | T47: =SUM(F47:R47) -> 0 | U47: =S47*D47 -> 0 | V47: =SUM(T47*D47) -> 0
S48: =SUM(F48:K48) -> 0 | T48: =SUM(F48:R48) -> 0 | U48: =S48*D48 -> 0 | V48: =SUM(T48*D48) -> 0
S49: =SUM(F49:K49) -> 0 | T49: =SUM(F49:R49) -> 0 | U49: =S49*D49 -> 0 | V49: =SUM(T49*D49) -> 0
S50: =SUM(F50:K50) -> 0 | T50: =SUM(F50:R50) -> 0 | U50: =S50*D50 -> 0 | V50: =SUM(T50*D50) -> 0
S51: =SUM(F51:K51) -> 0 | T51: =SUM(F51:R51) -> 0 | U51: =S51*D51 -> 0 | V51: =SUM(T51*D51) -> 0
S52: =SUM(F52:K52) -> 0 | T52: =SUM(F52:R52) -> 0 | U52: =S52*D52 -> 0 | V52: =SUM(T52*D52) -> 0
S53: =SUM(F53:K53) -> 0 | T53: =SUM(F53:R53) -> 0 | U53: =S53*D53 -> 0 | V53: =SUM(T53*D53) -> 0
S54: =SUM(F54:K54) -> 0 | T54: =SUM(F54:R54) -> 0 | U54: =S54*D54 -> 0 | V54: =SUM(T54*D54) -> 0
S55: =SUM(F55:K55) -> 0 | T55: =SUM(F55:R55) -> 0 | U55: =S55*D55 -> 0 | V55: =SUM(T55*D55) -> 0
S56: =SUM(F56:K56) -> 0 | T56: =SUM(F56:R56) -> 0 | U56: =S56*D56 -> 0 | V56: =SUM(T56*D56) -> 0
S57: =SUM(F57:K57) -> 0 | T57: =SUM(F57:R57) -> 0 | U57: =S57*D57 -> 0 | V57: =SUM(T57*D57) -> 0
S58: =SUM(F58:K58) -> 0 | T58: =SUM(F58:R58) -> 0 | U58: =S58*D58 -> 0 | V58: =SUM(T58*D58) -> 0
... S72: =SUM(F72:K72) -> 0 | T72: =SUM(F72:R72) -> 0 | U72: =S72*D72 -> 0 | V72: =SUM(T72*D72) -> 0
F73: =SUM(F44:F72) -> 160 | G73: =SUM(G44:G72) -> 128 | H73: =SUM(H44:H72) -> 161 | I73: =SUM(I44:I72) -> 163 | J73: =SUM(J44:J72) -> 164 | K73: =SUM(K44:K72) -> 160 | L73: =SUM(L44:L72) -> 160 | M73: =SUM(M44:M72) -> 160 | ... V73: =SUM(V44:V72) -> 248030.51
A75: Revenue by Resource | F75: Hours
F76: 2024 | J76: 2025
A77: Name | B77: Company | C77: LCAT | D77: Rate | F77: 9 | G77: 10 | H77: 11 | I77: 12 | J77: 1 | K77: 2 | L77: 3 | M77: 4 | N77: 5 | O77: 6 | P77: 7 | Q77: 8 | R77: 9
F108: =SUM(F78:F107) -> 0 | G108: =SUM(G78:G107) -> 0 | H108: =SUM(H78:H107) -> 0 | I108: =SUM(I78:I107) -> 0 | J108: =SUM(J78:J107) -> 0 | K108: =SUM(K78:K107) -> 0 | L108: =SUM(L78:L107) -> 0 | M108: =SUM(M78:M107) -> 0 | ... R108: =SUM(R78:R107) -> 0
A112: Forecast Revenue | F112: 2024 | J112: 2025
C113: Invoice | D113: Date | F113: 9 | G113: 10 | H113: 11 | I113: 12 | J113: 1 | K113: 2 | L113: 3 | M113: 4 | N113: 5 | O113: 6 | P113: 7 | Q113: 8 | R113: 9
C114: Sept
C115: Sept Travel
C116: Oct | G116: =$B$4/12 -> 31889.44
C117: Oct Travel
C118: Nov | H118: =$B$4/12 -> 31889.44
C119: Nov Travel
C120: Dec | I120: =$B$4/12 -> 31889.44
C121: Dec Travel
C122: Jan | J122: =$B$4/12 -> 31889.44
C123: Jan Travel
C124: Feb | K124: =$B$4/12 -> 31889.44
C125: Feb Travel
C126: Mar | L126: =$B$4/12 -> 31889.44
C127: Mar Travel
C128: Apr | M128: =$B$4/12 -> 31889.44
C129: Apr Travel
C130: May | N130: =$B$4/12 -> 31889.44
C131: May Travel
C132: Jun | O132: =$B$4/12 -> 31889.44
C133: Jun Travel
C134: Jul | P134: =$B$4/12 -> 31889.44
C135: Jul Travel
C136: Aug | Q136: =$B$4/12 -> 31889.44
C137: Aug Travel
C138: Sept | R138: =$B$4/12 -> 31889.44
C139: Sept Travel
D140: Revenue | F140: =SUM(F114:F126) -> 0 | G140: =SUM(G114:G139) -> 31889.44 | H140: =SUM(H114:H139) -> 31889.44 | I140: =SUM(I114:I139) -> 31889.44 | J140: =SUM(J114:J139) -> 31889.44 | K140: =SUM(K114:K139) -> 31889.44 | L140: =SUM(L114:L139) -> 31889.44 | M140: =SUM(M114:M139) -> 31889.44 | N140: =SUM(N114:N139) -> 31889.44 | ... R140: =SUM(R114:R139) -> 31889.44
A142: Actual Revenue | F142: 2024 | J142: 2025
C143: Invoice | D143: Date | F143: 9 | G143: 10 | H143: 11 | I143: 12 | J143: 1 | K143: 2 | L143: 3 | M143: 4 | N143: 5 | O143: 6 | P143: 7 | Q143: 8 | R143: 9
C144: Sept
C145: Sept Travel
C146: Oct | G146: 31889.44
C147: Oct Travel
C148: Nov | H148: 31889.44
C149: Nov Travel
C150: Dec | I150: 31889.44
C151: Dec Travel
C152: Jan | J152: 31889.44
C153: Jan Travel
C154: Feb | K154: 31889.44
C155: Feb Travel
C156: Mar | L156: 31889.44
C157: Mar Travel
C158: Apr | M158: 31889.44
C159: Apr Travel
C160: May | N160: 31889.44
C161: May Travel
C162: Jun | O162: 31889.44
C163: Jun Travel
C164: Jul
...

Sheet DHS FLETF
A2: Project: | B2: DHS FLETF
A3: PoP: | B3: 9/30/24 - 9/29/25
A4: Funded Ceiling: | B4: 1457551
A6: Hours Forecast
E7: 2024 | J7: 2025
A8: Name | B8: Company | C8: LCAT | D8: Rate | E8: 8 | F8: 9 | G8: 10 | H8: 11 | I8: 12 | J8: 1 | K8: 2 | L8: 3 | M8: 4 | N8: 5 | O8: 6 | P8: 7 | Q8: 8 | R8: Total Hrs | S8: Rev CTD | T8: Total Rev
A9: Jour OR Analyst Rptg T1 | C9: Senior Consultant II | D9: 134 | G9: 66.666667 | H9: 66.666667 | I9: 66.666667 | J9: 66.666667 | K9: 66.666667 | L9: 66.666667 | M9: 66.666667 | N9: 66.666667 | O9: 66.666667 | P9: 66.666667 | Q9: 66.666667 | R9: =SUM(E9:I9) -> 200 | S9: =Q9*D9 -> 8933.3333 | T9: =SUM(R9*D9) -> 26800
A10: Sr Ops Research Anly T1 | C10: Consulting Manager II | D10: 151.28 | G10: 8.3333333 | H10: 8.3333333 | I10: 8.3333333 | J10: 8.3333333 | K10: 8.3333333 | L10: 8.3333333 | M10: 8.3333333 | N10: 8.3333333 | O10: 8.3333333 | P10: 8.3333333 | Q10: 8.3333333 | R10: =SUM(F10:J10) -> 33.333333 | S10: =Q10*B10 -> 0 | T10: =SUM(R10*B10) -> 0
A11: Jour OR Analyst Rptg T1 | C11: Consultant II | D11: 130 | G11: 308.33333 | H11: 308.33333 | I11: 308.33333 | J11: 308.33333 | K11: 308.33333 | L11: 308.33333 | M11: 308.33333 | N11: 308.33333 | O11: 308.33333 | P11: 308.33333 | Q11: 308.33333 | R11: =SUM(F11:I11) -> 925 | S11: =Q11*B11 -> 0 | T11: =SUM(R11*B11) -> 0
A12: Journ Bus Ops Grp 2 T5 | C12: Senior Consultant II | D12: 144.3 | G12: 154.16667 | H12: 154.16667 | I12: 154.16667 | J12: 154.16667 | K12: 154.16667 | L12: 154.16667 | M12: 154.16667 | N12: 154.16667 | O12: 154.16667 | P12: 154.16667 | Q12: 154.16667 | R12: =SUM(F12:I12) -> 462.5 | S12: =Q12*B12 -> 0 | T12: =SUM(R12*B12) -> 0
A13: Tec Spec Journ ORA T1 | C13: Senior Consultant I | D13: 139 | G13: 320 | H13: 320 | I13: 320 | J13: 320 | K13: 320 | L13: 320 | M13: 320 | N13: 320 | O13: 320 | P13: 320 | Q13: 320
A14: Senior Manager | C14: Director I | D14: 196 | G14: 22.75 | H14: 22.75 | I14: 22.75 | J14: 22.75 | K14: 22.75 | L14: 22.75 | M14: 22.75 | N14: 22.75 | O14: 22.75 | P14: 22.75 | Q14: 22.75
R17: =SUM(E17:I17) -> 0 | S17: =Q17*D17 -> 0 | T17: =SUM(R17*D17) -> 0
R18: =SUM(E18:I18) -> 0 | S18: =Q18*D18 -> 0 | T18: =SUM(R18*D18) -> 0
R19: =SUM(E19:I19) -> 0 | S19: =Q19*D19 -> 0 | T19: =SUM(R19*D19) -> 0
R20: =SUM(E20:I20) -> 0 | S20: =Q20*D20 -> 0 | T20: =SUM(R20*D20) -> 0
R21: =SUM(E21:I21) -> 0 | S21: =Q21*D21 -> 0 | T21: =SUM(R21*D21) -> 0
R22: =SUM(E22:I22) -> 0 | S22: =Q22*D22 -> 0 | T22: =SUM(R22*D22) -> 0
R23: =SUM(E23:I23) -> 0 | S23: =Q23*D23 -> 0 | T23: =SUM(R23*D23) -> 0
R24: =SUM(E24:I24) -> 0 | S24: =Q24*D24 -> 0 | T24: =SUM(R24*D24) -> 0
R25: =SUM(E25:I25) -> 0 | S25: =Q25*D25 -> 0 | T25: =SUM(R25*D25) -> 0
R26: =SUM(E26:I26) -> 0 | S26: =Q26*D26 -> 0 | T26: =SUM(R26*D26) -> 0
R27: =SUM(E27:I27) -> 0 | S27: =Q27*D27 -> 0 | T27: =SUM(R27*D27) -> 0
R28: =SUM(E28:I28) -> 0 | S28: =Q28*D28 -> 0 | T28: =SUM(R28*D28) -> 0
... R38: =SUM(E38:I38) -> 0 | S38: =Q38*D38 -> 0 | T38: =SUM(R38*D38) -> 0
E39: =SUM(E9:E38) -> 0 | F39: =SUM(F9:F38) -> 0 | G39: =SUM(G9:G38) -> 880.25 | H39: =SUM(H9:H38) -> 880.25 | I39: =SUM(I9:I38) -> 880.25 | J39: =SUM(J9:J38) -> 880.25 | K39: =SUM(K9:K38) -> 880.25 | L39: =SUM(L9:L38) -> 880.25 | ... T39: =SUM(T9:T38) -> 26800
A41: Hours Actual
E42: 2024 | J42: 2025
A43: Name | B43: Company | C43: LCAT | D43: Rate | E43: 8 | F43: 9 | G43: 10 | H43: 11 | I43: 12 | J43: 1 | K43: 2 | L43: 3 | M43: 4 | N43: 5 | O43: 6 | P43: 7 | Q43: Total Hrs CTD | R43: Total Hrs | S43: Rev CTD | T43: Total Rev
A44: =A9 -> Jour OR Analyst Rptg T1 | B44: =B9 -> 0 | C44: =C9 -> Senior Consultant II | D44: =D9 -> 134 | R44: =SUM(E44:I44) -> 0 | S44: =Q44*D44 -> 0 | T44: =SUM(R44*D44) -> 0
A45: =A10 -> Sr Ops Research Anly T1 | B45: =B10 -> 0 | C45: =C10 -> Consulting Manager II | D45: =D10 -> 151.28 | R45: =SUM(E45:I45) -> 0 | S45: =Q45*D45 -> 0 | T45: =SUM(R45*D45) -> 0
A46: =A11 -> Jour OR Analyst Rptg T1 | B46: =B11 -> 0 | C46: =C11 -> Consultant II | D46: =D11 -> 130 | R46: =SUM(E46:I46) -> 0 | S46: =Q46*D46 -> 0 | T46: =SUM(R46*D46) -> 0
A47: =A12 -> Journ Bus Ops Grp 2 T5 | B47: =B12 -> 0 | C47: =C12 -> Senior Consultant II | D47: =D12 -> 144.3 | R47: =SUM(E47:I47) -> 0 | S47: =Q47*D47 -> 0 | T47: =SUM(R47*D47) -> 0
A48: =A13 -> Tec Spec Journ ORA T1 | B48: =B13 -> 0 | C48: =C13 -> Senior Consultant I | D48: =D13 -> 139
A49: =A14 -> Senior Manager | B49: =B14 -> 0 | C49: =C14 -> Director I | D49: =D14 -> 196
A50: =A15 -> 0 | B50: =B15 -> 0 | C50: =C15 -> 0 | D50: =D15 -> 0
A51: =A16 -> 0 | B51: =B16 -> 0 | C51: =C16 -> 0 | D51: =D16 -> 0
A52: =A17 -> 0 | B52: =B17 -> 0 | C52: =C17 -> 0 | D52: =D17 -> 0 | R52: =SUM(E52:I52) -> 0 | S52: =Q52*D52 -> 0 | T52: =SUM(R52*D52) -> 0
A53: =A18 -> 0 | B53: =B18 -> 0 | C53: =C18 -> 0 | D53: =D18 -> 0 | R53: =SUM(E53:I53) -> 0 | S53: =Q53*D53 -> 0 | T53: =SUM(R53*D53) -> 0
A54: =A19 -> 0 | B54: =B19 -> 0 | C54: =C19 -> 0 | D54: =D19 -> 0 | R54: =SUM(E54:I54) -> 0 | S54: =Q54*D54 -> 0 | T54: =SUM(R54*D54) -> 0
A55: =A20 -> 0 | B55: =B20 -> 0 | C55: =C20 -> 0 | D55: =D20 -> 0 | R55: =SUM(E55:I55) -> 0 | S55: =Q55*D55 -> 0 | T55: =SUM(R55*D55) -> 0
A56: =A21 -> 0 | B56: =B21 -> 0 | C56: =C21 -> 0 | D56: =D21 -> 0 | R56: =SUM(E56:I56) -> 0 | S56: =Q56*D56 -> 0 | T56: =SUM(R56*D56) -> 0
A57: =A22 -> 0 | B57: =B22 -> 0 | C57: =C22 -> 0 | D57: =D22 -> 0 | R57: =SUM(E57:I57) -> 0 | S57: =Q57*D57 -> 0 | T57: =SUM(R57*D57) -> 0
A58: =A23 -> 0 | B58: =B23 -> 0 | C58: =C23 -> 0 | D58: =D23 -> 0 | R58: =SUM(E58:I58) -> 0 | S58: =Q58*D58 -> 0 | T58: =SUM(R58*D58) -> 0
R59: =SUM(E59:I59) -> 0 | S59: =Q59*D59 -> 0 | T59: =SUM(R59*D59) -> 0
R60: =SUM(E60:I60) -> 0 | S60: =Q60*D60 -> 0 | T60: =SUM(R60*D60) -> 0
R61: =SUM(E61:I61) -> 0 | S61: =Q61*D61 -> 0 | T61: =SUM(R61*D61) -> 0
R62: =SUM(E62:I62) -> 0 | S62: =Q62*D62 -> 0 | T62: =SUM(R62*D62) -> 0
R63: =SUM(E63:I63) -> 0 | S63: =Q63*D63 -> 0 | T63: =SUM(R63*D63) -> 0
R64: =SUM(E64:I64) -> 0 | S64: =Q64*D64 -> 0 | T64: =SUM(R64*D64) -> 0
R65: =SUM(E65:I65) -> 0 | S65: =Q65*D65 -> 0 | T65: =SUM(R65*D65) -> 0
R66: =SUM(E66:I66) -> 0 | S66: =Q66*D66 -> 0 | T66: =SUM(R66*D66) -> 0
R67: =SUM(E67:I67) -> 0 | S67: =Q67*D67 -> 0 | T67: =SUM(R67*D67) -> 0
R68: =SUM(E68:I68) -> 0 | S68: =Q68*D68 -> 0 | T68: =SUM(R68*D68) -> 0
R69: =SUM(E69:I69) -> 0 | S69: =Q69*D69 -> 0 | T69: =SUM(R69*D69) -> 0
R70: =SUM(E70:I70) -> 0 | S70: =Q70*D70 -> 0 | T70: =SUM(R70*D70) -> 0
... R73: =SUM(E73:I73) -> 0 | S73: =Q73*D73 -> 0 | T73: =SUM(R73*D73) -> 0
E74: =SUM(E44:E73) -> 0 | F74: =SUM(F44:F73) -> 0 | G74: =SUM(G44:G73) -> 0 | H74: =SUM(H44:H73) -> 0 | I74: =SUM(I44:I73) -> 0 | J74: =SUM(J44:J73) -> 0 | K74: =SUM(K44:K73) -> 0 | L74: =SUM(L44:L73) -> 0 | ... T74: =SUM(T44:T73) -> 0
A76: Forecast Revenue by Resource
E77: 2024 | J77: 2025
A78: Name | B78: Company | C78: LCAT | D78: Rate | E78: 8 | F78: 9 | G78: 10 | H78: 11 | I78: 12 | J78: 1 | K78: 2 | L78: 3 | M78: 4 | N78: 5 | O78: 6 | P78: 7
A79: =A9 -> Jour OR Analyst Rptg T1 | B79: =B9 -> 0 | C79: =C9 -> Senior Consultant II | D79: =D9 -> 134 | E79: =E9*$D9 -> 0 | F79: =F9*$D9 -> 0 | G79: =G9*$D9 -> 8933.3333 | H79: =H9*$D9 -> 8933.3333 | I79: =I9*$D9 -> 8933.3333 | J79: =J9*$D9 -> 8933.3333 | K79: =K9*$D9 -> 8933.3333 | L79: =L9*$D9 -> 8933.3333 | ... P79: =P9*$D9 -> 8933.3333
A80: =A10 -> Sr Ops Research Anly T1 | B80: =B10 -> 0 | C80: =C10 -> Consulting Manager II | D80: =D10 -> 151.28 | E80: =E10*$D10 -> 0 | F80: =F10*$D10 -> 0 | G80: =G10*$D10 -> 1260.6667 | H80: =H10*$D10 -> 1260.6667 | I80: =I10*$D10 -> 1260.6667 | J80: =J10*$D10 -> 1260.6667 | K80: =K10*$D10 -> 1260.6667 | L80: =L10*$D10 -> 1260.6667 | ... P80: =P10*$D10 -> 1260.6667
A81: =A11 -> Jour OR Analyst Rptg T1 | B81: =B11 -> 0 | C81: =C11 -> Consultant II | D81: =D11 -> 130 | E81: =E11*$D11 -> 0 | F81: =F11*$D11 -> 0 | G81: =G11*$D11 -> 40083.333 | H81: =H11*$D11 -> 40083.333 | I81: =I11*$D11 -> 40083.333 | J81: =J11*$D11 -> 40083.333 | K81: =K11*$D11 -> 40083.333 | L81: =L11*$D11 -> 40083.333 | ... P81: =P11*$D11 -> 40083.333
A82: =A12 -> Journ Bus Ops Grp 2 T5 | B82: =B12 -> 0 | C82: =C12 -> Senior Consultant II | D82: =D12 -> 144.3 | E82: =E12*$D12 -> 0 | F82: =F12*$D12 -> 0 | G82: =G12*$D12 -> 22246.25 | H82: =H12*$D12 -> 22246.25 | I82: =I12*$D12 -> 22246.25 | J82: =J12*$D12 -> 22246.25 | K82: =K12*$D12 -> 22246.25 | L82: =L12*$D12 -> 22246.25 | ... P82: =P12*$D12 -> 22246.25
A83: =A13 -> Tec Spec Journ ORA T1 | B83: =B13 -> 0 | C83: =C13 -> Senior Consultant I | D83: =D13 -> 139 | E83: =E13*$D13 -> 0 | F83: =F13*$D13 -> 0 | G83: =G13*$D13 -> 44480 | H83: =H13*$D13 -> 44480 | I83: =I13*$D13 -> 44480 | J83: =J13*$D13 -> 44480 | K83: =K13*$D13 -> 44480 | L83: =L13*$D13 -> 44480 | ... P83: =P13*$D13 -> 44480
A84: =A14 -> Senior Manager | B84: =B14 -> 0 | C84: =C14 -> Director I | D84: =D14 -> 196 | E84: =E14*$D14 -> 0 | F84: =F14*$D14 -> 0 | G84: =G14*$D14 -> 4459 | H84: =H14*$D14 -> 4459 | I84: =I14*$D14 -> 4459 | J84: =J14*$D14 -> 4459 | K84: =K14*$D14 -> 4459 | L84: =L14*$D14 -> 4459 | ... P84: =P14*$D14 -> 4459
A85: =A15 -> 0 | B85: =B15 -> 0 | C85: =C15 -> 0 | D85: =D15 -> 0 | E85: =E15*$D15 -> 0 | F85: =F15*$D15 -> 0 | G85: =G15*$D15 -> 0 | H85: =H15*$D15 -> 0 | I85: =I15*$D15 -> 0 | J85: =J15*$D15 -> 0 | K85: =K15*$D15 -> 0 | L85: =L15*$D15 -> 0 | ... P85: =P15*$D15 -> 0
A86: =A16 -> 0 | B86: =B16 -> 0 | C86: =C16 -> 0 | D86: =D16 -> 0 | E86: =E16*$D16 -> 0 | F86: =F16*$D16 -> 0 | G86: =G16*$D16 -> 0 | H86: =H16*$D16 -> 0 | I86: =I16*$D16 -> 0 | J86: =J16*$D16 -> 0 | K86: =K16*$D16 -> 0 | L86: =L16*$D16 -> 0 | ... P86: =P16*$D16 -> 0
A87: =A17 -> 0 | B87: =B17 -> 0 | C87: =C17 -> 0 | D87: =D17 -> 0 | E87: =E17*$D17 -> 0 | F87: =F17*$D17 -> 0 | G87: =G17*$D17 -> 0 | H87: =H17*$D17 -> 0 | I87: =I17*$D17 -> 0 | J87: =J17*$D17 -> 0 | K87: =K17*$D17 -> 0 | L87: =L17*$D17 -> 0 | ... P87: =P17*$D17 -> 0
A88: =A18 -> 0 | B88: =B18 -> 0 | C88: =C18 -> 0 | D88: =D18 -> 0 | E88: =E18*$D18 -> 0 | F88: =F18*$D18 -> 0 | G88: =G18*$D18 -> 0 | H88: =H18*$D18 -> 0 | I88: =I18*$D18 -> 0 | J88: =J18*$D18 -> 0 | K88: =K18*$D18 -> 0 | L88: =L18*$D18 -> 0 | ... P88: =P18*$D18 -> 0
A89: =A19 -> 0 | B89: =B19 -> 0 | C89: =C19 -> 0 | D89: =D19 -> 0 | E89: =E19*$D19 -> 0 | F89: =F19*$D19 -> 0 | G89: =G19*$D19 -> 0 | H89: =H19*$D19 -> 0 | I89: =I19*$D19 -> 0 | J89: =J19*$D19 -> 0 | K89: =K19*$D19 -> 0 | L89: =L19*$D19 -> 0 | ... P89: =P19*$D19 -> 0
A90: =A20 -> 0 | B90: =B20 -> 0 | C90: =C20 -> 0 | D90: =D20 -> 0 | E90: =E20*$D20 -> 0 | F90: =F20*$D20 -> 0 | G90: =G20*$D20 -> 0 | H90: =H20*$D20 -> 0 | I90: =I20*$D20 -> 0 | J90: =J20*$D20 -> 0 | K90: =K20*$D20 -> 0 | L90: =L20*$D20 -> 0 | ... P90: =P20*$D20 -> 0
... A92: =A22 -> 0 | B92: =B22 -> 0 | C92: =C22 -> 0 | D92: =D22 -> 0 | E92: =E22*$D22 -> 0 | F92: =F22*$D22 -> 0 | G92: =G22*$D22 -> 0 | H92: =H22*$D22 -> 0 | I92: =I22*$D22 -> 0 | J92: =J22*$D22 -> 0 | K92: =K22*$D22 -> 0 | L92: =L22*$D22 -> 0 | ... P92: =P22*$D22 -> 0
E109: =SUM(E79:E108) -> 0 | F109: =SUM(F79:F108) -> 0 | G109: =SUM(G79:G108) -> 121462.58 | H109: =SUM(H79:H108) -> 121462.58 | I109: =SUM(I79:I108) -> 121462.58 | J109: =SUM(J79:J108) -> 121462.58 | K109: =SUM(K79:K108) -> 121462.58 | L109: =SUM(L79:L108) -> 121462.58 | ... P109: =SUM(P79:P108) -> 121462.58
A111: T&M Revenue by Resource
E112: 2024 | J112: 2025
A113: Name | B113: Company | C113: LCAT | D113: Rate | E113: 8 | F113: 9 | G113: 10 | H113: 11 | I113: 12 | J113: 1 | K113: 2 | L113: 3 | M113: 4 | N113: 5 | O113: 6 | P113: 7
A114: =A9 -> Jour OR Analyst Rptg T1 | B114: =B9 -> 0 | C114: =C9 -> Senior Consultant II | D114: =D9 -> 134 | E114: =$D114*E44 -> 0 | F114: =$D114*F44 -> 0 | G114: =$D114*G44 -> 0 | H114: =$D114*H44 -> 0 | I114: =$D114*I44 -> 0 | J114: =$D114*J44 -> 0 | K114: =$D114*K44 -> 0 | L114: =$D114*L44 -> 0 | ... P114: =$D114*P44 -> 0
A115: =A10 -> Sr Ops Research Anly T1 | B115: =B10 -> 0 | C115: =C10 -> Consulting Manager II | D115: =D10 -> 151.28 | E115: =$D115*E45 -> 0 | F115: =$D115*F45 -> 0 | G115: =$D115*G45 -> 0 | H115: =$D115*H45 -> 0 | I115: =$D115*I45 -> 0 | J115: =$D115*J45 -> 0 | K115: =$D115*K45 -> 0 | L115: =$D115*L45 -> 0 | ... P115: =$D115*P45 -> 0
A116: =A11 -> Jour OR Analyst Rptg T1 | B116: =B11 -> 0 | C116: =C11 -> Consultant II | D116: =D11 -> 130 | E116: =$D116*E46 -> 0 | F116: =$D116*F46 -> 0 | G116: =$D116*G46 -> 0 | H116: =$D116*H46 -> 0 | I116: =$D116*I46 -> 0 | J116: =$D116*J46 -> 0 | K116: =$D116*K46 -> 0 | L116: =$D116*L46 -> 0 | ... P116: =$D116*P46 -> 0
A117: =A12 -> Journ Bus Ops Grp 2 T5 | B117: =B12 -> 0 | C117: =C12 -> Senior Consultant II | D117: =D12 -> 144.3 | E117: =$D117*E47 -> 0 | F117: =$D117*F47 -> 0 | G117: =$D117*G47 -> 0 | H117: =$D117*H47 -> 0 | I117: =$D117*I47 -> 0 | J117: =$D117*J47 -> 0 | K117: =$D117*K47 -> 0 | L117: =$D117*L47 -> 0 | ... P117: =$D117*P47 -> 0
A118: =A13 -> Tec Spec Journ ORA T1 | B118: =B13 -> 0 | C118: =C13 -> Senior Consultant I | D118: =D13 -> 139 | E118: =$D118*E48 -> 0 | F118: =$D118*F48 -> 0 | G118: =$D118*G48 -> 0 | H118: =$D118*H48 -> 0 | I118: =$D118*I48 -> 0 | J118: =$D118*J48 -> 0 | K118: =$D118*K48 -> 0 | L118: =$D118*L48 -> 0 | ... P118: =$D118*P48 -> 0
A119: =A14 -> Senior Manager | B119: =B14 -> 0 | C119: =C14 -> Director I | D119: =D14 -> 196 | E119: =$D119*E49 -> 0 | F119: =$D119*F49 -> 0 | G119: =$D119*G49 -> 0 | H119: =$D119*H49 -> 0 | I119: =$D119*I49 -> 0 | J119: =$D119*J49 -> 0 | K119: =$D119*K49 -> 0 | L119: =$D119*L49 -> 0 | ... P119: =$D119*P49 -> 0
A120: =A15 -> 0 | B120: =B15 -> 0 | C120: =C15 -> 0 | D120: =D15 -> 0 | E120: =$D120*E50 -> 0 | F120: =$D120*F50 -> 0 | G120: =$D120*G50 -> 0 | H120: =$D120*H50 -> 0 | I120: =$D120*I50 -> 0 | J120: =$D120*J50 -> 0 | K120: =$D120*K50 -> 0 | L120: =$D120*L50 -> 0 | ... P120: =$D120*P50 -> 0
A121: =A16 -> 0 | B121: =B16 -> 0 | C121: =C16 -> 0 | D121: =D16 -> 0 | E121: =$D121*E51 -> 0 | F121: =$D121*F51 -> 0 | G121: =$D121*G51 -> 0 | H121: =$D121*H51 -> 0 | I121: =$D121*I51 -> 0 | J121: =$D121*J51 -> 0 | K121: =$D121*K51 -> 0 | L121: =$D121*L51 -> 0 | ... P121: =$D121*P51 -> 0
A122: =A17 -> 0 | B122: =B17 -> 0 | C122: =C17 -> 0 | D122: =D17 -> 0 | E122: =$D122*E52 -> 0 | F122: =$D122*F52 -> 0 | G122: =$D122*G52 -> 0 | H122: =$D122*H52 -> 0 | I122: =$D122*I52 -> 0 | J122: =$D122*J52 -> 0 | K122: =$D122*K52 -> 0 | L122: =$D122*L52 -> 0 | ... P122: =$D122*P52 -> 0
A123: =A18 -> 0 | B123: =B18 -> 0 | C123: =C18 -> 0 | D123: =D18 -> 0 | E123: =$D123*E53 -> 0 | F123: =$D123*F53 -> 0 | G123: =$D123*G53 -> 0 | H123: =$D123*H53 -> 0 | I123: =$D123*I53 -> 0 | J123: =$D123*J53 -> 0 | K123: =$D123*K53 -> 0 | L123: =$D123*L53 -> 0 | ... P123: =$D123*P53 -> 0
A124: =A19 -> 0 | B124: =B19 -> 0 | C124: =C19 -> 0 | D124: =D19 -> 0 | E124: =$D124*E54 -> 0 | F124: =$D124*F54 -> 0 | G124: =$D124*G54 -> 0 | H124: =$D124*H54 -> 0 | I124: =$D124*I54 -> 0 | J124: =$D124*J54 -> 0 | K124: =$D124*K54 -> 0 | L124: =$D124*L54 -> 0 | ... P124: =$D124*P54 -> 0
A125: =A20 -> 0 | B125: =B20 -> 0 | C125: =C20 -> 0 | D125: =D20 -> 0 | E125: =$D125*E55 -> 0 | F125: =$D125*F55 -> 0 | G125: =$D125*G55 -> 0 | H125: =$D125*H55 -> 0 | I125: =$D125*I55 -> 0 | J125: =$D125*J55 -> 0 | K125: =$D125*K55 -> 0 | L125: =$D125*L55 -> 0 | ... P125: =$D125*P55 -> 0
... A136: =A31 -> 0 | B136: =B31 -> 0 | C136: =C31 -> 0 | D136: =D31 -> 0 | E136: =$D136*E66 -> 0 | F136: =$D136*F66 -> 0 | G136: =$D136*G66 -> 0 | H136: =$D136*H66 -> 0 | I136: =$D136*I66 -> 0 | J136: =$D136*J66 -> 0 | K136: =$D136*K66 -> 0 | L136: =$D136*L66 -> 0 | ... P136: =$D136*P66 -> 0
E144: =SUM(E114:E143) -> 0 | F144: =SUM(F114:F143) -> 0 | G144: =SUM(G114:G143) -> 0 | H144: =SUM(H114:H143) -> 0 | I144: =SUM(I114:I143) -> 0 | J144: =SUM(J114:J143) -> 0 | K144: =SUM(K114:K143) -> 0 | L144: =SUM(L114:L143) -> 0 | ... P144: =SUM(P114:P143) -> 0
A146: Projected Revenue | E146: 2024 | J146: 2025
C147: Invoice | D147: Date | E147: 8 | F147: 9 | G147: 10 | H147: 11 | I147: 12 | J147: 1 | K147: 2 | L147: 3 | M147: 4 | N147: 5 | O147: 6 | P147: 7 | Q147: Total
E148: =E109 -> 0 | F148: =F109 -> 0 | G148: =G109 -> 121462.58 | H148: =H109 -> 121462.58 | I148: =I109 -> 121462.58 | J148: =J109 -> 121462.58 | K148: =K109 -> 121462.58 | L148: =L109 -> 121462.58 | ... P148: =P109 -> 121462.58 | Q148: =SUM(E148:P148) -> 1214625.8
Q149: =SUM(E149:P149) -> 0
Q150: =SUM(E150:P150) -> 0
Q151: =SUM(E151:P151) -> 0
Q152: =SUM(E152:P152) -> 0
Q153: =SUM(E153:P153) -> 0
...

Sheet DOT CTS
A2: Project: | B2: DOT CTS
A3: PoP: | B3: 9/30/24 - 9/30/25
A4: Funded Ceiling: | B4: 399999.96 | C4: =B4/12 -> 33333.33
A6: Hours Forecast
E7: 2024 | J7: 2025
A8: Name | B8: Company | C8: LCAT | D8: Rate | E8: 8 | F8: 9 | G8: 10 | H8: 11 | I8: 12 | J8: 1 | K8: 2 | L8: 3 | M8: 4 | N8: 5 | O8: 6 | P8: 7 | Q8: 8 | R8: Total Hrs | S8: Rev CTD | T8: Total Rev
R9: =SUM(E9:I9) -> 0 | S9: =Q9*D9 -> 0 | T9: =SUM(R9*D9) -> 0
R10: =SUM(E10:J10) -> 0 | S10: =Q10*D10 -> 0 | T10: =SUM(R10*D10) -> 0
R11: =SUM(E11:I11) -> 0 | S11: =Q11*D11 -> 0 | T11: =SUM(R11*D11) -> 0
R12: =SUM(E12:I12) -> 0 | S12: =Q12*D12 -> 0 | T12: =SUM(R12*D12) -> 0
R17: =SUM(E17:I17) -> 0 | S17: =Q17*D17 -> 0 | T17: =SUM(R17*D17) -> 0
R18: =SUM(E18:I18) -> 0 | S18: =Q18*D18 -> 0 | T18: =SUM(R18*D18) -> 0
R19: =SUM(E19:I19) -> 0 | S19: =Q19*D19 -> 0 | T19: =SUM(R19*D19) -> 0
R20: =SUM(E20:I20) -> 0 | S20: =Q20*D20 -> 0 | T20: =SUM(R20*D20) -> 0
R21: =SUM(E21:I21) -> 0 | S21: =Q21*D21 -> 0 | T21: =SUM(R21*D21) -> 0
R22: =SUM(E22:I22) -> 0 | S22: =Q22*D22 -> 0 | T22: =SUM(R22*D22) -> 0
R23: =SUM(E23:I23) -> 0 | S23: =Q23*D23 -> 0 | T23: =SUM(R23*D23) -> 0
R24: =SUM(E24:I24) -> 0 | S24: =Q24*D24 -> 0 | T24: =SUM(R24*D24) -> 0
R25: =SUM(E25:I25) -> 0 | S25: =Q25*D25 -> 0 | T25: =SUM(R25*D25) -> 0
R26: =SUM(E26:I26) -> 0 | S26: =Q26*D26 -> 0 | T26: =SUM(R26*D26) -> 0
... R38: =SUM(E38:I38) -> 0 | S38: =Q38*D38 -> 0 | T38: =SUM(R38*D38) -> 0
E39: =SUM(E9:E38) -> 0 | F39: =SUM(F9:F38) -> 0 | G39: =SUM(G9:G38) -> 0 | H39: =SUM(H9:H38) -> 0 | I39: =SUM(I9:I38) -> 0 | J39: =SUM(J9:J38) -> 0 | K39: =SUM(K9:K38) -> 0 | L39: =SUM(L9:L38) -> 0 | ... T39: =SUM(T9:T38) -> 0
A41: Hours Actual
E42: 2024 | J42: 2025
A43: Name | B43: Company | C43: LCAT | D43: Rate | E43: 8 | F43: 9 | G43: 10 | H43: 11 | I43: 12 | J43: 1 | K43: 2 | L43: 3 | M43: 4 | N43: 5 | O43: 6 | P43: 7 | Q43: Total Hrs CTD | R43: Total Hrs | S43: Rev CTD | T43: Total Rev
A44: =A9 -> 0 | B44: =B9 -> 0 | C44: =C9 -> 0 | D44: =D9 -> 0 | R44: =SUM(E44:I44) -> 0 | S44: =Q44*D44 -> 0 | T44: =SUM(R44*D44) -> 0
A45: =A10 -> 0 | B45: =B10 -> 0 | C45: =C10 -> 0 | D45: =D10 -> 0 | R45: =SUM(E45:I45) -> 0 | S45: =Q45*D45 -> 0 | T45: =SUM(R45*D45) -> 0
A46: =A11 -> 0 | B46: =B11 -> 0 | C46: =C11 -> 0 | D46: =D11 -> 0 | R46: =SUM(E46:I46) -> 0 | S46: =Q46*D46 -> 0 | T46: =SUM(R46*D46) -> 0
A47: =A12 -> 0 | B47: =B12 -> 0 | C47: =C12 -> 0 | D47: =D12 -> 0 | R47: =SUM(E47:I47) -> 0 | S47: =Q47*D47 -> 0 | T47: =SUM(R47*D47) -> 0
A48: =A13 -> 0 | B48: =B13 -> 0 | C48: =C13 -> 0 | D48: =D13 -> 0
A49: =A14 -> 0 | B49: =B14 -> 0 | C49: =C14 -> 0 | D49: =D14 -> 0
A50: =A15 -> 0 | B50: =B15 -> 0 | C50: =C15 -> 0 | D50: =D15 -> 0
A51: =A16 -> 0 | B51: =B16 -> 0 | C51: =C16 -> 0 | D51: =D16 -> 0
A52: =A17 -> 0 | B52: =B17 -> 0 | C52: =C17 -> 0 | D52: =D17 -> 0 | R52: =SUM(E52:I52) -> 0 | S52: =Q52*D52 -> 0 | T52: =SUM(R52*D52) -> 0
A53: =A18 -> 0 | B53: =B18 -> 0 | C53: =C18 -> 0 | D53: =D18 -> 0 | R53: =SUM(E53:I53) -> 0 | S53: =Q53*D53 -> 0 | T53: =SUM(R53*D53) -> 0
A54: =A19 -> 0 | B54: =B19 -> 0 | C54: =C19 -> 0 | D54: =D19 -> 0 | R54: =SUM(E54:I54) -> 0 | S54: =Q54*D54 -> 0 | T54: =SUM(R54*D54) -> 0
A55: =A20 -> 0 | B55: =B20 -> 0 | C55: =C20 -> 0 | D55: =D20 -> 0 | R55: =SUM(E55:I55) -> 0 | S55: =Q55*D55 -> 0 | T55: =SUM(R55*D55) -> 0
A56: =A21 -> 0 | B56: =B21 -> 0 | C56: =C21 -> 0 | D56: =D21 -> 0 | R56: =SUM(E56:I56) -> 0 | S56: =Q56*D56 -> 0 | T56: =SUM(R56*D56) -> 0
A57: =A22 -> 0 | B57: =B22 -> 0 | C57: =C22 -> 0 | D57: =D22 -> 0 | R57: =SUM(E57:I57) -> 0 | S57: =Q57*D57 -> 0 | T57: =SUM(R57*D57) -> 0
A58: =A23 -> 0 | B58: =B23 -> 0 | C58: =C23 -> 0 | D58: =D23 -> 0 | R58: =SUM(E58:I58) -> 0 | S58: =Q58*D58 -> 0 | T58: =SUM(R58*D58) -> 0
R59: =SUM(E59:I59) -> 0 | S59: =Q59*D59 -> 0 | T59: =SUM(R59*D59) -> 0
R60: =SUM(E60:I60) -> 0 | S60: =Q60*D60 -> 0 | T60: =SUM(R60*D60) -> 0
R61: =SUM(E61:I61) -> 0 | S61: =Q61*D61 -> 0 | T61: =SUM(R61*D61) -> 0
R62: =SUM(E62:I62) -> 0 | S62: =Q62*D62 -> 0 | T62: =SUM(R62*D62) -> 0
R63: =SUM(E63:I63) -> 0 | S63: =Q63*D63 -> 0 | T63: =SUM(R63*D63) -> 0
R64: =SUM(E64:I64) -> 0 | S64: =Q64*D64 -> 0 | T64: =SUM(R64*D64) -> 0
R65: =SUM(E65:I65) -> 0 | S65: =Q65*D65 -> 0 | T65: =SUM(R65*D65) -> 0
R66: =SUM(E66:I66) -> 0 | S66: =Q66*D66 -> 0 | T66: =SUM(R66*D66) -> 0
R67: =SUM(E67:I67) -> 0 | S67: =Q67*D67 -> 0 | T67: =SUM(R67*D67) -> 0
R68: =SUM(E68:I68) -> 0 | S68: =Q68*D68 -> 0 | T68: =SUM(R68*D68) -> 0
R69: =SUM(E69:I69) -> 0 | S69: =Q69*D69 -> 0 | T69: =SUM(R69*D69) -> 0
R70: =SUM(E70:I70) -> 0 | S70: =Q70*D70 -> 0 | T70: =SUM(R70*D70) -> 0
... R73: =SUM(E73:I73) -> 0 | S73: =Q73*D73 -> 0 | T73: =SUM(R73*D73) -> 0
E74: =SUM(E44:E73) -> 0 | F74: =SUM(F44:F73) -> 0 | G74: =SUM(G44:G73) -> 0 | H74: =SUM(H44:H73) -> 0 | I74: =SUM(I44:I73) -> 0 | J74: =SUM(J44:J73) -> 0 | K74: =SUM(K44:K73) -> 0 | L74: =SUM(L44:L73) -> 0 | ... T74: =SUM(T44:T73) -> 0
A76: Forecast Revenue by Resource
E77: 2024 | J77: 2025
A78: Name | B78: Company | C78: LCAT | D78: Rate | E78: 8 | F78: 9 | G78: 10 | H78: 11 | I78: 12 | J78: 1 | K78: 2 | L78: 3 | M78: 4 | N78: 5 | O78: 6 | P78: 7
A79: =A9 -> 0 | B79: =B9 -> 0 | C79: =C9 -> 0 | D79: =D9 -> 0 | E79: =E9*$D9 -> 0 | F79: =F9*$D9 -> 0 | G79: =G9*$D9 -> 0 | H79: =H9*$D9 -> 0 | I79: =I9*$D9 -> 0 | J79: =J9*$D9 -> 0 | K79: =K9*$D9 -> 0 | L79: =L9*$D9 -> 0 | ... P79: =P9*$D9 -> 0
A80: =A10 -> 0 | B80: =B10 -> 0 | C80: =C10 -> 0 | D80: =D10 -> 0 | E80: =E10*$D10 -> 0 | F80: =F10*$D10 -> 0 | G80: =G10*$D10 -> 0 | H80: =H10*$D10 -> 0 | I80: =I10*$D10 -> 0 | J80: =J10*$D10 -> 0 | K80: =K10*$D10 -> 0 | L80: =L10*$D10 -> 0 | ... P80: =P10*$D10 -> 0
A81: =A11 -> 0 | B81: =B11 -> 0 | C81: =C11 -> 0 | D81: =D11 -> 0 | E81: =E11*$D11 -> 0 | F81: =F11*$D11 -> 0 | G81: =G11*$D11 -> 0 | H81: =H11*$D11 -> 0 | I81: =I11*$D11 -> 0 | J81: =J11*$D11 -> 0 | K81: =K11*$D11 -> 0 | L81: =L11*$D11 -> 0 | ... P81: =P11*$D11 -> 0
A82: =A12 -> 0 | B82: =B12 -> 0 | C82: =C12 -> 0 | D82: =D12 -> 0 | E82: =E12*$D12 -> 0 | F82: =F12*$D12 -> 0 | G82: =G12*$D12 -> 0 | H82: =H12*$D12 -> 0 | I82: =I12*$D12 -> 0 | J82: =J12*$D12 -> 0 | K82: =K12*$D12 -> 0 | L82: =L12*$D12 -> 0 | ... P82: =P12*$D12 -> 0
A83: =A13 -> 0 | B83: =B13 -> 0 | C83: =C13 -> 0 | D83: =D13 -> 0 | E83: =E13*$D13 -> 0 | F83: =F13*$D13 -> 0 | G83: =G13*$D13 -> 0 | H83: =H13*$D13 -> 0 | I83: =I13*$D13 -> 0 | J83: =J13*$D13 -> 0 | K83: =K13*$D13 -> 0 | L83: =L13*$D13 -> 0 | ... P83: =P13*$D13 -> 0
A84: =A14 -> 0 | B84: =B14 -> 0 | C84: =C14 -> 0 | D84: =D14 -> 0 | E84: =E14*$D14 -> 0 | F84: =F14*$D14 -> 0 | G84: =G14*$D14 -> 0 | H84: =H14*$D14 -> 0 | I84: =I14*$D14 -> 0 | J84: =J14*$D14 -> 0 | K84: =K14*$D14 -> 0 | L84: =L14*$D14 -> 0 | ... P84: =P14*$D14 -> 0
A85: =A15 -> 0 | B85: =B15 -> 0 | C85: =C15 -> 0 | D85: =D15 -> 0 | E85: =E15*$D15 -> 0 | F85: =F15*$D15 -> 0 | G85: =G15*$D15 -> 0 | H85: =H15*$D15 -> 0 | I85: =I15*$D15 -> 0 | J85: =J15*$D15 -> 0 | K85: =K15*$D15 -> 0 | L85: =L15*$D15 -> 0 | ... P85: =P15*$D15 -> 0
A86: =A16 -> 0 | B86: =B16 -> 0 | C86: =C16 -> 0 | D86: =D16 -> 0 | E86: =E16*$D16 -> 0 | F86: =F16*$D16 -> 0 | G86: =G16*$D16 -> 0 | H86: =H16*$D16 -> 0 | I86: =I16*$D16 -> 0 | J86: =J16*$D16 -> 0 | K86: =K16*$D16 -> 0 | L86: =L16*$D16 -> 0 | ... P86: =P16*$D16 -> 0
A87: =A17 -> 0 | B87: =B17 -> 0 | C87: =C17 -> 0 | D87: =D17 -> 0
A88: =A18 -> 0 | B88: =B18 -> 0 | C88: =C18 -> 0 | D88: =D18 -> 0
A89: =A19 -> 0 | B89: =B19 -> 0 | C89: =C19 -> 0 | D89: =D19 -> 0
A90: =A20 -> 0 | B90: =B20 -> 0 | C90: =C20 -> 0 | D90: =D20 -> 0
A91: =A21 -> 0 | B91: =B21 -> 0 | C91: =C21 -> 0 | D91: =D21 -> 0
A92: =A22 -> 0 | B92: =B22 -> 0 | C92: =C22 -> 0 | D92: =D22 -> 0
E109: =SUM(E79:E108) -> 0 | F109: =SUM(F79:F108) -> 0 | G109: =SUM(G79:G108) -> 0 | H109: =SUM(H79:H108) -> 0 | I109: =SUM(I79:I108) -> 0 | J109: =SUM(J79:J108) -> 0 | K109: =SUM(K79:K108) -> 0 | L109: =SUM(L79:L108) -> 0 | ... P109: =SUM(P79:P108) -> 0
A111: T&M Revenue by Resource
E112: 2024 | J112: 2025
A113: Name | B113: Company | C113: LCAT | D113: Rate | E113: 8 | F113: 9 | G113: 10 | H113: 11 | I113: 12 | J113: 1 | K113: 2 | L113: 3 | M113: 4 | N113: 5 | O113: 6 | P113: 7
A114: =A9 -> 0 | B114: =B9 -> 0 | C114: =C9 -> 0 | D114: =D9 -> 0 | E114: =$D114*E44 -> 0 | F114: =$D114*F44 -> 0 | G114: =$D114*G44 -> 0 | H114: =$D114*H44 -> 0 | I114: =$D114*I44 -> 0 | J114: =$D114*J44 -> 0 | K114: =$D114*K44 -> 0 | L114: =$D114*L44 -> 0 | ... P114: =$D114*P44 -> 0
A115: =A10 -> 0 | B115: =B10 -> 0 | C115: =C10 -> 0 | D115: =D10 -> 0 | E115: =$D115*E45 -> 0 | F115: =$D115*F45 -> 0 | G115: =$D115*G45 -> 0 | H115: =$D115*H45 -> 0 | I115: =$D115*I45 -> 0 | J115: =$D115*J45 -> 0 | K115: =$D115*K45 -> 0 | L115: =$D115*L45 -> 0 | ... P115: =$D115*P45 -> 0
A116: =A11 -> 0 | B116: =B11 -> 0 | C116: =C11 -> 0 | D116: =D11 -> 0 | E116: =$D116*E46 -> 0 | F116: =$D116*F46 -> 0 | G116: =$D116*G46 -> 0 | H116: =$D116*H46 -> 0 | I116: =$D116*I46 -> 0 | J116: =$D116*J46 -> 0 | K116: =$D116*K46 -> 0 | L116: =$D116*L46 -> 0 | ... P116: =$D116*P46 -> 0
A117: =A12 -> 0 | B117: =B12 -> 0 | C117: =C12 -> 0 | D117: =D12 -> 0 | E117: =$D117*E47 -> 0 | F117: =$D117*F47 -> 0 | G117: =$D117*G47 -> 0 | H117: =$D117*H47 -> 0 | I117: =$D117*I47 -> 0 | J117: =$D117*J47 -> 0 | K117: =$D117*K47 -> 0 | L117: =$D117*L47 -> 0 | ... P117: =$D117*P47 -> 0
A118: =A13 -> 0 | B118: =B13 -> 0 | C118: =C13 -> 0 | D118: =D13 -> 0 | E118: =$D118*E48 -> 0 | F118: =$D118*F48 -> 0 | G118: =$D118*G48 -> 0 | H118: =$D118*H48 -> 0 | I118: =$D118*I48 -> 0 | J118: =$D118*J48 -> 0 | K118: =$D118*K48 -> 0 | L118: =$D118*L48 -> 0 | ... P118: =$D118*P48 -> 0
A119: =A14 -> 0 | B119: =B14 -> 0 | C119: =C14 -> 0 | D119: =D14 -> 0 | E119: =$D119*E49 -> 0 | F119: =$D119*F49 -> 0 | G119: =$D119*G49 -> 0 | H119: =$D119*H49 -> 0 | I119: =$D119*I49 -> 0 | J119: =$D119*J49 -> 0 | K119: =$D119*K49 -> 0 | L119: =$D119*L49 -> 0 | ... P119: =$D119*P49 -> 0
A120: =A15 -> 0 | B120: =B15 -> 0 | C120: =C15 -> 0 | D120: =D15 -> 0 | E120: =$D120*E50 -> 0 | F120: =$D120*F50 -> 0 | G120: =$D120*G50 -> 0 | H120: =$D120*H50 -> 0 | I120: =$D120*I50 -> 0 | J120: =$D120*J50 -> 0 | K120: =$D120*K50 -> 0 | L120: =$D120*L50 -> 0 | ... P120: =$D120*P50 -> 0
A121: =A16 -> 0 | B121: =B16 -> 0 | C121: =C16 -> 0 | D121: =D16 -> 0 | E121: =$D121*E51 -> 0 | F121: =$D121*F51 -> 0 | G121: =$D121*G51 -> 0 | H121: =$D121*H51 -> 0 | I121: =$D121*I51 -> 0 | J121: =$D121*J51 -> 0 | K121: =$D121*K51 -> 0 | L121: =$D121*L51 -> 0 | ... P121: =$D121*P51 -> 0
A122: =A17 -> 0 | B122: =B17 -> 0 | C122: =C17 -> 0 | D122: =D17 -> 0 | E122: =$D122*E52 -> 0 | F122: =$D122*F52 -> 0 | G122: =$D122*G52 -> 0 | H122: =$D122*H52 -> 0 | I122: =$D122*I52 -> 0 | J122: =$D122*J52 -> 0 | K122: =$D122*K52 -> 0 | L122: =$D122*L52 -> 0 | ... P122: =$D122*P52 -> 0
A123: =A18 -> 0 | B123: =B18 -> 0 | C123: =C18 -> 0 | D123: =D18 -> 0 | E123: =$D123*E53 -> 0 | F123: =$D123*F53 -> 0 | G123: =$D123*G53 -> 0 | H123: =$D123*H53 -> 0 | I123: =$D123*I53 -> 0 | J123: =$D123*J53 -> 0 | K123: =$D123*K53 -> 0 | L123: =$D123*L53 -> 0 | ... P123: =$D123*P53 -> 0
A124: =A19 -> 0 | B124: =B19 -> 0 | C124: =C19 -> 0 | D124: =D19 -> 0 | E124: =$D124*E54 -> 0 | F124: =$D124*F54 -> 0 | G124: =$D124*G54 -> 0 | H124: =$D124*H54 -> 0 | I124: =$D124*I54 -> 0 | J124: =$D124*J54 -> 0 | K124: =$D124*K54 -> 0 | L124: =$D124*L54 -> 0 | ... P124: =$D124*P54 -> 0
A125: =A20 -> 0 | B125: =B20 -> 0 | C125: =C20 -> 0 | D125: =D20 -> 0 | E125: =$D125*E55 -> 0 | F125: =$D125*F55 -> 0 | G125: =$D125*G55 -> 0 | H125: =$D125*H55 -> 0 | I125: =$D125*I55 -> 0 | J125: =$D125*J55 -> 0 | K125: =$D125*K55 -> 0 | L125: =$D125*L55 -> 0 | ... P125: =$D125*P55 -> 0
... A136: =A31 -> 0 | B136: =B31 -> 0 | C136: =C31 -> 0 | D136: =D31 -> 0 | E136: =$D136*E66 -> 0 | F136: =$D136*F66 -> 0 | G136: =$D136*G66 -> 0 | H136: =$D136*H66 -> 0 | I136: =$D136*I66 -> 0 | J136: =$D136*J66 -> 0 | K136: =$D136*K66 -> 0 | L136: =$D136*L66 -> 0 | ... P136: =$D136*P66 -> 0
E144: =SUM(E114:E143) -> 0 | F144: =SUM(F114:F143) -> 0 | G144: =SUM(G114:G143) -> 0 | H144: =SUM(H114:H143) -> 0 | I144: =SUM(I114:I143) -> 0 | J144: =SUM(J114:J143) -> 0 | K144: =SUM(K114:K143) -> 0 | L144: =SUM(L114:L143) -> 0 | ... P144: =SUM(P114:P143) -> 0
A146: Forecast Revenue | E146: 2024 | J146: 2025
C147: Invoice | D147: Date | E147: 8 | F147: 9 | G147: 10 | H147: 11 | I147: 12 | J147: 1 | K147: 2 | L147: 3 | M147: 4 | N147: 5 | O147: 6 | P147: 7 | Q147: Total
Q148: =SUM(E148:P148) -> 0
Q149: =SUM(E149:P149) -> 0
Q150: =SUM(E150:P150) -> 0
Q151: =SUM(E151:P151) -> 0
Q152: =SUM(E152:P152) -> 0
Q153: =SUM(E153:P153) -> 0
Q154: =SUM(E154:P154) -> 0
Q155: =SUM(E155:P155) -> 0
Q156: =SUM(E156:P156) -> 0
...

Sheet AO Call 2.3
A2: Project: | B2: Call 2 - EA Support
A3: PoP: | B3: 9/26/25 - 9/25/26
A4: Funded Ceiling: | B4: 3225811.7
A6: Hours Forecast
F7: 2025 | J7: 2026 | V7: 2027
D8: Working Days | F8: 4 | G8: 21 | H8: 20 | I8: 20 | J8: 21 | K8: 20 | L8: 21 | M8: 22 | N8: 23 | O8: 19 | P8: 23 | Q8: 22 | R8: 18 | S8: 20 | T8: 20 | U8: 20 | V8: 21 | W8: 20 | X8: 21 | Y8: 22 | Z8: 23 | AA8: 19 | AB8: 23 | AC8: 22 | AD8: 18 | AE8: 20 | AF8: 20 | AG8: 20
A9: Name | B9: Company | C9: LCAT | D9: Rate | F9: 9 | G9: 10 | H9: 11 | I9: 12 | J9: 1 | K9: 2 | L9: 3 | M9: 4 | N9: 5 | O9: 6 | P9: 7 | Q9: 8 | R9: 9 | S9: 10 | T9: 11 | U9: 12 | V9: 1 | W9: 2 | X9: 3 | Y9: 4 | Z9: 5 | AA9: 6 | AB9: 7 | AC9: 8 | AD9: 9 | AE9: 10 | AF9: 11 | AG9: 12
A10: Abdelhaq, Haneen | B10: TechSur | C10: Project Manager | D10: 81.63 | F10: 32 | G10: 160 | I10: 160 | J10: 160 | K10: 160 | L10: 160 | M10: =M$8*8 -> 176 | N10: =N$8*8 -> 184 | O10: =O$8*8 -> 152 | P10: =P$8*8 -> 184 | Q10: =Q$8*8 -> 176 | R10: =R$8*8 -> 144 | S10: =($S$8-1)*8 -> 152 | T10: =($S$8-1)*8 -> 152 | U10: =($S$8-1)*8 -> 152 | V10: =($S$8-1)*8 -> 152 | W10: =($S$8-1)*8 -> 152 | X10: =($S$8-1)*8 -> 152 | Y10: =($S$8-1)*8 -> 152 | Z10: =($S$8-1)*8 -> 152 | ... AD10: =($S$8-1)*8 -> 152
A11: Cherukuri, Ajay | B11: TechSur | C11: Data Architect | D11: 97.96 | F11: 32 | G11: 160 | H11: 160 | I11: 160 | J11: 160 | K11: 160 | L11: 160 | M11: =M$8*8 -> 176 | N11: =N$8*8 -> 184 | O11: =O$8*8 -> 152 | P11: =P$8*8 -> 184 | Q11: =Q$8*8 -> 176 | R11: =R$8*8 -> 144
A12: Guglietta, Jayson | B12: TechSur | C12: System Integration Engineer | D12: 154.94 | F12: 32 | G12: 160 | H12: 160 | I12: 160 | J12: 160 | K12: 160 | L12: 160 | M12: =M$8*8 -> 176 | N12: =N$8*8 -> 184 | O12: =O$8*8 -> 152 | P12: =P$8*8 -> 184 | Q12: =Q$8*8 -> 176 | R12: =R$8*8 -> 144 | S12: =($S$8-1)*8 -> 152 | T12: =($S$8-1)*8 -> 152 | U12: =($S$8-1)*8 -> 152 | V12: =($S$8-1)*8 -> 152 | W12: =($S$8-1)*8 -> 152 | X12: =($S$8-1)*8 -> 152 | Y12: =($S$8-1)*8 -> 152 | Z12: =($S$8-1)*8 -> 152 | ... AD12: =($S$8-1)*8 -> 152
A13: Gura, Alec | B13: TechSur | C13: Communications Specialist | D13: 75.92 | F13: 32 | G13: 160 | H13: 160 | I13: 160 | J13: 160 | K13: 160 | L13: 160 | M13: =M$8*8 -> 176 | N13: =N$8*8 -> 184 | O13: =O$8*8 -> 152 | P13: =P$8*8 -> 184 | Q13: =Q$8*8 -> 176 | R13: =R$8*8 -> 144 | S13: =($S$8-1)*8 -> 152 | T13: =($S$8-1)*8 -> 152 | U13: =($S$8-1)*8 -> 152 | V13: =($S$8-1)*8 -> 152 | W13: =($S$8-1)*8 -> 152 | X13: =($S$8-1)*8 -> 152 | Y13: =($S$8-1)*8 -> 152 | Z13: =($S$8-1)*8 -> 152 | ... AD13: =($S$8-1)*8 -> 152
A14: Harkins, Christopher | B14: TechSur | C14: System Integration Engineer | D14: 154.94 | F14: 32 | G14: 160 | H14: 160 | I14: 160 | J14: 160 | K14: 160 | L14: 160 | M14: =M$8*8 -> 176 | N14: =N$8*8 -> 184 | O14: =O$8*8 -> 152 | P14: =P$8*8 -> 184 | Q14: =Q$8*8 -> 176 | R14: =R$8*8 -> 144 | S14: =($S$8-1)*8 -> 152 | T14: =($S$8-1)*8 -> 152 | U14: =($S$8-1)*8 -> 152 | V14: =($S$8-1)*8 -> 152 | W14: =($S$8-1)*8 -> 152 | X14: =($S$8-1)*8 -> 152 | Y14: =($S$8-1)*8 -> 152 | Z14: =($S$8-1)*8 -> 152 | ... AD14: =($S$8-1)*8 -> 152
A15: Indukuri, Ramajyothi | B15: TechSur | C15: Business Analyst - Senior | D15: 122.45 | F15: 32 | G15: 160 | H15: 160 | I15: 160 | J15: 160 | K15: 160 | L15: 160 | M15: =M$8*8 -> 176 | N15: =N$8*8 -> 184 | O15: =O$8*8 -> 152 | P15: =P$8*8 -> 184 | Q15: =Q$8*8 -> 176 | R15: =R$8*8 -> 144 | S15: =($S$8-1)*8 -> 152 | T15: =($S$8-1)*8 -> 152 | U15: =($S$8-1)*8 -> 152 | V15: =($S$8-1)*8 -> 152 | W15: =($S$8-1)*8 -> 152 | X15: =($S$8-1)*8 -> 152 | Y15: =($S$8-1)*8 -> 152 | Z15: =($S$8-1)*8 -> 152 | ... AD15: =($S$8-1)*8 -> 152
A16: Keswani, Navin | B16: TechSur | C16: System Integration Engineer | D16: 154.94 | F16: 32 | G16: 160 | H16: 160 | I16: 160 | J16: 160 | K16: 160 | L16: 160 | M16: =M$8*8 -> 176 | N16: =N$8*8 -> 184 | O16: =O$8*8 -> 152 | P16: =P$8*8 -> 184 | Q16: =Q$8*8 -> 176 | R16: =R$8*8 -> 144 | S16: =($S$8-1)*8 -> 152 | T16: =($S$8-1)*8 -> 152 | U16: =($S$8-1)*8 -> 152 | V16: =($S$8-1)*8 -> 152 | W16: =($S$8-1)*8 -> 152 | X16: =($S$8-1)*8 -> 152 | Y16: =($S$8-1)*8 -> 152 | Z16: =($S$8-1)*8 -> 152 | ... AD16: =($S$8-1)*8 -> 152
A17: Ramamoorthy, Madhavan | B17: TechSur | C17: Systems Architect | D17: 110.2 | F17: 32 | G17: 160 | H17: 160 | I17: 160 | J17: 160 | K17: 160 | L17: 160 | M17: =M$8*8 -> 176 | N17: =N$8*8 -> 184 | O17: =O$8*8 -> 152 | P17: =P$8*8 -> 184 | Q17: =Q$8*8 -> 176 | R17: =R$8*8 -> 144 | S17: =($S$8-1)*8 -> 152 | T17: =($S$8-1)*8 -> 152 | U17: =($S$8-1)*8 -> 152 | V17: =($S$8-1)*8 -> 152 | W17: =($S$8-1)*8 -> 152 | X17: =($S$8-1)*8 -> 152 | Y17: =($S$8-1)*8 -> 152 | Z17: =($S$8-1)*8 -> 152 | ... AD17: =($S$8-1)*8 -> 152
A18: Saleh, Zakariya | B18: TechSur | C18: Systems Architect | D18: 110.2 | F18: 32 | G18: 160 | H18: 160 | I18: 160 | J18: 160 | K18: 160 | L18: 160 | M18: =M$8*8 -> 176 | N18: =N$8*8 -> 184 | O18: =O$8*8 -> 152 | P18: =P$8*8 -> 184 | Q18: =Q$8*8 -> 176 | R18: =R$8*8 -> 144 | S18: =($S$8-1)*8 -> 152 | T18: =($S$8-1)*8 -> 152 | U18: =($S$8-1)*8 -> 152 | V18: =($S$8-1)*8 -> 152 | W18: =($S$8-1)*8 -> 152 | X18: =($S$8-1)*8 -> 152 | Y18: =($S$8-1)*8 -> 152 | Z18: =($S$8-1)*8 -> 152 | ... AD18: =($S$8-1)*8 -> 152
A19: Shewaneh, Yenenesh | B19: TechSur | C19: Data Architect | D19: 97.96 | F19: 32 | G19: 160 | H19: 160 | I19: 160 | J19: 160 | K19: 160 | L19: 160 | M19: =M$8*8 -> 176 | N19: =N$8*8 -> 184 | O19: =O$8*8 -> 152 | P19: =P$8*8 -> 184 | Q19: =Q$8*8 -> 176 | R19: =R$8*8 -> 144 | S19: =($S$8-1)*8 -> 152 | T19: =($S$8-1)*8 -> 152 | U19: =($S$8-1)*8 -> 152 | V19: =($S$8-1)*8 -> 152 | W19: =($S$8-1)*8 -> 152 | X19: =($S$8-1)*8 -> 152 | Y19: =($S$8-1)*8 -> 152 | Z19: =($S$8-1)*8 -> 152 | ... AD19: =($S$8-1)*8 -> 152
A20: Singhal, Tarun | B20: TechSur | C20: Cloud Architect- CDaaS-PaaS-Cloud Hosting | D20: 155.1 | F20: 32 | G20: 160 | H20: 160 | I20: 160 | J20: 160 | K20: 160 | L20: 160 | M20: =M$8*8 -> 176 | N20: =N$8*8 -> 184 | O20: =O$8*8 -> 152 | P20: =P$8*8 -> 184 | Q20: =Q$8*8 -> 176 | R20: =R$8*8 -> 144 | S20: =($S$8-1)*8 -> 152 | T20: =($S$8-1)*8 -> 152 | U20: =($S$8-1)*8 -> 152 | V20: =($S$8-1)*8 -> 152 | W20: =($S$8-1)*8 -> 152 | X20: =($S$8-1)*8 -> 152 | Y20: =($S$8-1)*8 -> 152 | Z20: =($S$8-1)*8 -> 152 | ... AD20: =($S$8-1)*8 -> 152
A21: Tanksale, Vidyadhar | B21: TechSur | C21: Enterprise Architect | D21: 115.47 | F21: 32 | G21: 160 | H21: 160 | I21: 160 | J21: 160 | K21: 160 | L21: 160 | M21: =M$8*8 -> 176 | N21: =N$8*8 -> 184 | O21: =O$8*8 -> 152 | P21: =P$8*8 -> 184 | Q21: =Q$8*8 -> 176 | R21: =R$8*8 -> 144 | S21: =($S$8-1)*8 -> 152 | T21: =($S$8-1)*8 -> 152 | U21: =($S$8-1)*8 -> 152 | V21: =($S$8-1)*8 -> 152 | W21: =($S$8-1)*8 -> 152 | X21: =($S$8-1)*8 -> 152 | Y21: =($S$8-1)*8 -> 152 | Z21: =($S$8-1)*8 -> 152 | ... AD21: =($S$8-1)*8 -> 152
A22: Telang, Sudeep | B22: TechSur | C22: Enterprise Architect | D22: 115.47 | F22: 32 | G22: 160 | H22: 160 | I22: 160 | J22: 160 | K22: 160 | L22: 160 | M22: =M$8*8 -> 176 | N22: =N$8*8 -> 184 | O22: =O$8*8 -> 152 | P22: =P$8*8 -> 184 | Q22: =Q$8*8 -> 176 | R22: =R$8*8 -> 144 | S22: =($S$8-1)*8 -> 152 | T22: =($S$8-1)*8 -> 152 | U22: =($S$8-1)*8 -> 152 | V22: =($S$8-1)*8 -> 152 | W22: =($S$8-1)*8 -> 152 | X22: =($S$8-1)*8 -> 152 | Y22: =($S$8-1)*8 -> 152 | Z22: =($S$8-1)*8 -> 152 | ... AD22: =($S$8-1)*8 -> 152
A23: Welch, Alisa | B23: TechSur | C23: Business Analyst - Senior | D23: 122.45 | F23: 32 | G23: 160 | H23: 160 | I23: 160 | J23: 160 | K23: 160 | L23: 160 | M23: =M$8*8 -> 176 | N23: =N$8*8 -> 184 | O23: =O$8*8 -> 152 | P23: =P$8*8 -> 184 | Q23: =Q$8*8 -> 176 | R23: =R$8*8 -> 144 | S23: =($S$8-1)*8 -> 152 | T23: =($S$8-1)*8 -> 152 | U23: =($S$8-1)*8 -> 152 | V23: =($S$8-1)*8 -> 152 | W23: =($S$8-1)*8 -> 152 | X23: =($S$8-1)*8 -> 152 | Y23: =($S$8-1)*8 -> 152 | Z23: =($S$8-1)*8 -> 152 | ... AD23: =($S$8-1)*8 -> 152
A24: Pedram Farid | B24: TechSur | C24: Enterprise Architect | D24: 115.47 | F24: 32 | G24: 160 | H24: 160 | I24: 160 | J24: 160 | K24: 160 | L24: 160 | M24: =M$8*8 -> 176 | N24: =N$8*8 -> 184 | O24: =O$8*8 -> 152 | P24: =P$8*8 -> 184 | Q24: =Q$8*8 -> 176 | R24: =R$8*8 -> 144 | S24: =($S$8-1)*8 -> 152 | T24: =($S$8-1)*8 -> 152 | U24: =($S$8-1)*8 -> 152 | V24: =($S$8-1)*8 -> 152 | W24: =($S$8-1)*8 -> 152 | X24: =($S$8-1)*8 -> 152 | Y24: =($S$8-1)*8 -> 152 | Z24: =($S$8-1)*8 -> 152 | ... AD24: =($S$8-1)*8 -> 152
A25: Ceenil Kaur | B25: TechSur | C25: Project Manager | D25: 81.63
A26: Carl Mosca | B26: TechSur | C26: System Integration Engineer | D26: 154.94
A27: Mohammad Khan | C27: System Integration Engineer | D27: 154.94
A28: Ranga Lakshminarayanan | C28: Cloud architect | D28: 155.1
A29: Nagarajan Pattabiraman | B29: Systems Integration Engineer | C29: Systems Integration Engineer | D29: 154.94
A30: David Ylizarde | B30: Systems Integration Engineer | C30: Systems Integration Engineer | D30: 154.94
A31: John Bauer | B31: Systems Integration Engineer | C31: Systems Integration Engineer | D31: 154.94
A32: John Castro | B32: Systems Integration Engineer | C32: Systems Integration Engineer | D32: 154.94
F38: =SUM(F10:F37) -> 480 | G38: =SUM(G10:G37) -> 2400 | H38: =SUM(H10:H37) -> 2240 | I38: =SUM(I10:I37) -> 2400 | J38: =SUM(J10:J37) -> 2400 | K38: =SUM(K10:K37) -> 2400 | L38: =SUM(L10:L37) -> 2400 | M38: =SUM(M10:M37) -> 2640 | ... AG38: =SUM(AG10:AG37) -> 0
A40: Hours Actual
F41: 2025 | J41: 2026 | V41: 2027
A42: Name | B42: Company | C42: LCAT | D42: Rate | F42: 9 | G42: 10 | H42: 11 | I42: 12 | J42: 1 | K42: 2 | L42: 3 | M42: 4 | N42: 5 | O42: 6 | P42: 7 | Q42: 8 | R42: 9 | S42: 10 | T42: 11 | U42: 12 | V42: 1 | W42: 2 | X42: 3 | Y42: 4 | Z42: 5 | AA42: 6 | AB42: 7 | AC42: 8 | AD42: 9 | AE42: 10 | AF42: 11 | AG42: 12
A43: =A10 -> Abdelhaq, Haneen | B43: =B10 -> TechSur | C43: =C10 -> Project Manager | D43: =D10 -> 81.63 | G43: 96 | H43: 0 | I43: 0 | J43: 0 | K43: 0 | L43: 0 | M43: 0 | N43: 0 | O43: 0 | P43: 0
A44: =A11 -> Cherukuri, Ajay | B44: =B11 -> TechSur | C44: =C11 -> Data Architect | D44: =D11 -> 97.96 | F44: 0 | G44: 0 | H44: 0 | I44: 0 | J44: 0 | K44: 0 | L44: 0 | M44: 0 | N44: 0 | O44: 0 | P44: 0
A45: =A12 -> Guglietta, Jayson | B45: =B12 -> TechSur | C45: =C12 -> System Integration Engineer | D45: =D12 -> 154.94 | F45: 24 | G45: 88 | H45: 80 | I45: 176 | J45: 160 | K45: 152 | L45: 176 | M45: 176 | N45: 160 | O45: 168 | P45: 144
A46: =A13 -> Gura, Alec | B46: =B13 -> TechSur | C46: =C13 -> Communications Specialist | D46: =D13 -> 75.92 | F46: 16 | G46: 96 | H46: 80 | I46: 160 | J46: 160 | K46: 152 | L46: 168 | M46: 176 | N46: 160 | O46: 152 | P46: 176
A47: =A14 -> Harkins, Christopher | B47: =B14 -> TechSur | C47: =C14 -> System Integration Engineer | D47: =D14 -> 154.94 | F47: 16 | G47: 96 | H47: 80 | I47: 176 | J47: 128 | K47: 152 | L47: 176 | M47: 176 | N47: 160 | O47: 168 | P47: 176
A48: =A15 -> Indukuri, Ramajyothi | B48: =B15 -> TechSur | C48: =C15 -> Business Analyst - Senior | D48: =D15 -> 122.45 | F48: 24 | G48: 96 | H48: 80 | I48: 176 | J48: 160 | K48: 152 | L48: 176 | M48: 176 | N48: 160 | O48: 168 | P48: 176
A49: =A16 -> Keswani, Navin | B49: =B16 -> TechSur | C49: =C16 -> System Integration Engineer | D49: =D16 -> 154.94 | F49: 24 | G49: 96 | H49: 80 | I49: 176 | J49: 160 | K49: 152 | L49: 176 | M49: 176 | N49: 160 | O49: 168 | P49: 176
A50: =A17 -> Ramamoorthy, Madhavan | B50: =B17 -> TechSur | C50: =C17 -> Systems Architect | D50: =D17 -> 110.2 | F50: 24 | G50: 96 | H50: 80 | I50: 0 | J50: 0 | K50: 0 | L50: 0 | M50: 0 | N50: 0 | O50: 0 | P50: 0
A51: =A18 -> Saleh, Zakariya | B51: =B18 -> TechSur | C51: =C18 -> Systems Architect | D51: =D18 -> 110.2 | F51: 16 | G51: 96 | H51: 64 | I51: 176 | J51: 72 | K51: 152 | L51: 176 | M51: 176 | N51: 160 | O51: 168 | P51: 176
A52: =A19 -> Shewaneh, Yenenesh | B52: =B19 -> TechSur | C52: =C19 -> Data Architect | D52: =D19 -> 97.96 | F52: 24 | G52: 96 | H52: 80 | I52: 176 | J52: 160 | K52: 152 | L52: 176 | M52: 176 | N52: 160 | O52: 168 | P52: 176
A53: =A20 -> Singhal, Tarun | B53: =B20 -> TechSur | C53: =C20 -> Cloud Architect- CDaaS-PaaS-Cloud Hosting | D53: =D20 -> 155.1 | F53: 24 | G53: 96 | H53: 80 | I53: 176 | J53: 160 | K53: 152 | L53: 160 | M53: 0 | N53: 0 | O53: 0 | P53: 0
A54: =A21 -> Tanksale, Vidyadhar | B54: =B21 -> TechSur | C54: =C21 -> Enterprise Architect | D54: =D21 -> 115.47 | F54: 24 | G54: 80 | H54: 80 | I54: 176 | J54: 160 | K54: 120 | L54: 96 | M54: 176 | N54: 144 | O54: 164 | P54: 176
A55: =A22 -> Telang, Sudeep | B55: =B22 -> TechSur | C55: =C22 -> Enterprise Architect | D55: =D22 -> 115.47 | F55: 24 | G55: 96 | H55: 72 | I55: 104 | J55: 88 | K55: 152 | L55: 176 | M55: 176 | N55: 128 | O55: 168 | P55: 176
... A57: =A24 -> Pedram Farid | B57: =B24 -> TechSur | C57: =C24 -> Enterprise Architect | D57: =D24 -> 115.47 | F57: 21 | G57: 96 | H57: 8 | I57: 0 | J57: 0 | K57: 0 | L57: 0 | M57: 0 | N57: 0 | O57: 0 | P57: 0
A58: =A25 -> Ceenil Kaur | B58: =B25 -> TechSur | C58: =C25 -> Project Manager | D58: =D25 -> 81.63 | I58: 96 | J58: 160 | K58: 152 | L58: 176 | M58: 176 | N58: 156 | O58: 168 | P58: 160
A59: =A26 -> Carl Mosca | B59: =B26 -> TechSur | C59: =C26 -> System Integration Engineer | D59: =D26 -> 154.94 | I59: 136 | J59: 160 | K59: 152 | L59: 171 | M59: 176 | N59: 152 | O59: 168 | P59: 102
A60: =A27 -> Mohammad Khan | B60: =B27 -> 0 | C60: =C27 -> System Integration Engineer | D60: =D27 -> 154.94 | I60: 136 | J60: 132 | K60: 124 | L60: 176 | M60: 176 | N60: 152 | O60: 160 | P60: 176
A61: =A28 -> Ranga Lakshminarayanan | B61: =B28 -> 0 | C61: =C28 -> Cloud architect | D61: =D28 -> 155.1 | M61: 152 | N61: 160 | O61: 168 | P61: 176
A62: =A29 -> Nagarajan Pattabiraman | C62: =B29 -> Systems Integration Engineer | D62: =D29 -> 154.94
A63: =A30 -> David Ylizarde | C63: =B30 -> Systems Integration Engineer | D63: =D30 -> 154.94
A64: =A31 -> John Bauer | C64: =B31 -> Systems Integration Engineer | D64: =D31 -> 154.94
A65: =A32 -> John Castro | C65: =B32 -> Systems Integration Engineer | D65: =D32 -> 154.94
F71: =SUM(F43:F70) -> 285 | G71: =SUM(G43:G70) -> 1320 | H71: =SUM(H43:H70) -> 944 | I71: =SUM(I43:I70) -> 2216 | J71: =SUM(J43:J70) -> 2020 | K71: =SUM(K43:K70) -> 2068 | L71: =SUM(L43:L70) -> 2355 | M71: =SUM(M43:M70) -> 2440 | ... AG71: =SUM(AG43:AG70) -> 0
A73: Forecast Revenue by Resource
F74: 2025 | J74: 2026 | V74: 2027
A75: Name | B75: Company | C75: LCAT | D75: Rate | F75: 9 | G75: 10 | H75: 11 | I75: 12 | J75: 1 | K75: 2 | L75: 3 | M75: 4 | N75: 5 | O75: 6 | P75: 7 | Q75: 8 | R75: 9 | S75: 10 | T75: 11 | U75: 12 | V75: 1 | W75: 2 | X75: 3 | Y75: 4 | Z75: 5 | AA75: 6 | AB75: 7 | AC75: 8 | AD75: 9 | AE75: 10 | AF75: 11 | AG75: 12
A76: =A10 -> Abdelhaq, Haneen | B76: =B10 -> TechSur | C76: =C10 -> Project Manager | D76: =D10 -> 81.63 | F76: =$D76*F10 -> 2612.16 | G76: =$D76*G10 -> 13060.8 | H76: =$D76*H10 -> 0 | I76: =$D76*I10 -> 13060.8 | J76: =$D76*J10 -> 13060.8 | K76: =$D76*K10 -> 13060.8 | L76: =$D76*L10 -> 13060.8 | M76: =$D76*M10 -> 14366.88 | ... AD76: =$D76*AD10 -> 12407.76
A77: =A11 -> Cherukuri, Ajay | B77: =B11 -> TechSur | C77: =C11 -> Data Architect | D77: =D11 -> 97.96 | F77: =$D77*F11 -> 3134.72 | G77: =$D77*G11 -> 15673.6 | H77: =$D77*H11 -> 15673.6 | I77: =$D77*I11 -> 15673.6 | J77: =$D77*J11 -> 15673.6 | K77: =$D77*K11 -> 15673.6 | L77: =$D77*L11 -> 15673.6 | M77: =$D77*M11 -> 17240.96 | ... AD77: =$D77*AD11 -> 0
A78: =A12 -> Guglietta, Jayson | B78: =B12 -> TechSur | C78: =C12 -> System Integration Engineer | D78: =D12 -> 154.94 | F78: =$D78*F12 -> 4958.08 | G78: =$D78*G12 -> 24790.4 | H78: =$D78*H12 -> 24790.4 | I78: =$D78*I12 -> 24790.4 | J78: =$D78*J12 -> 24790.4 | K78: =$D78*K12 -> 24790.4 | L78: =$D78*L12 -> 24790.4 | M78: =$D78*M12 -> 27269.44 | ... AD78: =$D78*AD12 -> 23550.88
A79: =A13 -> Gura, Alec | B79: =B13 -> TechSur | C79: =C13 -> Communications Specialist | D79: =D13 -> 75.92 | F79: =$D79*F13 -> 2429.44 | G79: =$D79*G13 -> 12147.2 | H79: =$D79*H13 -> 12147.2 | I79: =$D79*I13 -> 12147.2 | J79: =$D79*J13 -> 12147.2 | K79: =$D79*K13 -> 12147.2 | L79: =$D79*L13 -> 12147.2 | M79: =$D79*M13 -> 13361.92 | ... AD79: =$D79*AD13 -> 11539.84
A80: =A14 -> Harkins, Christopher | B80: =B14 -> TechSur | C80: =C14 -> System Integration Engineer | D80: =D14 -> 154.94 | F80: =$D80*F14 -> 4958.08 | G80: =$D80*G14 -> 24790.4 | H80: =$D80*H14 -> 24790.4 | I80: =$D80*I14 -> 24790.4 | J80: =$D80*J14 -> 24790.4 | K80: =$D80*K14 -> 24790.4 | L80: =$D80*L14 -> 24790.4 | M80: =$D80*M14 -> 27269.44 | ... AD80: =$D80*AD14 -> 23550.88
A81: =A15 -> Indukuri, Ramajyothi | B81: =B15 -> TechSur | C81: =C15 -> Business Analyst - Senior | D81: =D15 -> 122.45 | F81: =$D81*F15 -> 3918.4 | G81: =$D81*G15 -> 19592 | H81: =$D81*H15 -> 19592 | I81: =$D81*I15 -> 19592 | J81: =$D81*J15 -> 19592 | K81: =$D81*K15 -> 19592 | L81: =$D81*L15 -> 19592 | M81: =$D81*M15 -> 21551.2 | ... AD81: =$D81*AD15 -> 18612.4
A82: =A16 -> Keswani, Navin | B82: =B16 -> TechSur | C82: =C16 -> System Integration Engineer | D82: =D16 -> 154.94 | F82: =$D82*F16 -> 4958.08 | G82: =$D82*G16 -> 24790.4 | H82: =$D82*H16 -> 24790.4 | I82: =$D82*I16 -> 24790.4 | J82: =$D82*J16 -> 24790.4 | K82: =$D82*K16 -> 24790.4 | L82: =$D82*L16 -> 24790.4 | M82: =$D82*M16 -> 27269.44 | ... AD82: =$D82*AD16 -> 23550.88
A83: =A17 -> Ramamoorthy, Madhavan | B83: =B17 -> TechSur | C83: =C17 -> Systems Architect | D83: =D17 -> 110.2 | F83: =$D83*F17 -> 3526.4 | G83: =$D83*G17 -> 17632 | H83: =$D83*H17 -> 17632 | I83: =$D83*I17 -> 17632 | J83: =$D83*J17 -> 17632 | K83: =$D83*K17 -> 17632 | L83: =$D83*L17 -> 17632 | M83: =$D83*M17 -> 19395.2 | ... AD83: =$D83*AD17 -> 16750.4
A84: =A18 -> Saleh, Zakariya | B84: =B18 -> TechSur | C84: =C18 -> Systems Architect | D84: =D18 -> 110.2 | F84: =$D84*F18 -> 3526.4 | G84: =$D84*G18 -> 17632 | H84: =$D84*H18 -> 17632 | I84: =$D84*I18 -> 17632 | J84: =$D84*J18 -> 17632 | K84: =$D84*K18 -> 17632 | L84: =$D84*L18 -> 17632 | M84: =$D84*M18 -> 19395.2 | ... AD84: =$D84*AD18 -> 16750.4
A85: =A19 -> Shewaneh, Yenenesh | B85: =B19 -> TechSur | C85: =C19 -> Data Architect | D85: =D19 -> 97.96 | F85: =$D85*F19 -> 3134.72 | G85: =$D85*G19 -> 15673.6 | H85: =$D85*H19 -> 15673.6 | I85: =$D85*I19 -> 15673.6 | J85: =$D85*J19 -> 15673.6 | K85: =$D85*K19 -> 15673.6 | L85: =$D85*L19 -> 15673.6 | M85: =$D85*M19 -> 17240.96 | ... AD85: =$D85*AD19 -> 14889.92
A86: =A20 -> Singhal, Tarun | B86: =B20 -> TechSur | C86: =C20 -> Cloud Architect- CDaaS-PaaS-Cloud Hosting | D86: =D20 -> 155.1 | F86: =$D86*F20 -> 4963.2 | G86: =$D86*G20 -> 24816 | H86: =$D86*H20 -> 24816 | I86: =$D86*I20 -> 24816 | J86: =$D86*J20 -> 24816 | K86: =$D86*K20 -> 24816 | L86: =$D86*L20 -> 24816 | M86: =$D86*M20 -> 27297.6 | ... AD86: =$D86*AD20 -> 23575.2
A87: =A21 -> Tanksale, Vidyadhar | B87: =B21 -> TechSur | C87: =C21 -> Enterprise Architect | D87: =D21 -> 115.47 | F87: =$D87*F21 -> 3695.04 | G87: =$D87*G21 -> 18475.2 | H87: =$D87*H21 -> 18475.2 | I87: =$D87*I21 -> 18475.2 | J87: =$D87*J21 -> 18475.2 | K87: =$D87*K21 -> 18475.2 | L87: =$D87*L21 -> 18475.2 | M87: =$D87*M21 -> 20322.72 | ... AD87: =$D87*AD21 -> 17551.44
... A93: =A27 -> Mohammad Khan | B93: =B27 -> 0 | C93: =C27 -> System Integration Engineer | D93: =D27 -> 154.94 | F93: =$D93*F27 -> 0 | G93: =$D93*G27 -> 0 | H93: =$D93*H27 -> 0 | I93: =$D93*I27 -> 0 | J93: =$D93*J27 -> 0 | K93: =$D93*K27 -> 0 | L93: =$D93*L27 -> 0 | M93: =$D93*M27 -> 0 | ... AD93: =$D93*AD27 -> 0
A94: =A29 -> Nagarajan Pattabiraman | C94: =C29 -> Systems Integration Engineer | D94: =D29 -> 154.94
A95: =A30 -> David Ylizarde | C95: =C30 -> Systems Integration Engineer | D95: =D30 -> 154.94
A96: =A31 -> John Bauer | C96: =C31 -> Systems Integration Engineer | D96: =D31 -> 154.94
A97: =A32 -> John Castro | C97: =C32 -> Systems Integration Engineer | D97: =D32 -> 154.94
F104: =SUM(F76:F103) -> 57123.2 | G104: =SUM(G76:G103) -> 285616 | H104: =SUM(H76:H103) -> 272555.2 | I104: =SUM(I76:I103) -> 285616 | J104: =SUM(J76:J103) -> 285616 | K104: =SUM(K76:K103) -> 285616 | L104: =SUM(L76:L103) -> 285616 | M104: =SUM(M76:M103) -> 314177.6 | ... AD104: =SUM(AD76:AD103) -> 256445.28
A106: Revenue by Resource
F107: 2025 | J107: 2026 | V107: 2027
A108: Name | B108: Company | C108: LCAT | D108: Rate | F108: 9 | G108: 10 | H108: 11 | I108: 12 | J108: 1 | K108: 2 | L108: 3 | M108: 4 | N108: 5 | O108: 6 | P108: 7 | Q108: 8 | R108: 9 | S108: 10 | T108: 11 | U108: 12 | V108: 1 | W108: 2 | X108: 3 | Y108: 4 | Z108: 5 | AA108: 6 | AB108: 7 | AC108: 8 | AD108: 9 | AE108: 10 | AF108: 11 | AG108: 12
A109: =A10 -> Abdelhaq, Haneen | B109: =B10 -> TechSur | C109: =C10 -> Project Manager | D109: =D10 -> 81.63 | F109: =$D109*F43 -> 0 | G109: =$D109*G43 -> 7836.48 | H109: =$D109*H43 -> 0 | I109: =$D109*I43 -> 0 | J109: =$D109*J43 -> 0 | K109: =$D109*K43 -> 0 | L109: =$D109*L43 -> 0 | M109: =$D109*M43 -> 0 | ... AD109: =$D109*AD43 -> 0
A110: =A11 -> Cherukuri, Ajay | B110: =B11 -> TechSur | C110: =C11 -> Data Architect | D110: =D11 -> 97.96 | F110: =$D110*F44 -> 0 | G110: =$D110*G44 -> 0 | H110: =$D110*H44 -> 0 | I110: =$D110*I44 -> 0 | J110: =$D110*J44 -> 0 | K110: =$D110*K44 -> 0 | L110: =$D110*L44 -> 0 | M110: =$D110*M44 -> 0 | ... AD110: =$D110*AD44 -> 0
A111: =A12 -> Guglietta, Jayson | B111: =B12 -> TechSur | C111: =C12 -> System Integration Engineer | D111: =D12 -> 154.94 | F111: =$D111*F45 -> 3718.56 | G111: =$D111*G45 -> 13634.72 | H111: =$D111*H45 -> 12395.2 | I111: =$D111*I45 -> 27269.44 | J111: =$D111*J45 -> 24790.4 | K111: =$D111*K45 -> 23550.88 | L111: =$D111*L45 -> 27269.44 | M111: =$D111*M45 -> 27269.44 | ... AD111: =$D111*AD45 -> 0
A112: =A13 -> Gura, Alec | B112: =B13 -> TechSur | C112: =C13 -> Communications Specialist | D112: =D13 -> 75.92 | F112: =$D112*F46 -> 1214.72 | G112: =$D112*G46 -> 7288.32 | H112: =$D112*H46 -> 6073.6 | I112: =$D112*I46 -> 12147.2 | J112: =$D112*J46 -> 12147.2 | K112: =$D112*K46 -> 11539.84 | L112: =$D112*L46 -> 12754.56 | M112: =$D112*M46 -> 13361.92 | ... AD112: =$D112*AD46 -> 0
A113: =A14 -> Harkins, Christopher | B113: =B14 -> TechSur | C113: =C14 -> System Integration Engineer | D113: =D14 -> 154.94 | F113: =$D113*F47 -> 2479.04 | G113: =$D113*G47 -> 14874.24 | H113: =$D113*H47 -> 12395.2 | I113: =$D113*I47 -> 27269.44 | J113: =$D113*J47 -> 19832.32 | K113: =$D113*K47 -> 23550.88 | L113: =$D113*L47 -> 27269.44 | M113: =$D113*M47 -> 27269.44 | ... AD113: =$D113*AD47 -> 0
A114: =A15 -> Indukuri, Ramajyothi | B114: =B15 -> TechSur | C114: =C15 -> Business Analyst - Senior | D114: =D15 -> 122.45 | F114: =$D114*F48 -> 2938.8 | G114: =$D114*G48 -> 11755.2 | H114: =$D114*H48 -> 9796 | I114: =$D114*I48 -> 21551.2 | J114: =$D114*J48 -> 19592 | K114: =$D114*K48 -> 18612.4 | L114: =$D114*L48 -> 21551.2 | M114: =$D114*M48 -> 21551.2 | ... AD114: =$D114*AD48 -> 0
A115: =A16 -> Keswani, Navin | B115: =B16 -> TechSur | C115: =C16 -> System Integration Engineer | D115: =D16 -> 154.94 | F115: =$D115*F49 -> 3718.56 | G115: =$D115*G49 -> 14874.24 | H115: =$D115*H49 -> 12395.2 | I115: =$D115*I49 -> 27269.44 | J115: =$D115*J49 -> 24790.4 | K115: =$D115*K49 -> 23550.88 | L115: =$D115*L49 -> 27269.44 | M115: =$D115*M49 -> 27269.44 | ... AD115: =$D115*AD49 -> 0
A116: =A17 -> Ramamoorthy, Madhavan | B116: =B17 -> TechSur | C116: =C17 -> Systems Architect | D116: =D17 -> 110.2 | F116: =$D116*F50 -> 2644.8 | G116: =$D116*G50 -> 10579.2 | H116: =$D116*H50 -> 8816 | I116: =$D116*I50 -> 0 | J116: =$D116*J50 -> 0 | K116: =$D116*K50 -> 0 | L116: =$D116*L50 -> 0 | M116: =$D116*M50 -> 0 | ... AD116: =$D116*AD50 -> 0
A117: =A18 -> Saleh, Zakariya | B117: =B18 -> TechSur | C117: =C18 -> Systems Architect | D117: =D18 -> 110.2 | F117: =$D117*F51 -> 1763.2 | G117: =$D117*G51 -> 10579.2 | H117: =$D117*H51 -> 7052.8 | I117: =$D117*I51 -> 19395.2 | J117: =$D117*J51 -> 7934.4 | K117: =$D117*K51 -> 16750.4 | L117: =$D117*L51 -> 19395.2 | M117: =$D117*M51 -> 19395.2 | ... AD117: =$D117*AD51 -> 0
A118: =A19 -> Shewaneh, Yenenesh | B118: =B19 -> TechSur | C118: =C19 -> Data Architect | D118: =D19 -> 97.96 | F118: =$D118*F52 -> 2351.04 | G118: =$D118*G52 -> 9404.16 | H118: =$D118*H52 -> 7836.8 | I118: =$D118*I52 -> 17240.96 | J118: =$D118*J52 -> 15673.6 | K118: =$D118*K52 -> 14889.92 | L118: =$D118*L52 -> 17240.96 | M118: =$D118*M52 -> 17240.96 | ... AD118: =$D118*AD52 -> 0
A119: =A20 -> Singhal, Tarun | B119: =B20 -> TechSur | C119: =C20 -> Cloud Architect- CDaaS-PaaS-Cloud Hosting | D119: =D20 -> 155.1 | F119: =$D119*F53 -> 3722.4 | G119: =$D119*G53 -> 14889.6 | H119: =$D119*H53 -> 12408 | I119: =$D119*I53 -> 27297.6 | J119: =$D119*J53 -> 24816 | K119: =$D119*K53 -> 23575.2 | L119: =$D119*L53 -> 24816 | M119: =$D119*M53 -> 0 | ... AD119: =$D119*AD53 -> 0
A120: =A21 -> Tanksale, Vidyadhar | B120: =B21 -> TechSur | C120: =C21 -> Enterprise Architect | D120: =D21 -> 115.47 | F120: =$D120*F54 -> 2771.28 | G120: =$D120*G54 -> 9237.6 | H120: =$D120*H54 -> 9237.6 | I120: =$D120*I54 -> 20322.72 | J120: =$D120*J54 -> 18475.2 | K120: =$D120*K54 -> 13856.4 | L120: =$D120*L54 -> 11085.12 | M120: =$D120*M54 -> 20322.72 | ... AD120: =$D120*AD54 -> 0
... A126: =A27 -> Mohammad Khan | B126: =B27 -> 0 | C126: =C27 -> System Integration Engineer | D126: =D27 -> 154.94 | F126: =$D126*F60 -> 0 | G126: =$D126*G60 -> 0 | H126: =$D126*H60 -> 0 | I126: =$D126*I60 -> 21071.84 | J126: =$D126*J60 -> 20452.08 | K126: =$D126*K60 -> 19212.56 | L126: =$D126*L60 -> 27269.44 | M126: =$D126*M60 -> 27269.44 | ... AD126: =$D126*AD60 -> 0
A127: =A61 -> Ranga Lakshminarayanan | B127: =B61 -> 0 | C127: =C61 -> Cloud architect | D127: =D61 -> 155.1 | M127: =$D127*M61 -> 23575.2 | N127: =D127*N61 -> 24816 | O127: =D127*O61 -> 26056.8 | P127: =D127*P61 -> 27297.6 | Q127: =$D127*Q61 -> 0 | R127: =$D127*R61 -> 0 | S127: =$D127*S61 -> 0 | T127: =$D127*T61 -> 0 | U127: =$D127*U61 -> 0 | V127: =$D127*V61 -> 0 | W127: =$D127*W61 -> 0 | X127: =$D127*X61 -> 0 | ... AD127: =$D127*AD61 -> 0
A128: =A29 -> Nagarajan Pattabiraman | C128: =C29 -> Systems Integration Engineer | D128: =D29 -> 154.94 | Q128: =$D128*Q62 -> 0 | R128: =$D128*R62 -> 0 | S128: =$D128*S62 -> 0 | T128: =$D128*T62 -> 0 | U128: =$D128*U62 -> 0 | V128: =$D128*V62 -> 0 | W128: =$D128*W62 -> 0 | X128: =$D128*X62 -> 0 | ... AD128: =$D128*AD62 -> 0
A129: =A30 -> David Ylizarde | C129: =C30 -> Systems Integration Engineer | D129: =D30 -> 154.94 | Q129: =$D129*Q63 -> 0 | R129: =$D129*R63 -> 0 | S129: =$D129*S63 -> 0 | T129: =$D129*T63 -> 0 | U129: =$D129*U63 -> 0 | V129: =$D129*V63 -> 0 | W129: =$D129*W63 -> 0 | X129: =$D129*X63 -> 0 | ... AD129: =$D129*AD63 -> 0
A130: =A31 -> John Bauer | C130: =C31 -> Systems Integration Engineer | D130: =D31 -> 154.94 | Q130: =$D130*Q64 -> 0 | R130: =$D130*R64 -> 0 | S130: =$D130*S64 -> 0 | T130: =$D130*T64 -> 0 | U130: =$D130*U64 -> 0 | V130: =$D130*V64 -> 0 | W130: =$D130*W64 -> 0 | X130: =$D130*X64 -> 0 | ... AD130: =$D130*AD64 -> 0
A131: =A32 -> John Castro | C131: =C32 -> Systems Integration Engineer | D131: =D32 -> 154.94 | Q131: =$D131*Q65 -> 0 | R131: =$D131*R65 -> 0 | S131: =$D131*S65 -> 0 | T131: =$D131*T65 -> 0 | U131: =$D131*U65 -> 0 | V131: =$D131*V65 -> 0 | W131: =$D131*W65 -> 0 | X131: =$D131*X65 -> 0 | ... AD131: =$D131*AD65 -> 0
Q132: =$D132*Q66 -> 0 | R132: =$D132*R66 -> 0 | S132: =$D132*S66 -> 0 | T132: =$D132*T66 -> 0 | U132: =$D132*U66 -> 0 | V132: =$D132*V66 -> 0 | W132: =$D132*W66 -> 0 | X132: =$D132*X66 -> 0 | ... AD132: =$D132*AD66 -> 0
...

Sheet AO Call 4.3
A2: Project: | B2: Call 4 - MFA Support
A3: PoP: | B3: 4/10/26-4/9/27
A4: Funded Ceiling: | B4: 1941638.4
A5: Contract Ceiling | B5: 1941638.4
A6: Hours Forecast
D7: Working Days | E7: 20 | F7: 22 | G7: 22 | H7: 20 | I7: 23 | J7: 19 | K7: 21 | L7: 21 | M7: 20 | N7: 22 | O7: 20 | P7: 21 | Q7: 20 | R7: 22 | S7: 22 | T7: 20 | U7: 23 | V7: 19 | W7: 21 | X7: 21 | Y7: 20 | Z7: 22 | AA7: 20 | AB7: 21 | AC7: 20 | AD7: 22 | AE7: 22 | AF7: 20 | AG7: 23 | AH7: 19 | AI7: 21 | AJ7: 21 | AK7: 20 | AL7: 22 | AM7: 20 | AN7: 21 | AO7: 20 | AP7: 22 | AQ7: 22 | AR7: 20 | AS7: 23 | AT7: 19 | AU7: 21 | AV7: 21 | AW7: 20
E8: 2026 | N8: 2027 | Z8: 2028 | AL8: 2029
A9: Name | B9: Company | C9: LCAT | D9: Rate | E9: 4 | F9: 5 | G9: 6 | H9: 7 | I9: 8 | J9: 9 | K9: 10 | L9: 11 | M9: 12 | N9: 1 | O9: 2 | P9: 3 | Q9: 4 | R9: 5 | S9: 6 | T9: 7 | U9: 8 | V9: 9 | W9: 10 | X9: 11 | Y9: 12 | Z9: 1 | AA9: 2 | AB9: 3 | AC9: 4 | AD9: 5 | AE9: 6 | AF9: 7 | AG9: 8 | AH9: 9 | AI9: 10 | AJ9: 11 | AK9: 12 | AL9: 1 | AM9: 2 | AN9: 3 | AO9: 4 | AP9: 5 | AQ9: 6 | AR9: 7 | AS9: 8 | AT9: 9 | AU9: 10 | AV9: 11 | AW9: 12
A10: Bandapally, Sunil Kumar | B10: TechSur | C10: Systems Integration Engineer | D10: 154.94 | E10: 120 | F10: 159.6 | G10: =(G$7-1)*8 -> 168 | H10: =(H$7-1)*8 -> 152 | I10: =(I$7-1)*8 -> 176 | J10: =(J$7-1)*8 -> 144 | K10: =(K$7-1)*8 -> 160 | L10: =(L$7-1)*8 -> 160 | M10: =(M$7-1)*8 -> 152 | N10: =(N$7-1)*8 -> 168 | ... P10: =(P$7-1)*8 -> 160 | Q10: 64
A11: Gupta, Sangamewar | B11: TechSur | C11: Systems Integration Engineer | D11: 154.94 | E11: 120 | F11: 159.6 | G11: =(G$7-1)*8 -> 168 | H11: =(H$7-1)*8 -> 152 | I11: =(I$7-1)*8 -> 176 | J11: =(J$7-1)*8 -> 144 | K11: =(K$7-1)*8 -> 160 | L11: =(L$7-1)*8 -> 160 | M11: =(M$7-1)*8 -> 152 | N11: =(N$7-1)*8 -> 168 | ... P11: =(P$7-1)*8 -> 160 | Q11: 64
A12: Kakhramon, Talibdjanov | B12: TechSur | C12: Systems Integration Engineer | D12: 154.94 | E12: 120 | F12: 159.6 | G12: =(G$7-1)*8 -> 168 | H12: =(H$7-1)*8 -> 152 | I12: =(I$7-1)*8 -> 176 | J12: =(J$7-1)*8 -> 144 | K12: =(K$7-1)*8 -> 160 | L12: =(L$7-1)*8 -> 160 | M12: =(M$7-1)*8 -> 152 | N12: =(N$7-1)*8 -> 168 | ... P12: =(P$7-1)*8 -> 160 | Q12: 64
A13: Nazir, Muhammad | B13: TechSur | C13: Systems Integration Engineer | D13: 154.94 | E13: 120 | F13: 159.6 | G13: =(G$7-1)*8 -> 168 | H13: =(H$7-1)*8 -> 152 | I13: =(I$7-1)*8 -> 176 | J13: =(J$7-1)*8 -> 144 | K13: =(K$7-1)*8 -> 160 | L13: =(L$7-1)*8 -> 160 | M13: =(M$7-1)*8 -> 152 | N13: =(N$7-1)*8 -> 168 | ... P13: =(P$7-1)*8 -> 160 | Q13: 64
A14: Verma, Narayan Kumar | B14: TechSur | C14: Systems Integration Engineer | D14: 154.94 | E14: 120 | F14: 159.6 | G14: =(G$7-1)*8 -> 168 | H14: =(H$7-1)*8 -> 152 | I14: =(I$7-1)*8 -> 176 | J14: =(J$7-1)*8 -> 144 | K14: =(K$7-1)*8 -> 160 | L14: =(L$7-1)*8 -> 160 | M14: =(M$7-1)*8 -> 152 | N14: =(N$7-1)*8 -> 168 | ... P14: =(P$7-1)*8 -> 160 | Q14: 64
A15: Holcomb, Lauryn | B15: TechSur | C15: Project Manager | D15: 81.63 | E15: 120 | F15: 159.6 | G15: =(G$7-1)*8 -> 168 | H15: =(H$7-1)*8 -> 152 | I15: =(I$7-1)*8 -> 176 | J15: =(J$7-1)*8 -> 144 | K15: =(K$7-1)*8 -> 160 | L15: =(L$7-1)*8 -> 160 | M15: =(M$7-1)*8 -> 152 | N15: =(N$7-1)*8 -> 168 | ... P15: =(P$7-1)*8 -> 160 | Q15: 64
E40: =SUM(E10:E39) -> 720 | F40: =SUM(F10:F39) -> 957.6 | G40: =SUM(G10:G39) -> 1008 | H40: =SUM(H10:H39) -> 912 | I40: =SUM(I10:I39) -> 1056 | J40: =SUM(J10:J39) -> 864 | K40: =SUM(K10:K39) -> 960 | L40: =SUM(L10:L39) -> 960 | ... AW40: =SUM(AW10:AW39) -> 0
A42: Hours Actual
E43: 2026 | N43: 2027 | Z43: 2028 | AL43: 2029
A44: Name | B44: Company | C44: LCAT | D44: Rate | E44: 4 | F44: 5 | G44: 6 | H44: 7 | I44: 8 | J44: 9 | K44: 10 | L44: 11 | M44: 12 | N44: 1 | O44: 2 | P44: 3 | Q44: 4 | R44: 5 | S44: 6 | T44: 7 | U44: 8 | V44: 9 | W44: 10 | X44: 11 | Y44: 12 | Z44: 1 | AA44: 2 | AB44: 3 | AC44: 4 | AD44: 5 | AE44: 6 | AF44: 7 | AG44: 8 | AH44: 9 | AI44: 10 | AJ44: 11 | AK44: 12 | AL44: 1 | AM44: 2 | AN44: 3 | AO44: 4 | AP44: 5 | AQ44: 6 | AR44: 7 | AS44: 8 | AT44: 9 | AU44: 10 | AV44: 11 | AW44: 12
A45: =A10 -> Bandapally, Sunil Kumar | B45: =B10 -> TechSur | C45: =C10 -> Systems Integration Engineer | D45: =D10 -> 154.94 | E45: 118 | F45: 158 | G45: 168 | H45: 176
A46: =A11 -> Gupta, Sangamewar | B46: =B11 -> TechSur | C46: =C11 -> Systems Integration Engineer | D46: =D11 -> 154.94 | E46: 120 | F46: 152 | G46: 160 | H46: 168
A47: =A12 -> Kakhramon, Talibdjanov | B47: =B12 -> TechSur | C47: =C12 -> Systems Integration Engineer | D47: =D12 -> 154.94 | E47: 120 | F47: 152 | G47: 160 | H47: 176
A48: =A13 -> Nazir, Muhammad | B48: =B13 -> TechSur | C48: =C13 -> Systems Integration Engineer | D48: =D13 -> 154.94 | E48: 120 | F48: 120 | G48: 168 | H48: 176
A49: =A14 -> Verma, Narayan Kumar | B49: =B14 -> TechSur | C49: =C14 -> Systems Integration Engineer | D49: =D14 -> 154.94 | E49: 120 | F49: 160 | G49: 168 | H49: 176
A50: =A15 -> Holcomb, Lauryn | B50: =B15 -> TechSur | C50: =C15 -> Project Manager | D50: =D15 -> 81.63 | E50: 112 | F50: 160 | G50: 168 | H50: 176
A51: =A17 -> 0 | B51: =B17 -> 0 | C51: =C17 -> 0 | D51: =D17 -> 0
A52: =A18 -> 0 | B52: =B18 -> 0 | C52: =C18 -> 0 | D52: =D18 -> 0
A53: =A19 -> 0 | B53: =B19 -> 0 | C53: =C19 -> 0 | D53: =D19 -> 0
A54: =A20 -> 0 | B54: =B20 -> 0 | C54: =C20 -> 0 | D54: =D20 -> 0
E75: =SUM(E45:E74) -> 710 | F75: =SUM(F45:F74) -> 902 | G75: =SUM(G45:G74) -> 992 | H75: =SUM(H45:H74) -> 1048 | I75: =SUM(I45:I74) -> 0 | J75: =SUM(J45:J74) -> 0 | K75: =SUM(K45:K74) -> 0 | L75: =SUM(L45:L74) -> 0 | ... AW75: =SUM(AW45:AW74) -> 0
A77: Forecast Revenue by Resource
E78: 2026 | N78: 2027 | Z78: 2028 | AL78: 2029
A79: Name | B79: Company | C79: LCAT | D79: Rate | E79: 4 | F79: 5 | G79: 6 | H79: 7 | I79: 8 | J79: 9 | K79: 10 | L79: 11 | M79: 12 | N79: 1 | O79: 2 | P79: 3 | Q79: 4 | R79: 5 | S79: 6 | T79: 7 | U79: 8 | V79: 9 | W79: 10 | X79: 11 | Y79: 12 | Z79: 1 | AA79: 2 | AB79: 3 | AC79: 4 | AD79: 5 | AE79: 6 | AF79: 7 | AG79: 8 | AH79: 9 | AI79: 10 | AJ79: 11 | AK79: 12 | AL79: 1 | AM79: 2 | AN79: 3 | AO79: 4 | AP79: 5 | AQ79: 6 | AR79: 7 | AS79: 8 | AT79: 9 | AU79: 10 | AV79: 11 | AW79: 12
A80: =A10 -> Bandapally, Sunil Kumar | B80: =B10 -> TechSur | C80: =C10 -> Systems Integration Engineer | D80: =D10 -> 154.94 | E80: =$D80*E10 -> 18592.8 | F80: =$D80*F10 -> 24728.424 | G80: =$D80*G10 -> 26029.92 | H80: =$D80*H10 -> 23550.88 | I80: =$D80*I10 -> 27269.44 | J80: =$D80*J10 -> 22311.36 | K80: =$D80*K10 -> 24790.4 | L80: =$D80*L10 -> 24790.4 | ... Q80: =$D80*Q10 -> 9916.16 | R80: =R10*$D10 -> 0 | S80: =S10*$D10 -> 0 | T80: =T10*$D10 -> 0 | U80: =U10*$D10 -> 0 | V80: =V10*$D10 -> 0 | W80: =W10*$D10 -> 0 | X80: =X10*$D10 -> 0 | Y80: =Y10*$D10 -> 0 | ... AO80: =AO10*$D10 -> 0
A81: =A11 -> Gupta, Sangamewar | B81: =B11 -> TechSur | C81: =C11 -> Systems Integration Engineer | D81: =D11 -> 154.94 | E81: =$D81*E11 -> 18592.8 | F81: =$D81*F11 -> 24728.424 | G81: =$D81*G11 -> 26029.92 | H81: =$D81*H11 -> 23550.88 | I81: =$D81*I11 -> 27269.44 | J81: =$D81*J11 -> 22311.36 | K81: =$D81*K11 -> 24790.4 | L81: =$D81*L11 -> 24790.4 | ... Q81: =$D81*Q11 -> 9916.16 | R81: =R11*$D11 -> 0 | S81: =S11*$D11 -> 0 | T81: =T11*$D11 -> 0 | U81: =U11*$D11 -> 0 | V81: =V11*$D11 -> 0 | W81: =W11*$D11 -> 0 | X81: =X11*$D11 -> 0 | Y81: =Y11*$D11 -> 0 | ... AO81: =AO11*$D11 -> 0
A82: =A12 -> Kakhramon, Talibdjanov | B82: =B12 -> TechSur | C82: =C12 -> Systems Integration Engineer | D82: =D12 -> 154.94 | E82: =$D82*E12 -> 18592.8 | F82: =$D82*F12 -> 24728.424 | G82: =$D82*G12 -> 26029.92 | H82: =$D82*H12 -> 23550.88 | I82: =$D82*I12 -> 27269.44 | J82: =$D82*J12 -> 22311.36 | K82: =$D82*K12 -> 24790.4 | L82: =$D82*L12 -> 24790.4 | ... Q82: =$D82*Q12 -> 9916.16 | R82: =R12*$D12 -> 0 | S82: =S12*$D12 -> 0 | T82: =T12*$D12 -> 0 | U82: =U12*$D12 -> 0 | V82: =V12*$D12 -> 0 | W82: =W12*$D12 -> 0 | X82: =X12*$D12 -> 0 | Y82: =Y12*$D12 -> 0 | ... AO82: =AO12*$D12 -> 0
A83: =A14 -> Verma, Narayan Kumar | B83: =B14 -> TechSur | C83: =C14 -> Systems Integration Engineer | D83: =D14 -> 154.94 | E83: =$D83*E13 -> 18592.8 | F83: =$D83*F13 -> 24728.424 | G83: =$D83*G13 -> 26029.92 | H83: =$D83*H13 -> 23550.88 | I83: =$D83*I13 -> 27269.44 | J83: =$D83*J13 -> 22311.36 | K83: =$D83*K13 -> 24790.4 | L83: =$D83*L13 -> 24790.4 | ... Q83: =$D83*Q13 -> 9916.16 | R83: =R13*$D14 -> 0 | S83: =S13*$D14 -> 0 | T83: =T13*$D14 -> 0 | U83: =U13*$D14 -> 0 | V83: =V13*$D14 -> 0 | W83: =W13*$D14 -> 0 | X83: =X13*$D14 -> 0 | Y83: =Y13*$D14 -> 0 | ... AO83: =AO13*$D14 -> 0
A84: =A15 -> Holcomb, Lauryn | B84: =B15 -> TechSur | C84: =C15 -> Project Manager | D84: =D15 -> 81.63 | E84: =$D84*E15 -> 9795.6 | F84: =$D84*F14 -> 13028.148 | G84: =$D84*G14 -> 13713.84 | H84: =$D84*H14 -> 12407.76 | I84: =$D84*I14 -> 14366.88 | J84: =$D84*J14 -> 11754.72 | K84: =$D84*K14 -> 13060.8 | L84: =$D84*L14 -> 13060.8 | M84: =$D84*M14 -> 12407.76 | ... Q84: =$D84*Q14 -> 5224.32 | R84: =R14*$D15 -> 0 | S84: =S14*$D15 -> 0 | T84: =T14*$D15 -> 0 | U84: =U14*$D15 -> 0 | V84: =V14*$D15 -> 0 | W84: =W14*$D15 -> 0 | X84: =X14*$D15 -> 0 | Y84: =Y14*$D15 -> 0 | ... AO84: =AO14*$D15 -> 0
A85: =A16 -> 0 | B85: =B16 -> 0 | C85: =C16 -> 0 | D85: =D16 -> 0 | E85: =$D85*E15 -> 0 | F85: =$D85*F15 -> 0 | G85: =$D85*G15 -> 0 | H85: =$D85*H15 -> 0 | I85: =$D85*I15 -> 0 | J85: =$D85*J15 -> 0 | K85: =$D85*K15 -> 0 | L85: =$D85*L15 -> 0 | M85: =$D85*M15 -> 0 | N85: =$D85*N17 -> 0 | O85: =$D85*O17 -> 0 | P85: =$D85*P17 -> 0 | Q85: =$D85*Q17 -> 0 | R85: =R17*$D16 -> 0 | S85: =S17*$D16 -> 0 | T85: =T17*$D16 -> 0 | U85: =U17*$D16 -> 0 | V85: =V17*$D16 -> 0 | W85: =W17*$D16 -> 0 | X85: =X17*$D16 -> 0 | Y85: =Y17*$D16 -> 0 | ... AO85: =AO17*$D16 -> 0
A86: =A17 -> 0 | B86: =B17 -> 0 | C86: =C17 -> 0 | D86: =D17 -> 0 | E86: =$D86*E16 -> 0 | F86: =$D86*F16 -> 0 | G86: =$D86*G16 -> 0 | H86: =$D86*H16 -> 0 | I86: =$D86*I16 -> 0 | J86: =$D86*J16 -> 0 | K86: =$D86*K16 -> 0 | L86: =$D86*L16 -> 0 | ... Q86: =$D86*Q16 -> 0 | R86: =R16*$D17 -> 0 | S86: =S16*$D17 -> 0 | T86: =T16*$D17 -> 0 | U86: =U16*$D17 -> 0 | V86: =V16*$D17 -> 0 | W86: =W16*$D17 -> 0 | X86: =X16*$D17 -> 0 | Y86: =Y16*$D17 -> 0 | ... AO86: =AO16*$D17 -> 0
A87: =A18 -> 0 | B87: =B18 -> 0 | C87: =C18 -> 0 | D87: =D18 -> 0 | E87: =$D87*E17 -> 0 | F87: =$D87*F17 -> 0 | G87: =$D87*G17 -> 0 | H87: =$D87*H17 -> 0 | I87: =$D87*I17 -> 0 | J87: =$D87*J17 -> 0 | K87: =$D87*K17 -> 0 | L87: =$D87*L17 -> 0 | ... AO87: =$D87*AO17 -> 0
A88: =A19 -> 0 | B88: =B19 -> 0 | C88: =C19 -> 0 | D88: =D19 -> 0 | E88: =$D88*E18 -> 0 | F88: =$D88*F18 -> 0 | G88: =$D88*G18 -> 0 | H88: =$D88*H18 -> 0 | I88: =$D88*I18 -> 0 | J88: =$D88*J18 -> 0 | K88: =$D88*K18 -> 0 | L88: =$D88*L18 -> 0 | ... AO88: =$D88*AO18 -> 0
A89: =A20 -> 0 | B89: =B20 -> 0 | C89: =C20 -> 0 | D89: =D20 -> 0 | E89: =$D89*E19 -> 0 | F89: =$D89*F19 -> 0 | G89: =$D89*G19 -> 0 | H89: =$D89*H19 -> 0 | I89: =$D89*I19 -> 0 | J89: =$D89*J19 -> 0 | K89: =$D89*K19 -> 0 | L89: =$D89*L19 -> 0 | ... AO89: =$D89*AO19 -> 0
A90: =A21 -> 0 | B90: =B21 -> 0 | C90: =C21 -> 0 | D90: =D21 -> 0 | E90: =$D90*E20 -> 0 | F90: =$D90*F20 -> 0
E91: =$D91*E21 -> 0 | F91: =$D91*F21 -> 0
E110: =SUM(E80:E109) -> 84166.8 | F110: =SUM(F80:F109) -> 111941.84 | G110: =SUM(G80:G109) -> 117833.52 | H110: =SUM(H80:H109) -> 106611.28 | I110: =SUM(I80:I109) -> 123444.64 | J110: =SUM(J80:J109) -> 101000.16 | K110: =SUM(K80:K109) -> 112222.4 | L110: =SUM(L80:L109) -> 112222.4 | ... AW110: =SUM(AW80:AW109) -> 0
A112: Revenue by Resource
E113: 2026 | N113: 2027 | Z113: 2028 | AL113: 2029
A114: Name | B114: Company | C114: LCAT | D114: Rate | E114: 4 | F114: 5 | G114: 6 | H114: 7 | I114: 8 | J114: 9 | K114: 10 | L114: 11 | M114: 12 | N114: 1 | O114: 2 | P114: 3 | Q114: 4 | R114: 5 | S114: 6 | T114: 7 | U114: 8 | V114: 9 | W114: 10 | X114: 11 | Y114: 12 | Z114: 1 | AA114: 2 | AB114: 3 | AC114: 4 | AD114: 5 | AE114: 6 | AF114: 7 | AG114: 8 | AH114: 9 | AI114: 10 | AJ114: 11 | AK114: 12 | AL114: 1 | AM114: 2 | AN114: 3 | AO114: 4 | AP114: 5 | AQ114: 6 | AR114: 7 | AS114: 8 | AT114: 9 | AU114: 10 | AV114: 11 | AW114: 12
A115: =A10 -> Bandapally, Sunil Kumar | B115: =B10 -> TechSur | C115: =C10 -> Systems Integration Engineer | D115: =D10 -> 154.94 | E115: =$D115*E45 -> 18282.92 | F115: =$D115*F45 -> 24480.52 | G115: =$D115*G45 -> 26029.92 | H115: =$D115*H45 -> 27269.44 | I115: =$D115*I45 -> 0 | J115: =$D115*J45 -> 0 | K115: =$D115*K45 -> 0 | L115: =$D115*L45 -> 0 | ... AO115: =$D115*AO45 -> 0
A116: =A11 -> Gupta, Sangamewar | B116: =B11 -> TechSur | C116: =C11 -> Systems Integration Engineer | D116: =D11 -> 154.94 | E116: =$D116*E46 -> 18592.8 | F116: =$D116*F46 -> 23550.88 | G116: =$D116*G46 -> 24790.4 | H116: =$D116*H46 -> 26029.92 | I116: =$D116*I46 -> 0 | J116: =$D116*J46 -> 0 | K116: =$D116*K46 -> 0 | L116: =$D116*L46 -> 0 | ... AO116: =$D116*AO46 -> 0
A117: =A12 -> Kakhramon, Talibdjanov | B117: =B12 -> TechSur | C117: =C12 -> Systems Integration Engineer | D117: =D12 -> 154.94 | E117: =$D117*E47 -> 18592.8 | F117: =$D117*F47 -> 23550.88 | G117: =$D117*G47 -> 24790.4 | H117: =$D117*H47 -> 27269.44 | I117: =$D117*I47 -> 0 | J117: =$D117*J47 -> 0 | K117: =$D117*K47 -> 0 | L117: =$D117*L47 -> 0 | ... AO117: =$D117*AO47 -> 0
A118: =A13 -> Nazir, Muhammad | B118: =B13 -> TechSur | C118: =C13 -> Systems Integration Engineer | D118: =D13 -> 154.94 | E118: =$D118*E48 -> 18592.8 | F118: =$D118*F48 -> 18592.8 | G118: =$D118*G48 -> 26029.92 | H118: =$D118*H48 -> 27269.44 | I118: =$D118*I48 -> 0 | J118: =$D118*J48 -> 0 | K118: =$D118*K48 -> 0 | L118: =$D118*L48 -> 0 | ... P118: =$D118*P48 -> 0
A119: =A14 -> Verma, Narayan Kumar | B119: =B14 -> TechSur | C119: =C14 -> Systems Integration Engineer | D119: =D14 -> 154.94 | E119: =$D119*E49 -> 18592.8 | F119: =$D119*F49 -> 24790.4 | G119: =$D119*G49 -> 26029.92 | H119: =$D119*H49 -> 27269.44 | I119: =$D119*I49 -> 0 | J119: =$D119*J49 -> 0 | K119: =$D119*K49 -> 0 | L119: =$D119*L49 -> 0 | ... P119: =$D119*P49 -> 0 | Q119: =$D119*Q48 -> 0 | R119: =$D119*R48 -> 0 | S119: =$D119*S48 -> 0 | T119: =$D119*T48 -> 0 | U119: =$D119*U48 -> 0 | V119: =$D119*V48 -> 0 | W119: =$D119*W48 -> 0 | X119: =$D119*X48 -> 0 | ... AO119: =$D119*AO48 -> 0
A120: =A15 -> Holcomb, Lauryn | B120: =B15 -> TechSur | C120: =C15 -> Project Manager | D120: =D15 -> 81.63 | E120: =$D120*E50 -> 9142.56 | F120: =$D120*F50 -> 13060.8 | G120: =$D120*G50 -> 13713.84 | H120: =$D120*H50 -> 14366.88 | I120: =$D120*I50 -> 0 | J120: =$D120*J50 -> 0 | K120: =$D120*K50 -> 0 | L120: =$D120*L50 -> 0 | ... P120: =$D120*P50 -> 0 | Q120: =$D120*Q49 -> 0 | R120: =$D120*R49 -> 0 | S120: =$D120*S49 -> 0 | T120: =$D120*T49 -> 0 | U120: =$D120*U49 -> 0 | V120: =$D120*V49 -> 0 | W120: =$D120*W49 -> 0 | X120: =$D120*X49 -> 0 | ... AO120: =$D120*AO49 -> 0
A121: =A16 -> 0 | B121: =B16 -> 0 | C121: =C16 -> 0 | E121: =$D121*E50 -> 0 | F121: =$D121*F50 -> 0 | G121: =$D121*G50 -> 0 | H121: =$D121*H50 -> 0 | I121: =$D121*I50 -> 0 | J121: =$D121*J50 -> 0 | K121: =$D121*K50 -> 0 | L121: =$D121*L50 -> 0 | ... AO121: =$D121*AO50 -> 0
A122: =A17 -> 0 | B122: =B17 -> 0 | C122: =C17 -> 0 | D122: =D17 -> 0 | E122: =$D122*E51 -> 0 | F122: =$D122*F51 -> 0 | G122: =$D122*G51 -> 0 | H122: =$D122*H51 -> 0 | I122: =$D122*I51 -> 0 | J122: =$D122*J51 -> 0 | K122: =$D122*K51 -> 0 | L122: =$D122*L51 -> 0 | ... AO122: =$D122*AO51 -> 0
A123: =A18 -> 0 | B123: =B18 -> 0 | C123: =C18 -> 0 | D123: =D18 -> 0 | E123: =$D123*E52 -> 0 | F123: =$D123*F52 -> 0 | G123: =$D123*G52 -> 0 | H123: =$D123*H52 -> 0 | I123: =$D123*I52 -> 0 | J123: =$D123*J52 -> 0 | K123: =$D123*K52 -> 0 | L123: =$D123*L52 -> 0 | ... P123: =$D123*P52 -> 0
A124: =A19 -> 0 | B124: =B19 -> 0 | C124: =C19 -> 0 | D124: =D19 -> 0 | E124: =$D124*E53 -> 0 | F124: =$D124*F53 -> 0 | G124: =$D124*G53 -> 0 | H124: =$D124*H53 -> 0 | I124: =$D124*I53 -> 0 | J124: =$D124*J53 -> 0 | K124: =$D124*K53 -> 0 | L124: =$D124*L53 -> 0 | ... P124: =$D124*P53 -> 0
A125: =A20 -> 0 | B125: =B20 -> 0 | C125: =C20 -> 0 | D125: =D20 -> 0 | E125: =$D125*E54 -> 0 | F125: =$D125*F54 -> 0 | G125: =$D125*G54 -> 0 | H125: =$D125*H54 -> 0 | I125: =$D125*I54 -> 0 | J125: =$D125*J54 -> 0 | K125: =$D125*K54 -> 0 | L125: =$D125*L54 -> 0 | ... P125: =$D125*P54 -> 0
E146: =SUM(E115:E145) -> 101796.68 | F146: =SUM(F115:F145) -> 128026.28 | G146: =SUM(G115:G145) -> 141384.4 | H146: =SUM(H115:H145) -> 149474.56 | I146: =SUM(I115:I145) -> 0 | J146: =SUM(J115:J145) -> 0 | K146: =SUM(K115:K145) -> 0 | L146: =SUM(L115:L145) -> 0 | ... AW146: =SUM(AW115:AW145) -> 0 | AY146: =SUM(E146:AX146) -> 520681.92
A148: Invoice and Revenue Analysis
E149: 2026 | N149: 2027 | Z149: 2028 | AL149: 2029
C150: Invoice | D150: Date | E150: 4 | F150: 5 | G150: 6 | H150: 7 | I150: 8 | J150: 9 | K150: 10 | L150: 11 | M150: 12 | N150: 1 | O150: 2 | P150: 3 | Q150: 4 | R150: 5 | S150: 6 | T150: 7 | U150: 8 | V150: 9 | W150: 10 | X150: 11 | Y150: 12 | Z150: 1 | AA150: 2 | AB150: 3 | AC150: 4 | AD150: 5 | AE150: 6 | AF150: 7 | AG150: 8 | AH150: 9 | AI150: 10 | AJ150: 11 | AK150: 12 | AL150: 1 | AM150: 2 | AN150: 3 | AO150: 4 | AP150: 5 | AQ150: 6 | AR150: 7 | AS150: 8 | AT150: 9 | AU150: 10 | AV150: 11 | AW150: 12
C151: I01382 - April | D151: 46149 | E151: =E146 -> 101796.68
C152: I01399 - May | F152: 128026.28
C153: I01432 - June | D153: 46209 | G153: 141384.4
C154: I01478 - July | D154: 46238 | H154: 149474.56
D164: Revenue | E164: =SUM(E151:E163) -> 101796.68 | F164: =SUM(F151:F163) -> 128026.28 | G164: =SUM(G151:G163) -> 141384.4 | H164: =SUM(H151:H163) -> 149474.56 | I164: =SUM(I151:I163) -> 0 | J164: =SUM(J151:J163) -> 0 | K164: =SUM(K151:K163) -> 0 | L164: =SUM(L151:L163) -> 0 | ... AW164: =SUM(AW151:AW163) -> 0
E168: 45772 | F168: 45802 | G168: 45833 | H168: 45863 | I168: 45894 | J168: 45925 | K168: 45955 | L168: 45986 | M168: 46016
D169: Forecast Rev | E169: =E110 -> 84166.8 | F169: =E169+F110 -> 196108.64 | G169: =F169+G110 -> 313942.16 | H169: =G169+H110 -> 420553.44 | I169: =H169+I110 -> 543998.08 | J169: =I169+J110 -> 644998.24 | K169: =J169+K110 -> 757220.64 | L169: =K169+L110 -> 869443.04 | M169: =L169+M110 -> 976054.32 | ... P169: =O169+P110 -> 1312721.5
D170: Actual Rev | E170: =E164 -> 101796.68 | F170: =E170+F164 -> 229822.96 | G170: =F170+G164 -> 371207.36 | H170: =G170+H164 -> 520681.92 | I170: =H170+I164 -> 520681.92 | J170: =I170+J164 -> 520681.92 | K170: =J170+K164 -> 520681.92 | L170: =K170+L164 -> 520681.92 | M170: =L170+M164 -> 520681.92
D171: Funding | E171: =$B$4 -> 1941638.4 | F171: =$B$4 -> 1941638.4 | G171: =$B$4 -> 1941638.4 | H171: =$B$4 -> 1941638.4 | I171: =$B$4 -> 1941638.4 | J171: =$B$4 -> 1941638.4 | K171: =$B$4 -> 1941638.4 | L171: =$B$4 -> 1941638.4 | ... P171: =$B$4 -> 1941638.4
D172: Variance $ | E172: =E169-E170 -> -17629.88 | F172: =F169-F170 -> -33714.316 | G172: =G169-G170 -> -57265.196 | H172: =H169-H170 -> -100128.48 | I172: =I169-I170 -> 23316.164 | J172: =J169-J170 -> 124316.32 | K172: =K169-K170 -> 236538.72 | L172: =L169-L170 -> 348761.12 | ... P172: =P169-P170 -> 1312721.5
D173: Variance % | E173: =E170/E169 -> 1.2094636 | F173: =F170/F169 -> 1.1719165 | G173: =G170/G169 -> 1.1824068 | H173: =H170/H169 -> 1.2380874 | I173: =I170/I169 -> 0.95713925 | J173: =J170/J169 -> 0.80726099 | K173: =K170/K169 -> 0.68762246 | L173: =L170/L169 -> 0.59886835 | ... P173: =P170/P169 -> 0

Sheet AO Call 13.1
A2: Project: | B2: Call 13 - DevSecOps
A3: PoP: | B3: 9/13/25 - 9/12/26 | C3: OP2: 9/13/26 - 9/12/27
A4: Funded Ceiling: | B4: 1491977.3
A6: Hours Forecast
D7: Working Days | E7: 22 | F7: 18 | G7: 21 | H7: 20 | I7: 20 | J7: 21 | K7: 20 | L7: 21 | M7: 22 | N7: 23 | O7: 19 | P7: 23 | Q7: 22 | R7: 18 | S7: 21 | T7: 20 | U7: 20 | V7: 21 | W7: 20 | X7: 21 | Y7: 22 | Z7: 23 | AA7: 19 | AB7: 23 | AC7: 22 | AD7: 18 | AE7: 21 | AF7: 20 | AG7: 20 | AH7: 21 | AI7: 20 | AJ7: 21 | AK7: 22 | AL7: 23 | AM7: 19 | AN7: 23 | AO7: 22 | AP7: 18 | AQ7: 21 | AR7: 20 | AS7: 20
E8: 2025 | J8: 2026 | V8: 2027 | AH8: 2028
A9: Name | B9: Company | C9: LCAT | D9: Rate | E9: 8 | F9: 9 | G9: 10 | H9: 11 | I9: 12 | J9: 1 | K9: 2 | L9: 3 | M9: 4 | N9: 5 | O9: 6 | P9: 7 | Q9: 8 | R9: 9 | S9: 10 | T9: 11 | U9: 12 | V9: 1 | W9: 2 | X9: 3 | Y9: 4 | Z9: 5 | AA9: 6 | AB9: 7 | AC9: 8 | AD9: 9 | AE9: 10 | AF9: 11 | AG9: 12 | AH9: 1 | AI9: 2 | AJ9: 3 | AK9: 4 | AL9: 5 | AM9: 6 | AN9: 7 | AO9: 8 | AP9: 9 | AQ9: 10 | AR9: 11 | AS9: 12
A10: Bulchandani, Kapil | B10: TechSur | C10: Systems Integration Engineer | D10: 154.94 | F10: 80 | G10: 160 | H10: 80 | I10: 160 | J10: =(J$7-1)*8 -> 160 | K10: 80 | T10: =(T$7-1)*8 -> 152 | U10: =(U$7-1)*8 -> 152 | V10: =(V$7-1)*8 -> 160 | W10: =(W$7-1)*8 -> 152 | X10: =(X$7-1)*8 -> 160 | Y10: =(Y$7-1)*8 -> 168 | Z10: =(Z$7-1)*8 -> 176 | AA10: =(AA$7-1)*8 -> 144 | ... AS10: =(AS$7-1)*8 -> 152
A11: Gohil, Shailendra | B11: TechSur | C11: Systems Integration Engineer | D11: 154.94 | F11: 80 | G11: 160 | H11: 80 | I11: 160 | J11: =(J$7-1)*8 -> 160 | K11: =(K$7-1)*8 -> 152 | L11: =L12*0.5 -> 80 | M11: 20 | N11: 20 | O11: 20 | P11: 20 | Q11: 20 | R11: 20 | T11: =(T$7-1)*8 -> 152 | U11: =(U$7-1)*8 -> 152 | V11: =(V$7-1)*8 -> 160 | W11: =(W$7-1)*8 -> 152 | X11: =(X$7-1)*8 -> 160 | Y11: =(Y$7-1)*8 -> 168 | Z11: =(Z$7-1)*8 -> 176 | AA11: =(AA$7-1)*8 -> 144 | ... AS11: =(AS$7-1)*8 -> 152
A12: Gupta, Madhur | B12: TechSur | C12: Business Analyst - Senior | D12: 122.45 | F12: 80 | G12: 160 | H12: 80 | I12: 160 | J12: =(J$7-1)*8 -> 160 | K12: =(K$7-1)*8 -> 152 | L12: =(L$7-1)*8 -> 160 | M12: =(M$7-1)*8 -> 168 | N12: =(N$7-1)*8 -> 176 | O12: =(O$7-1)*8 -> 144 | P12: =(P$7-1)*8 -> 176 | Q12: =(Q$7-1)*8 -> 168 | R12: 72
A13: Jain, Harsh | B13: JB Management | C13: Systems Integration Engineer | D13: 154.94 | F13: 80 | G13: 160 | H13: 80 | I13: 160 | J13: =(J$7-1)*8 -> 160 | K13: =(K$7-1)*8 -> 152 | L13: =(L$7-1)*8 -> 160 | M13: =(M$7-1)*8 -> 168 | N13: =(N$7-1)*8 -> 176 | O13: =(O$7-1)*8 -> 144 | P13: =((P$7-1)*8)-40 -> 136 | Q13: =(Q$7-1)*8 -> 168 | R13: 72
A14: Kumar, Manoj | B14: JB Management | C14: Systems Integration Engineer | D14: 154.94 | F14: 80 | G14: 160 | H14: 80 | I14: 160 | J14: =(J$7-1)*8 -> 160 | K14: =152-40 -> 112
A15: Sivaprakasam, Vijay | B15: TechSur | C15: Systems Integration Engineer | D15: 154.94 | F15: 80 | G15: 160 | H15: 80 | I15: 160 | J15: =(J$7-1)*8 -> 160 | K15: =(K$7-1)*8 -> 152 | L15: =(L$7-1)*8 -> 160 | M15: =(M$7-1)*8 -> 168 | N15: =((N$7-1)*8)-40 -> 136 | O15: =(O$7-1)*8 -> 144 | P15: =(P$7-1)*8 -> 176 | Q15: =(Q$7-1)*8 -> 168 | R15: 72
A16: Molabanti, Mohana | B16: TechSur | C16: Systems Integration Engineer | D16: 154.94 | K16: 40 | L16: =(L$7-1)*8 -> 160 | M16: =(M$7-1)*8 -> 168 | N16: =(N$7-1)*8 -> 176 | O16: =(O$7-1)*8 -> 144 | P16: =(P$7-1)*8 -> 176 | Q16: =(Q$7-1)*8 -> 168 | R16: 72
A17: Awodeu, Olusola | B17: TechSur | C17: Systems Integration Engineer | D17: 154.94 | K17: 40 | L17: =(L$7-1)*8 -> 160 | M17: =(M$7-1)*8 -> 168 | N17: =((N$7-1)*8)-24 -> 152 | O17: =(O$7-1)*8 -> 144 | P17: =(P$7-1)*8 -> 176 | Q17: =(Q$7-1)*8 -> 168 | R17: 72
A18: Devarshi Pathak | B18: TechSur | C18: Systems Integration Engineer | D18: 154.94 | P18: 80 | Q18: 168 | R18: 72
E40: =SUM(E10:E39) -> 0 | F40: =SUM(F10:F39) -> 480 | G40: =SUM(G10:G39) -> 960 | H40: =SUM(H10:H39) -> 480 | I40: =SUM(I10:I39) -> 960 | J40: =SUM(J10:J39) -> 960 | K40: =SUM(K10:K39) -> 880 | L40: =SUM(L10:L39) -> 880 | ... R40: =SUM(R10:R39) -> 452
A42: Hours Actual
E43: 2025 | J43: 2026 | V43: 2026 | AH43: 2027
A44: Name | B44: Company | C44: LCAT | D44: Rate | E44: 8 | F44: 9 | G44: 10 | H44: 11 | I44: 12 | J44: 1 | K44: 2 | L44: 3 | M44: 4 | N44: 5 | O44: 6 | P44: 7 | Q44: 8 | R44: 9 | S44: 10 | T44: 11 | U44: 12 | V44: 1 | W44: 2 | X44: 3 | Y44: 4 | Z44: 5 | AA44: 6 | AB44: 7 | AC44: 8 | AD44: 9 | AE44: 10 | AF44: 11 | AG44: 12 | AH44: 1 | AI44: 2 | AJ44: 3 | AK44: 4 | AL44: 5 | AM44: 6 | AN44: 7 | AO44: 8 | AP44: 9 | AQ44: 10 | AR44: 11 | AS44: 12
A45: =A10 -> Bulchandani, Kapil | B45: =B10 -> TechSur | C45: =C10 -> Systems Integration Engineer | D45: =D10 -> 154.94 | F45: 96 | G45: 96 | H45: 80 | I45: 176 | J45: 118.5 | K45: 38 | L45: 0 | M45: 0 | N45: 0 | O45: 0 | P45: 0
A46: =A11 -> Gohil, Shailendra | B46: =B11 -> TechSur | C46: =C11 -> Systems Integration Engineer | D46: =D11 -> 154.94 | F46: 96 | G46: 96 | H46: 20 | I46: 138 | J46: 112 | K46: 130 | L46: 63 | M46: 11 | N46: 0 | O46: 0 | P46: 0
A47: =A12 -> Gupta, Madhur | B47: =B12 -> TechSur | C47: =C12 -> Business Analyst - Senior | D47: =D12 -> 122.45 | F47: 92 | G47: 0 | H47: 80 | I47: 148 | J47: 160 | K47: 152 | L47: 176 | M47: 176 | N47: 160 | O47: 168 | P47: 176
A48: =A13 -> Jain, Harsh | B48: =B13 -> JB Management | C48: =C13 -> Systems Integration Engineer | D48: =D13 -> 154.94 | F48: 96 | G48: 96 | H48: 80 | I48: 176 | J48: 160 | K48: 152 | L48: 168 | M48: 176 | N48: 160 | O48: 168 | P48: 128
A49: =A14 -> Kumar, Manoj | B49: =B14 -> JB Management | C49: =C14 -> Systems Integration Engineer | D49: =D14 -> 154.94 | F49: 96 | G49: 96 | H49: 80 | I49: 176 | J49: 160 | K49: 136 | L49: 0 | M49: 0 | N49: 0 | O49: 0 | P49: 0
A50: =A15 -> Sivaprakasam, Vijay | B50: =B15 -> TechSur | C50: =C15 -> Systems Integration Engineer | D50: =D15 -> 154.94 | F50: 96 | G50: 96 | H50: 32 | I50: 176 | J50: 160 | K50: 112 | L50: 176 | M50: 176 | N50: 160 | O50: 168 | P50: 176
A51: =A16 -> Molabanti, Mohana | B51: =B16 -> TechSur | C51: =C16 -> Systems Integration Engineer | D51: =D16 -> 154.94 | K51: 16 | L51: 176 | M51: 176 | N51: 160 | O51: 168 | P51: 172
A52: =A17 -> Awodeu, Olusola | B52: =B17 -> TechSur | C52: =C17 -> Systems Integration Engineer | D52: =D17 -> 154.94 | K52: 16 | L52: 176 | M52: 176 | N52: 160 | O52: 168 | P52: 176
A53: =A18 -> Devarshi Pathak | B53: =B18 -> TechSur | C53: =C18 -> Systems Integration Engineer | D53: =D18 -> 154.94
A54: =A19 -> 0 | B54: =B19 -> 0 | C54: =C19 -> 0 | D54: =D19 -> 0
E75: =SUM(E45:E74) -> 0 | F75: =SUM(F45:F74) -> 572 | G75: =SUM(G45:G74) -> 480 | H75: =SUM(H45:H74) -> 372 | I75: =SUM(I45:I74) -> 990 | J75: =SUM(J45:J74) -> 870.5 | K75: =SUM(K45:K74) -> 752 | L75: =SUM(L45:L74) -> 935 | ... AS75: =SUM(AS45:AS74) -> 0
A77: Forecast Revenue by Resource
E78: 2025 | J78: 2026 | V78: 2026 | AH78: 2027
A79: Name | B79: Company | C79: LCAT | D79: Rate | E79: 8 | F79: 9 | G79: 10 | H79: 11 | I79: 12 | J79: 1 | K79: 2 | L79: 3 | M79: 4 | N79: 5 | O79: 6 | P79: 7 | Q79: 8 | R79: 9 | S79: 10 | T79: 11 | U79: 12 | V79: 1 | W79: 2 | X79: 3 | Y79: 4 | Z79: 5 | AA79: 6 | AB79: 7 | AC79: 8 | AD79: 9 | AE79: 10 | AF79: 11 | AG79: 12 | AH79: 1 | AI79: 2 | AJ79: 3 | AK79: 4 | AL79: 5 | AM79: 6 | AN79: 7 | AO79: 8 | AP79: 9 | AQ79: 10 | AR79: 11 | AS79: 12
A80: =A10 -> Bulchandani, Kapil | B80: =B10 -> TechSur | C80: =C10 -> Systems Integration Engineer | D80: =D10 -> 154.94 | E80: =E10*$D10 -> 0 | F80: =F10*$D10 -> 12395.2 | G80: =G10*$D10 -> 24790.4 | H80: =H10*$D10 -> 12395.2 | I80: =I10*$D10 -> 24790.4 | J80: =J10*$D10 -> 24790.4 | K80: =K10*$D10 -> 12395.2 | L80: =L10*$D10 -> 0 | ... AS80: =AS10*$D10 -> 23550.88
A81: =A11 -> Gohil, Shailendra | B81: =B11 -> TechSur | C81: =C11 -> Systems Integration Engineer | D81: =D11 -> 154.94 | E81: =E11*$D11 -> 0 | F81: =F11*$D11 -> 12395.2 | G81: =G11*$D11 -> 24790.4 | H81: =H11*$D11 -> 12395.2 | I81: =I11*$D11 -> 24790.4 | J81: =J11*$D11 -> 24790.4 | K81: =K11*$D11 -> 23550.88 | L81: =L11*$D11 -> 12395.2 | ... AS81: =AS11*$D11 -> 23550.88
A82: =A12 -> Gupta, Madhur | B82: =B12 -> TechSur | C82: =C12 -> Business Analyst - Senior | D82: =D12 -> 122.45 | E82: =E12*$D12 -> 0 | F82: =F12*$D12 -> 9796 | G82: =G12*$D12 -> 19592 | H82: =H12*$D12 -> 9796 | I82: =I12*$D12 -> 19592 | J82: =J12*$D12 -> 19592 | K82: =K12*$D12 -> 18612.4 | L82: =L12*$D12 -> 19592 | ... AS82: =AS12*$D12 -> 0
A83: =A13 -> Jain, Harsh | B83: =B13 -> JB Management | C83: =C13 -> Systems Integration Engineer | D83: =D13 -> 154.94 | E83: =E13*$D13 -> 0 | F83: =F13*$D13 -> 12395.2 | G83: =G13*$D13 -> 24790.4 | H83: =H13*$D13 -> 12395.2 | I83: =I13*$D13 -> 24790.4 | J83: =J13*$D13 -> 24790.4 | K83: =K13*$D13 -> 23550.88 | L83: =L13*$D13 -> 24790.4 | ... AS83: =AS13*$D13 -> 0
A84: =A14 -> Kumar, Manoj | B84: =B14 -> JB Management | C84: =C14 -> Systems Integration Engineer | D84: =D14 -> 154.94 | E84: =E14*$D14 -> 0 | F84: =F14*$D14 -> 12395.2 | G84: =G14*$D14 -> 24790.4 | H84: =H14*$D14 -> 12395.2 | I84: =I14*$D14 -> 24790.4 | J84: =J14*$D14 -> 24790.4 | K84: =K14*$D14 -> 17353.28 | L84: =L14*$D14 -> 0 | ... AS84: =AS14*$D14 -> 0
A85: =A15 -> Sivaprakasam, Vijay | B85: =B15 -> TechSur | C85: =C15 -> Systems Integration Engineer | D85: =D15 -> 154.94 | E85: =E15*$D15 -> 0 | F85: =F15*$D15 -> 12395.2 | G85: =G15*$D15 -> 24790.4 | H85: =H15*$D15 -> 12395.2 | I85: =I15*$D15 -> 24790.4 | J85: =J15*$D15 -> 24790.4 | K85: =K15*$D15 -> 23550.88 | L85: =L15*$D15 -> 24790.4 | ... AS85: =AS15*$D15 -> 0
A86: =A16 -> Molabanti, Mohana | B86: =B16 -> TechSur | C86: =C16 -> Systems Integration Engineer | D86: =D16 -> 154.94 | E86: =E16*$D16 -> 0 | F86: =F16*$D16 -> 0 | G86: =G16*$D16 -> 0 | H86: =H16*$D16 -> 0 | I86: =I16*$D16 -> 0 | J86: =J16*$D16 -> 0 | K86: =K16*$D16 -> 6197.6 | L86: =L16*$D16 -> 24790.4 | ... AS86: =AS16*$D16 -> 0
A87: =A17 -> Awodeu, Olusola | B87: =B17 -> TechSur | C87: =C17 -> Systems Integration Engineer | D87: =D17 -> 154.94 | E87: =E17*$D17 -> 0 | F87: =F17*$D17 -> 0 | G87: =G17*$D17 -> 0 | H87: =H17*$D17 -> 0 | I87: =I17*$D17 -> 0 | J87: =J17*$D17 -> 0 | K87: =K17*$D17 -> 6197.6 | L87: =L17*$D17 -> 24790.4 | ... AS87: =AS17*$D17 -> 0
A88: =A18 -> Devarshi Pathak | B88: =B18 -> TechSur | C88: =C18 -> Systems Integration Engineer | D88: =D18 -> 154.94 | E88: =E18*$D18 -> 0 | F88: =F18*$D18 -> 0 | G88: =G18*$D18 -> 0 | H88: =H18*$D18 -> 0 | I88: =I18*$D18 -> 0 | J88: =J18*$D18 -> 0 | K88: =K18*$D18 -> 0 | L88: =L18*$D18 -> 0 | ... AS88: =AS18*$D18 -> 0
E89: =E19*$D19 -> 0 | F89: =F19*$D19 -> 0 | G89: =G19*$D19 -> 0 | H89: =H19*$D19 -> 0 | I89: =I19*$D19 -> 0 | J89: =J19*$D19 -> 0 | K89: =K19*$D19 -> 0 | L89: =L19*$D19 -> 0 | ... AS89: =AS19*$D19 -> 0
E90: =E20*$D20 -> 0 | F90: =F20*$D20 -> 0 | G90: =G20*$D20 -> 0 | H90: =H20*$D20 -> 0 | I90: =I20*$D20 -> 0 | J90: =J20*$D20 -> 0 | K90: =K20*$D20 -> 0 | L90: =L20*$D20 -> 0 | ... AS90: =AS20*$D20 -> 0
E91: =E21*$D21 -> 0 | F91: =F21*$D21 -> 0 | G91: =G21*$D21 -> 0 | H91: =H21*$D21 -> 0 | I91: =I21*$D21 -> 0 | J91: =J21*$D21 -> 0 | K91: =K21*$D21 -> 0 | L91: =L21*$D21 -> 0 | ... AS91: =AS21*$D21 -> 0
E92: =E22*$D22 -> 0 | F92: =F22*$D22 -> 0 | G92: =G22*$D22 -> 0 | H92: =H22*$D22 -> 0 | I92: =I22*$D22 -> 0 | J92: =J22*$D22 -> 0 | K92: =K22*$D22 -> 0 | L92: =L22*$D22 -> 0 | ... AS92: =AS22*$D22 -> 0
E93: =E23*$D23 -> 0 | F93: =F23*$D23 -> 0 | G93: =G23*$D23 -> 0 | H93: =H23*$D23 -> 0 | I93: =I23*$D23 -> 0 | J93: =J23*$D23 -> 0 | K93: =K23*$D23 -> 0 | L93: =L23*$D23 -> 0 | ... AS93: =AS23*$D23 -> 0
E94: =E24*$D24 -> 0 | F94: =F24*$D24 -> 0 | G94: =G24*$D24 -> 0 | H94: =H24*$D24 -> 0 | I94: =I24*$D24 -> 0 | J94: =J24*$D24 -> 0 | K94: =K24*$D24 -> 0 | L94: =L24*$D24 -> 0 | ... AS94: =AS24*$D24 -> 0
E95: =E25*$D25 -> 0 | F95: =F25*$D25 -> 0 | G95: =G25*$D25 -> 0 | H95: =H25*$D25 -> 0 | I95: =I25*$D25 -> 0 | J95: =J25*$D25 -> 0 | K95: =K25*$D25 -> 0 | L95: =L25*$D25 -> 0 | ... AS95: =AS25*$D25 -> 0
E96: =E26*$D26 -> 0 | F96: =F26*$D26 -> 0 | G96: =G26*$D26 -> 0 | H96: =H26*$D26 -> 0 | I96: =I26*$D26 -> 0 | J96: =J26*$D26 -> 0 | K96: =K26*$D26 -> 0 | L96: =L26*$D26 -> 0 | ... AS96: =AS26*$D26 -> 0
E110: =SUM(E80:E109) -> 0 | F110: =SUM(F80:F109) -> 71772 | G110: =SUM(G80:G109) -> 143544 | H110: =SUM(H80:H109) -> 71772 | I110: =SUM(I80:I109) -> 143544 | J110: =SUM(J80:J109) -> 143544 | K110: =SUM(K80:K109) -> 131408.72 | L110: =SUM(L80:L109) -> 131148.8 | ... AS110: =SUM(AS80:AS109) -> 47101.76
A112: T&M Revenue by Resource
E113: 2025 | J113: 2026 | V113: 2027 | AH113: 2028
A114: Name | B114: Company | C114: LCAT | D114: Rate | E114: 8 | F114: 9 | G114: 10 | H114: 11 | I114: 12 | J114: 1 | K114: 2 | L114: 3 | M114: 4 | N114: 5 | O114: 6 | P114: 7 | Q114: 8 | R114: 9 | S114: 10 | T114: 11 | U114: 12 | V114: 1 | W114: 2 | X114: 3 | Y114: 4 | Z114: 5 | AA114: 6 | AB114: 7 | AC114: 8 | AD114: 9 | AE114: 10 | AF114: 11 | AG114: 12 | AH114: 1 | AI114: 2 | AJ114: 3 | AK114: 4 | AL114: 5 | AM114: 6 | AN114: 7 | AO114: 8 | AP114: 9 | AQ114: 10 | AR114: 11 | AS114: 12
A115: =A10 -> Bulchandani, Kapil | B115: =B10 -> TechSur | C115: =C10 -> Systems Integration Engineer | D115: =D10 -> 154.94 | E115: =E45*$D115 -> 0 | F115: =F45*$D115 -> 14874.24 | G115: =G45*$D115 -> 14874.24 | H115: =H45*$D115 -> 12395.2 | I115: =I45*$D115 -> 27269.44 | J115: =J45*$D115 -> 18360.39 | K115: =K45*$D115 -> 5887.72 | L115: =L45*$D115 -> 0 | ... AS115: =AS45*$D115 -> 0
A116: =A11 -> Gohil, Shailendra | B116: =B11 -> TechSur | C116: =C11 -> Systems Integration Engineer | D116: =D11 -> 154.94 | E116: =E46*$D116 -> 0 | F116: =F46*$D116 -> 14874.24 | G116: =G46*$D116 -> 14874.24 | H116: =H46*$D116 -> 3098.8 | I116: =I46*$D116 -> 21381.72 | J116: =J46*$D116 -> 17353.28 | K116: =K46*$D116 -> 20142.2 | L116: =L46*$D116 -> 9761.22 | ... AS116: =AS46*$D116 -> 0
A117: =A12 -> Gupta, Madhur | B117: =B12 -> TechSur | C117: =C12 -> Business Analyst - Senior | D117: =D12 -> 122.45 | E117: =E47*$D117 -> 0 | F117: =F47*$D117 -> 11265.4 | G117: =G47*$D117 -> 0 | H117: =H47*$D117 -> 9796 | I117: =I47*$D117 -> 18122.6 | J117: =J47*$D117 -> 19592 | K117: =K47*$D117 -> 18612.4 | L117: =L47*$D117 -> 21551.2 | ... AS117: =AS47*$D117 -> 0
A118: =A13 -> Jain, Harsh | B118: =B13 -> JB Management | C118: =C13 -> Systems Integration Engineer | D118: =D13 -> 154.94 | E118: =E48*$D118 -> 0 | F118: =F48*$D118 -> 14874.24 | G118: =G48*$D118 -> 14874.24 | H118: =H48*$D118 -> 12395.2 | I118: =I48*$D118 -> 27269.44 | J118: =J48*$D118 -> 24790.4 | K118: =K48*$D118 -> 23550.88 | L118: =L48*$D118 -> 26029.92 | ... AS118: =AS48*$D118 -> 0
A119: =A14 -> Kumar, Manoj | B119: =B14 -> JB Management | C119: =C14 -> Systems Integration Engineer | D119: =D14 -> 154.94 | E119: =E49*$D119 -> 0 | F119: =F49*$D119 -> 14874.24 | G119: =G49*$D119 -> 14874.24 | H119: =H49*$D119 -> 12395.2 | I119: =I49*$D119 -> 27269.44 | J119: =J49*$D119 -> 24790.4 | K119: =K49*$D119 -> 21071.84 | L119: =L49*$D119 -> 0 | ... AS119: =AS49*$D119 -> 0
A120: =A15 -> Sivaprakasam, Vijay | B120: =B15 -> TechSur | C120: =C15 -> Systems Integration Engineer | D120: =D15 -> 154.94 | E120: =E50*$D120 -> 0 | F120: =F50*$D120 -> 14874.24 | G120: =G50*$D120 -> 14874.24 | H120: =H50*$D120 -> 4958.08 | I120: =I50*$D120 -> 27269.44 | J120: =J50*$D120 -> 24790.4 | K120: =K50*$D120 -> 17353.28 | L120: =L50*$D120 -> 27269.44 | ... AS120: =AS50*$D120 -> 0
A121: =A16 -> Molabanti, Mohana | B121: =B16 -> TechSur | C121: =C16 -> Systems Integration Engineer | D121: =D16 -> 154.94 | E121: =E51*$D121 -> 0 | F121: =F51*$D121 -> 0 | G121: =G51*$D121 -> 0 | H121: =H51*$D121 -> 0 | I121: =I51*$D121 -> 0 | J121: =J51*$D121 -> 0 | K121: =K51*$D121 -> 2479.04 | L121: =L51*$D121 -> 27269.44 | ... AS121: =AS51*$D121 -> 0
A122: Awodeu, Olusola | B122: TechSur | C122: Systems Integration Engineer | D122: 154.94 | E122: =E52*$D122 -> 0 | F122: =F52*$D122 -> 0 | G122: =G52*$D122 -> 0 | H122: =H52*$D122 -> 0 | I122: =I52*$D122 -> 0 | J122: =J52*$D122 -> 0 | K122: =K52*$D122 -> 2479.04 | L122: =L52*$D122 -> 27269.44 | ... AS122: =AS52*$D122 -> 0
A123: =A18 -> Devarshi Pathak | B123: =B18 -> TechSur | C123: =C18 -> Systems Integration Engineer | D123: =D18 -> 154.94 | E123: =E53*$D123 -> 0 | F123: =F53*$D123 -> 0 | G123: =G53*$D123 -> 0 | H123: =H53*$D123 -> 0 | I123: =I53*$D123 -> 0 | J123: =J53*$D123 -> 0 | K123: =K53*$D123 -> 0 | L123: =L53*$D123 -> 0 | ... AS123: =AS53*$D123 -> 0
E124: =E54*$D124 -> 0 | F124: =F54*$D124 -> 0 | G124: =G54*$D124 -> 0 | H124: =H54*$D124 -> 0 | I124: =I54*$D124 -> 0 | J124: =J54*$D124 -> 0 | K124: =K54*$D124 -> 0 | L124: =L54*$D124 -> 0 | ... AS124: =AS54*$D124 -> 0
E125: =E55*$D125 -> 0 | F125: =F55*$D125 -> 0 | G125: =G55*$D125 -> 0 | H125: =H55*$D125 -> 0 | I125: =I55*$D125 -> 0 | J125: =J55*$D125 -> 0 | K125: =K55*$D125 -> 0 | L125: =L55*$D125 -> 0 | ... AS125: =AS55*$D125 -> 0
E126: =E56*$D126 -> 0 | F126: =F56*$D126 -> 0 | G126: =G56*$D126 -> 0 | H126: =H56*$D126 -> 0 | I126: =I56*$D126 -> 0 | J126: =J56*$D126 -> 0 | K126: =K56*$D126 -> 0 | L126: =L56*$D126 -> 0 | ... AS126: =AS56*$D126 -> 0
E127: =E57*$D127 -> 0 | F127: =F57*$D127 -> 0 | G127: =G57*$D127 -> 0 | H127: =H57*$D127 -> 0 | I127: =I57*$D127 -> 0 | J127: =J57*$D127 -> 0 | K127: =K57*$D127 -> 0 | L127: =L57*$D127 -> 0 | ... AS127: =AS57*$D127 -> 0
Q128: =Q58*$D128 -> 0 | R128: =R58*$D128 -> 0 | S128: =S58*$D128 -> 0 | T128: =T58*$D128 -> 0 | U128: =U58*$D128 -> 0 | V128: =V58*$D128 -> 0 | W128: =W58*$D128 -> 0 | X128: =X58*$D128 -> 0 | ... AS128: =AS58*$D128 -> 0
Q129: =Q59*$D129 -> 0 | R129: =R59*$D129 -> 0 | S129: =S59*$D129 -> 0 | T129: =T59*$D129 -> 0 | U129: =U59*$D129 -> 0 | V129: =V59*$D129 -> 0 | W129: =W59*$D129 -> 0 | X129: =X59*$D129 -> 0 | ... AS129: =AS59*$D129 -> 0
Q130: =Q60*$D130 -> 0 | R130: =R60*$D130 -> 0 | S130: =S60*$D130 -> 0 | T130: =T60*$D130 -> 0 | U130: =U60*$D130 -> 0 | V130: =V60*$D130 -> 0 | W130: =W60*$D130 -> 0 | X130: =X60*$D130 -> 0 | ... AS130: =AS60*$D130 -> 0
Q131: =Q61*$D131 -> 0 | R131: =R61*$D131 -> 0 | S131: =S61*$D131 -> 0 | T131: =T61*$D131 -> 0 | U131: =U61*$D131 -> 0 | V131: =V61*$D131 -> 0 | W131: =W61*$D131 -> 0 | X131: =X61*$D131 -> 0 | ... AS131: =AS61*$D131 -> 0
Q132: =Q62*$D132 -> 0 | R132: =R62*$D132 -> 0 | S132: =S62*$D132 -> 0 | T132: =T62*$D132 -> 0 | U132: =U62*$D132 -> 0 | V132: =V62*$D132 -> 0 | W132: =W62*$D132 -> 0 | X132: =X62*$D132 -> 0 | ... AS132: =AS62*$D132 -> 0
Q133: =Q63*$D133 -> 0 | R133: =R63*$D133 -> 0 | S133: =S63*$D133 -> 0 | T133: =T63*$D133 -> 0 | U133: =U63*$D133 -> 0 | V133: =V63*$D133 -> 0 | W133: =W63*$D133 -> 0 | X133: =X63*$D133 -> 0 | ... AS133: =AS63*$D133 -> 0
Q134: =Q64*$D134 -> 0 | R134: =R64*$D134 -> 0 | S134: =S64*$D134 -> 0 | T134: =T64*$D134 -> 0 | U134: =U64*$D134 -> 0 | V134: =V64*$D134 -> 0 | W134: =W64*$D134 -> 0 | X134: =X64*$D134 -> 0 | ... AS134: =AS64*$D134 -> 0
Q135: =Q65*$D135 -> 0 | R135: =R65*$D135 -> 0 | S135: =S65*$D135 -> 0 | T135: =T65*$D135 -> 0 | U135: =U65*$D135 -> 0 | V135: =V65*$D135 -> 0 | W135: =W65*$D135 -> 0 | X135: =X65*$D135 -> 0 | ... AS135: =AS65*$D135 -> 0
Q136: =Q66*$D136 -> 0 | R136: =R66*$D136 -> 0 | S136: =S66*$D136 -> 0 | T136: =T66*$D136 -> 0 | U136: =U66*$D136 -> 0 | V136: =V66*$D136 -> 0 | W136: =W66*$D136 -> 0 | X136: =X66*$D136 -> 0 | ... AS136: =AS66*$D136 -> 0
Q137: =Q67*$D137 -> 0 | R137: =R67*$D137 -> 0 | S137: =S67*$D137 -> 0 | T137: =T67*$D137 -> 0 | U137: =U67*$D137 -> 0 | V137: =V67*$D137 -> 0 | W137: =W67*$D137 -> 0 | X137: =X67*$D137 -> 0 | ... AS137: =AS67*$D137 -> 0
Q138: =Q68*$D138 -> 0 | R138: =R68*$D138 -> 0 | S138: =S68*$D138 -> 0 | T138: =T68*$D138 -> 0 | U138: =U68*$D138 -> 0 | V138: =V68*$D138 -> 0 | W138: =W68*$D138 -> 0 | X138: =X68*$D138 -> 0 | ... AS138: =AS68*$D138 -> 0
Q139: =Q69*$D139 -> 0 | R139: =R69*$D139 -> 0 | S139: =S69*$D139 -> 0 | T139: =T69*$D139 -> 0 | U139: =U69*$D139 -> 0 | V139: =V69*$D139 -> 0 | W139: =W69*$D139 -> 0 | X139: =X69*$D139 -> 0 | ... AS139: =AS69*$D139 -> 0
... Q144: =Q74*$D144 -> 0 | R144: =R74*$D144 -> 0 | S144: =S74*$D144 -> 0 | T144: =T74*$D144 -> 0 | U144: =U74*$D144 -> 0 | V144: =V74*$D144 -> 0 | W144: =W74*$D144 -> 0 | X144: =X74*$D144 -> 0 | ... AS144: =AS74*$D144 -> 0
E145: =SUM(E115:E144) -> 0 | F145: =SUM(F115:F144) -> 85636.6 | G145: =SUM(G115:G144) -> 74371.2 | H145: =SUM(H115:H144) -> 55038.48 | I145: =SUM(I115:I144) -> 148582.08 | J145: =SUM(J115:J144) -> 129676.87 | K145: =SUM(K115:K144) -> 111576.4 | L145: =SUM(L115:L144) -> 139150.66 | ... AS145: =SUM(AS115:AS144) -> 0 | AU145: =SUM(E145:AT145) -> 1242382.6
A147: Invoice and Revenue Analysis
E148: 2025 | J148: 2026 | V148: 2027 | AH148: 2028
B149: Total | C149: Invoice | D149: Date | E149: 8 | F149: 9 | G149: 10 | H149: 11 | I149: 12 | J149: 1 | K149: 2 | L149: 3 | M149: 4 | N149: 5 | O149: 6 | P149: 7 | Q149: 8 | R149: 9 | S149: 10 | T149: 11 | U149: 12 | V149: 1 | W149: 2 | X149: 3 | Y149: 4 | Z149: 5 | AA149: 6 | AB149: 7 | AC149: 8 | AD149: 9 | AE149: 10 | AF149: 11 | AG149: 12 | AH149: 1 | AI149: 2 | AJ149: 3 | AK149: 4 | AL149: 5 | AM149: 6 | AN149: 7 | AO149: 8 | AP149: 9 | AQ149: 10 | AR149: 11 | AS149: 12
C150: I01187 - Sept | D150: 45936 | F150: 85636.6
C151: I01208 - Oct | D151: 45967 | G151: 74371.2
C152: I01232 - Nov | D152: 46000 | H152: 55038.48
C153: I01259 - Dec | D153: 46028 | I153: 148582.08
C154: I01287 - Jan | D154: 46059 | J154: 129676.87
C155: I01307 - Feb | D155: 46086 | K155: 111576.4
C156: I01345 - Mar | D156: 46116 | L156: 139150.66
C157: I01378 - Apr | D157: 46142 | M157: =M145 -> 132333.3
C158: I01400 - May | D158: 46176 | N158: 118753.6
C159: Io1433 - June | D159: 46209 | O159: 124691.28
C160: I01479 - July | D160: 46238 | P160: 122572.08
B163: =SUM(B150:B162) -> 0 | D163: Revenue | E163: =SUM(E150:E162) -> 0 | F163: =SUM(F150:F162) -> 85636.6 | G163: =SUM(G150:G162) -> 74371.2 | H163: =SUM(H150:H162) -> 55038.48 | I163: =SUM(I150:I162) -> 148582.08 | J163: =SUM(J150:J162) -> 129676.87 | K163: =SUM(K150:K162) -> 111576.4 | L163: =SUM(L150:L162) -> 139150.66 | ... AS163: =SUM(AS150:AS162) -> 0 | AU163: =SUM(E163:AT163) -> 1242382.6
F166: 9 | G166: 10 | H166: 11 | I166: 12 | J166: 1 | K166: 2 | L166: 3 | M166: 4 | N166: 5 | O166: 6 | P166: 7 | Q166: 8 | R166: 9
E167: Forecast Rev | F167: =F110 -> 71772 | G167: =F167+G110 -> 215316 | H167: =G167+H110 -> 287088 | I167: =H167+I110 -> 430632 | J167: =I167+J110 -> 574176 | K167: =J167+K110 -> 705584.72 | L167: =K167+L110 -> 836733.52 | M167: =L167+M110 -> 964523.6 | N167: =M167+N110 -> 1088335.2 | ... R167: =Q167+R110 -> 1559751.2
E168: Actual Rev | F168: =F163 -> 85636.6 | G168: =G163+F168 -> 160007.8 | H168: =G168+H163 -> 215046.28 | I168: =H168+I163 -> 363628.36 | J168: =I168+J163 -> 493305.23 | K168: =J168+K163 -> 604881.63 | L168: =K168+L163 -> 744032.29 | M168: =L168+M163 -> 876365.59 | N168: =M168+N163 -> 995119.19 | O168: =N168+O163 -> 1119810.5 | ... Q168: =P168+Q163 -> 1242382.6 | R168: =Q168+P163 -> 1364954.6
...

Sheet AO Call 13.2
A2: Project: | B2: Call 13 - DevSecOps
A3: PoP: | B3: 9/13/26 - 9/12/27 | C3: OP2: 9/13/26 - 9/12/27
A4: Funded Ceiling: | B4: 1756992
A6: Hours Forecast
D7: Working Days | E7: 22 | F7: 18 | G7: 21 | H7: 20 | I7: 20 | J7: 21 | K7: 20 | L7: 21 | M7: 22 | N7: 23 | O7: 19 | P7: 23 | Q7: 22 | R7: 18 | S7: 21 | T7: 20 | U7: 20 | V7: 21 | W7: 20 | X7: 21 | Y7: 22 | Z7: 23 | AA7: 19 | AB7: 23 | AC7: 22 | AD7: 18 | AE7: 21 | AF7: 20 | AG7: 20 | AH7: 21 | AI7: 20 | AJ7: 21 | AK7: 22 | AL7: 23 | AM7: 19 | AN7: 23 | AO7: 22 | AP7: 18 | AQ7: 21 | AR7: 20 | AS7: 20
E8: 2026 | J8: 2027 | V8: 2028 | AH8: 2029
A9: Name | B9: Company | C9: LCAT | D9: Rate | E9: 8 | F9: 9 | G9: 10 | H9: 11 | I9: 12 | J9: 1 | K9: 2 | L9: 3 | M9: 4 | N9: 5 | O9: 6 | P9: 7 | Q9: 8 | R9: 9 | S9: 10 | T9: 11 | U9: 12 | V9: 1 | W9: 2 | X9: 3 | Y9: 4 | Z9: 5 | AA9: 6 | AB9: 7 | AC9: 8 | AD9: 9 | AE9: 10 | AF9: 11 | AG9: 12 | AH9: 1 | AI9: 2 | AJ9: 3 | AK9: 4 | AL9: 5 | AM9: 6 | AN9: 7 | AO9: 8 | AP9: 9 | AQ9: 10 | AR9: 11 | AS9: 12
A10: Gupta, Madhur | B10: TechSur | C10: Business Analyst - Senior | D10: 124.9 | F10: 80 | G10: 160 | H10: 80 | I10: 160 | J10: =(J$7-1)*8 -> 160 | K10: =(K$7-1)*8 -> 152 | L10: =(L$7-1)*8 -> 160 | M10: =(M$7-1)*8 -> 168 | N10: =(N$7-1)*8 -> 176 | O10: =(O$7-1)*8 -> 144 | P10: =(P$7-1)*8 -> 176 | Q10: =(Q$7-1)*8 -> 168 | R10: 72
A11: Jain, Harsh | B11: JB Management | C11: Systems Integration Engineer | D11: 158.04 | F11: 80 | G11: 160 | H11: 80 | I11: 160 | J11: =(J$7-1)*8 -> 160 | K11: =(K$7-1)*8 -> 152 | L11: =(L$7-1)*8 -> 160 | M11: =(M$7-1)*8 -> 168 | N11: =(N$7-1)*8 -> 176 | O11: =(O$7-1)*8 -> 144 | P11: =(P$7-1)*8 -> 176 | Q11: =(Q$7-1)*8 -> 168 | R11: 72
A12: Sivaprakasam, Vijay | B12: TechSur | C12: Systems Integration Engineer | D12: 158.04 | F12: 80 | G12: 160 | H12: 80 | I12: 160 | J12: =(J$7-1)*8 -> 160 | K12: =(K$7-1)*8 -> 152 | L12: =(L$7-1)*8 -> 160 | M12: =(M$7-1)*8 -> 168 | N12: =(N$7-1)*8 -> 176 | O12: =(O$7-1)*8 -> 144 | P12: =(P$7-1)*8 -> 176 | Q12: =(Q$7-1)*8 -> 168 | R12: 72
A13: Molabanti, Mohana | B13: TechSur | C13: Systems Integration Engineer | D13: 158.04 | F13: 80 | G13: 160 | H13: 80 | I13: 160 | J13: =(J$7-1)*8 -> 160 | K13: =(K$7-1)*8 -> 152 | L13: =(L$7-1)*8 -> 160 | M13: =(M$7-1)*8 -> 168 | N13: =(N$7-1)*8 -> 176 | O13: =(O$7-1)*8 -> 144 | P13: =(P$7-1)*8 -> 176 | Q13: =(Q$7-1)*8 -> 168 | R13: 72
A14: Awodeu, Olusola | B14: TechSur | C14: Systems Integration Engineer | D14: 158.04 | F14: 80 | G14: 160 | H14: 80 | I14: 160 | J14: =(J$7-1)*8 -> 160 | K14: =(K$7-1)*8 -> 152 | L14: =(L$7-1)*8 -> 160 | M14: =(M$7-1)*8 -> 168 | N14: =(N$7-1)*8 -> 176 | O14: =(O$7-1)*8 -> 144 | P14: =(P$7-1)*8 -> 176 | Q14: =(Q$7-1)*8 -> 168 | R14: 72
A15: Devarshi Pathak | B15: TechSur | C15: Systems Integration Engineer | D15: 158.04 | F15: 80 | G15: 160 | H15: 80 | I15: 160 | J15: =(J$7-1)*8 -> 160 | K15: =(K$7-1)*8 -> 152 | L15: =(L$7-1)*8 -> 160 | M15: =(M$7-1)*8 -> 168 | N15: =(N$7-1)*8 -> 176 | O15: =(O$7-1)*8 -> 144 | P15: =(P$7-1)*8 -> 176 | Q15: =(Q$7-1)*8 -> 168 | R15: 72
E40: =SUM(E10:E39) -> 0 | F40: =SUM(F10:F39) -> 480 | G40: =SUM(G10:G39) -> 960 | H40: =SUM(H10:H39) -> 480 | I40: =SUM(I10:I39) -> 960 | J40: =SUM(J10:J39) -> 960 | K40: =SUM(K10:K39) -> 912 | L40: =SUM(L10:L39) -> 960 | ... R40: =SUM(R10:R39) -> 432
A42: Hours Actual
E43: 2026 | J43: 2027 | V43: 2028 | AH43: 2029
A44: Name | B44: Company | C44: LCAT | D44: Rate | E44: 8 | F44: 9 | G44: 10 | H44: 11 | I44: 12 | J44: 1 | K44: 2 | L44: 3 | M44: 4 | N44: 5 | O44: 6 | P44: 7 | Q44: 8 | R44: 9 | S44: 10 | T44: 11 | U44: 12 | V44: 1 | W44: 2 | X44: 3 | Y44: 4 | Z44: 5 | AA44: 6 | AB44: 7 | AC44: 8 | AD44: 9 | AE44: 10 | AF44: 11 | AG44: 12 | AH44: 1 | AI44: 2 | AJ44: 3 | AK44: 4 | AL44: 5 | AM44: 6 | AN44: 7 | AO44: 8 | AP44: 9 | AQ44: 10 | AR44: 11 | AS44: 12
A45: =A10 -> Gupta, Madhur | B45: =B10 -> TechSur | C45: =C10 -> Business Analyst - Senior | D45: =D10 -> 124.9
A46: =A11 -> Jain, Harsh | B46: =B11 -> JB Management | C46: =C11 -> Systems Integration Engineer | D46: =D11 -> 158.04
A47: =A12 -> Sivaprakasam, Vijay | B47: =B12 -> TechSur | C47: =C12 -> Systems Integration Engineer | D47: =D12 -> 158.04
A48: =A13 -> Molabanti, Mohana | B48: =B13 -> TechSur | C48: =C13 -> Systems Integration Engineer | D48: =D13 -> 158.04
A49: =A14 -> Awodeu, Olusola | B49: =B14 -> TechSur | C49: =C14 -> Systems Integration Engineer | D49: =D14 -> 158.04
A50: =A15 -> Devarshi Pathak | B50: =B15 -> TechSur | C50: =C15 -> Systems Integration Engineer | D50: =D15 -> 158.04
A51: =A16 -> 0 | B51: =B16 -> 0 | C51: =C16 -> 0 | D51: =D16 -> 0
A52: =A17 -> 0 | B52: =B17 -> 0 | C52: =C17 -> 0 | D52: =D17 -> 0
A53: =A18 -> 0 | B53: =B18 -> 0 | C53: =C18 -> 0 | D53: =D18 -> 0
A54: =A19 -> 0 | B54: =B19 -> 0 | C54: =C19 -> 0 | D54: =D19 -> 0
E75: =SUM(E45:E74) -> 0 | F75: =SUM(F45:F74) -> 0 | G75: =SUM(G45:G74) -> 0 | H75: =SUM(H45:H74) -> 0 | I75: =SUM(I45:I74) -> 0 | J75: =SUM(J45:J74) -> 0 | K75: =SUM(K45:K74) -> 0 | L75: =SUM(L45:L74) -> 0 | ... AS75: =SUM(AS45:AS74) -> 0
A77: Forecast Revenue by Resource
E78: 2026 | J78: 2027 | V78: 2028 | AH78: 2029
A79: Name | B79: Company | C79: LCAT | D79: Rate | E79: 8 | F79: 9 | G79: 10 | H79: 11 | I79: 12 | J79: 1 | K79: 2 | L79: 3 | M79: 4 | N79: 5 | O79: 6 | P79: 7 | Q79: 8 | R79: 9 | S79: 10 | T79: 11 | U79: 12 | V79: 1 | W79: 2 | X79: 3 | Y79: 4 | Z79: 5 | AA79: 6 | AB79: 7 | AC79: 8 | AD79: 9 | AE79: 10 | AF79: 11 | AG79: 12 | AH79: 1 | AI79: 2 | AJ79: 3 | AK79: 4 | AL79: 5 | AM79: 6 | AN79: 7 | AO79: 8 | AP79: 9 | AQ79: 10 | AR79: 11 | AS79: 12
A80: =A10 -> Gupta, Madhur | B80: =B10 -> TechSur | C80: =C10 -> Business Analyst - Senior | D80: =D10 -> 124.9 | E80: =E10*$D10 -> 0 | F80: =F10*$D10 -> 9992 | G80: =G10*$D10 -> 19984 | H80: =H10*$D10 -> 9992 | I80: =I10*$D10 -> 19984 | J80: =J10*$D10 -> 19984 | K80: =K10*$D10 -> 18984.8 | L80: =L10*$D10 -> 19984 | ... AS80: =AS10*$D10 -> 0
A81: =A11 -> Jain, Harsh | B81: =B11 -> JB Management | C81: =C11 -> Systems Integration Engineer | D81: =D11 -> 158.04 | E81: =E11*$D11 -> 0 | F81: =F11*$D11 -> 12643.2 | G81: =G11*$D11 -> 25286.4 | H81: =H11*$D11 -> 12643.2 | I81: =I11*$D11 -> 25286.4 | J81: =J11*$D11 -> 25286.4 | K81: =K11*$D11 -> 24022.08 | L81: =L11*$D11 -> 25286.4 | ... AS81: =AS11*$D11 -> 0
A82: =A12 -> Sivaprakasam, Vijay | B82: =B12 -> TechSur | C82: =C12 -> Systems Integration Engineer | D82: =D12 -> 158.04 | E82: =E12*$D12 -> 0 | F82: =F12*$D12 -> 12643.2 | G82: =G12*$D12 -> 25286.4 | H82: =H12*$D12 -> 12643.2 | I82: =I12*$D12 -> 25286.4 | J82: =J12*$D12 -> 25286.4 | K82: =K12*$D12 -> 24022.08 | L82: =L12*$D12 -> 25286.4 | ... AS82: =AS12*$D12 -> 0
A83: =A13 -> Molabanti, Mohana | B83: =B13 -> TechSur | C83: =C13 -> Systems Integration Engineer | D83: =D13 -> 158.04 | E83: =E13*$D13 -> 0 | F83: =F13*$D13 -> 12643.2 | G83: =G13*$D13 -> 25286.4 | H83: =H13*$D13 -> 12643.2 | I83: =I13*$D13 -> 25286.4 | J83: =J13*$D13 -> 25286.4 | K83: =K13*$D13 -> 24022.08 | L83: =L13*$D13 -> 25286.4 | ... AS83: =AS13*$D13 -> 0
A84: =A14 -> Awodeu, Olusola | B84: =B14 -> TechSur | C84: =C14 -> Systems Integration Engineer | D84: =D14 -> 158.04 | E84: =E14*$D14 -> 0 | F84: =F14*$D14 -> 12643.2 | G84: =G14*$D14 -> 25286.4 | H84: =H14*$D14 -> 12643.2 | I84: =I14*$D14 -> 25286.4 | J84: =J14*$D14 -> 25286.4 | K84: =K14*$D14 -> 24022.08 | L84: =L14*$D14 -> 25286.4 | ... AS84: =AS14*$D14 -> 0
A85: =A15 -> Devarshi Pathak | B85: =B15 -> TechSur | C85: =C15 -> Systems Integration Engineer | D85: =D15 -> 158.04 | E85: =E15*$D15 -> 0 | F85: =F15*$D15 -> 12643.2 | G85: =G15*$D15 -> 25286.4 | H85: =H15*$D15 -> 12643.2 | I85: =I15*$D15 -> 25286.4 | J85: =J15*$D15 -> 25286.4 | K85: =K15*$D15 -> 24022.08 | L85: =L15*$D15 -> 25286.4 | ... AS85: =AS15*$D15 -> 0
A86: =A16 -> 0 | B86: =B16 -> 0 | C86: =C16 -> 0 | D86: =D16 -> 0 | E86: =E16*$D16 -> 0 | F86: =F16*$D16 -> 0 | G86: =G16*$D16 -> 0 | H86: =H16*$D16 -> 0 | I86: =I16*$D16 -> 0 | J86: =J16*$D16 -> 0 | K86: =K16*$D16 -> 0 | L86: =L16*$D16 -> 0 | ... AS86: =AS16*$D16 -> 0
A87: =A17 -> 0 | B87: =B17 -> 0 | C87: =C17 -> 0 | D87: =D17 -> 0 | E87: =E17*$D17 -> 0 | F87: =F17*$D17 -> 0 | G87: =G17*$D17 -> 0 | H87: =H17*$D17 -> 0 | I87: =I17*$D17 -> 0 | J87: =J17*$D17 -> 0 | K87: =K17*$D17 -> 0 | L87: =L17*$D17 -> 0 | ... AS87: =AS17*$D17 -> 0
A88: =A18 -> 0 | B88: =B18 -> 0 | C88: =C18 -> 0 | D88: =D18 -> 0 | E88: =E18*$D18 -> 0 | F88: =F18*$D18 -> 0 | G88: =G18*$D18 -> 0 | H88: =H18*$D18 -> 0 | I88: =I18*$D18 -> 0 | J88: =J18*$D18 -> 0 | K88: =K18*$D18 -> 0 | L88: =L18*$D18 -> 0 | ... AS88: =AS18*$D18 -> 0
E89: =E19*$D19 -> 0 | F89: =F19*$D19 -> 0 | G89: =G19*$D19 -> 0 | H89: =H19*$D19 -> 0 | I89: =I19*$D19 -> 0 | J89: =J19*$D19 -> 0 | K89: =K19*$D19 -> 0 | L89: =L19*$D19 -> 0 | ... AS89: =AS19*$D19 -> 0
E90: =E20*$D20 -> 0 | F90: =F20*$D20 -> 0 | G90: =G20*$D20 -> 0 | H90: =H20*$D20 -> 0 | I90: =I20*$D20 -> 0 | J90: =J20*$D20 -> 0 | K90: =K20*$D20 -> 0 | L90: =L20*$D20 -> 0 | ... AS90: =AS20*$D20 -> 0
E91: =E21*$D21 -> 0 | F91: =F21*$D21 -> 0 | G91: =G21*$D21 -> 0 | H91: =H21*$D21 -> 0 | I91: =I21*$D21 -> 0 | J91: =J21*$D21 -> 0 | K91: =K21*$D21 -> 0 | L91: =L21*$D21 -> 0 | ... AS91: =AS21*$D21 -> 0
E92: =E22*$D22 -> 0 | F92: =F22*$D22 -> 0 | G92: =G22*$D22 -> 0 | H92: =H22*$D22 -> 0 | I92: =I22*$D22 -> 0 | J92: =J22*$D22 -> 0 | K92: =K22*$D22 -> 0 | L92: =L22*$D22 -> 0 | ... AS92: =AS22*$D22 -> 0
E93: =E23*$D23 -> 0 | F93: =F23*$D23 -> 0 | G93: =G23*$D23 -> 0 | H93: =H23*$D23 -> 0 | I93: =I23*$D23 -> 0 | J93: =J23*$D23 -> 0 | K93: =K23*$D23 -> 0 | L93: =L23*$D23 -> 0 | ... AS93: =AS23*$D23 -> 0
E94: =E24*$D24 -> 0 | F94: =F24*$D24 -> 0 | G94: =G24*$D24 -> 0 | H94: =H24*$D24 -> 0 | I94: =I24*$D24 -> 0 | J94: =J24*$D24 -> 0 | K94: =K24*$D24 -> 0 | L94: =L24*$D24 -> 0 | ... AS94: =AS24*$D24 -> 0
E95: =E25*$D25 -> 0 | F95: =F25*$D25 -> 0 | G95: =G25*$D25 -> 0 | H95: =H25*$D25 -> 0 | I95: =I25*$D25 -> 0 | J95: =J25*$D25 -> 0 | K95: =K25*$D25 -> 0 | L95: =L25*$D25 -> 0 | ... AS95: =AS25*$D25 -> 0
E96: =E26*$D26 -> 0 | F96: =F26*$D26 -> 0 | G96: =G26*$D26 -> 0 | H96: =H26*$D26 -> 0 | I96: =I26*$D26 -> 0 | J96: =J26*$D26 -> 0 | K96: =K26*$D26 -> 0 | L96: =L26*$D26 -> 0 | ... AS96: =AS26*$D26 -> 0
E110: =SUM(E80:E109) -> 0 | F110: =SUM(F80:F109) -> 73208 | G110: =SUM(G80:G109) -> 146416 | H110: =SUM(H80:H109) -> 73208 | I110: =SUM(I80:I109) -> 146416 | J110: =SUM(J80:J109) -> 146416 | K110: =SUM(K80:K109) -> 139095.2 | L110: =SUM(L80:L109) -> 146416 | ... AS110: =SUM(AS80:AS109) -> 0
A112: T&M Revenue by Resource
E113: 2026 | J113: 2027 | V113: 2028 | AH113: 2029
A114: Name | B114: Company | C114: LCAT | D114: Rate | E114: 8 | F114: 9 | G114: 10 | H114: 11 | I114: 12 | J114: 1 | K114: 2 | L114: 3 | M114: 4 | N114: 5 | O114: 6 | P114: 7 | Q114: 8 | R114: 9 | S114: 10 | T114: 11 | U114: 12 | V114: 1 | W114: 2 | X114: 3 | Y114: 4 | Z114: 5 | AA114: 6 | AB114: 7 | AC114: 8 | AD114: 9 | AE114: 10 | AF114: 11 | AG114: 12 | AH114: 1 | AI114: 2 | AJ114: 3 | AK114: 4 | AL114: 5 | AM114: 6 | AN114: 7 | AO114: 8 | AP114: 9 | AQ114: 10 | AR114: 11 | AS114: 12
A115: =A10 -> Gupta, Madhur | B115: =B10 -> TechSur | C115: =C10 -> Business Analyst - Senior | D115: =D10 -> 124.9 | E115: =E45*$D115 -> 0 | F115: =F45*$D115 -> 0 | G115: =G45*$D115 -> 0 | H115: =H45*$D115 -> 0 | I115: =I45*$D115 -> 0 | J115: =J45*$D115 -> 0 | K115: =K45*$D115 -> 0 | L115: =L45*$D115 -> 0 | ... AS115: =AS45*$D115 -> 0
A116: =A11 -> Jain, Harsh | B116: =B11 -> JB Management | C116: =C11 -> Systems Integration Engineer | D116: =D11 -> 158.04 | E116: =E46*$D116 -> 0 | F116: =F46*$D116 -> 0 | G116: =G46*$D116 -> 0 | H116: =H46*$D116 -> 0 | I116: =I46*$D116 -> 0 | J116: =J46*$D116 -> 0 | K116: =K46*$D116 -> 0 | L116: =L46*$D116 -> 0 | ... AS116: =AS46*$D116 -> 0
A117: =A12 -> Sivaprakasam, Vijay | B117: =B12 -> TechSur | C117: =C12 -> Systems Integration Engineer | D117: =D12 -> 158.04 | E117: =E47*$D117 -> 0 | F117: =F47*$D117 -> 0 | G117: =G47*$D117 -> 0 | H117: =H47*$D117 -> 0 | I117: =I47*$D117 -> 0 | J117: =J47*$D117 -> 0 | K117: =K47*$D117 -> 0 | L117: =L47*$D117 -> 0 | ... AS117: =AS47*$D117 -> 0
A118: =A13 -> Molabanti, Mohana | B118: =B13 -> TechSur | C118: =C13 -> Systems Integration Engineer | D118: =D13 -> 158.04 | E118: =E48*$D118 -> 0 | F118: =F48*$D118 -> 0 | G118: =G48*$D118 -> 0 | H118: =H48*$D118 -> 0 | I118: =I48*$D118 -> 0 | J118: =J48*$D118 -> 0 | K118: =K48*$D118 -> 0 | L118: =L48*$D118 -> 0 | ... AS118: =AS48*$D118 -> 0
A119: =A14 -> Awodeu, Olusola | B119: =B14 -> TechSur | C119: =C14 -> Systems Integration Engineer | D119: =D14 -> 158.04 | E119: =E49*$D119 -> 0 | F119: =F49*$D119 -> 0 | G119: =G49*$D119 -> 0 | H119: =H49*$D119 -> 0 | I119: =I49*$D119 -> 0 | J119: =J49*$D119 -> 0 | K119: =K49*$D119 -> 0 | L119: =L49*$D119 -> 0 | ... AS119: =AS49*$D119 -> 0
A120: =A15 -> Devarshi Pathak | B120: =B15 -> TechSur | C120: =C15 -> Systems Integration Engineer | D120: =D15 -> 158.04 | E120: =E50*$D120 -> 0 | F120: =F50*$D120 -> 0 | G120: =G50*$D120 -> 0 | H120: =H50*$D120 -> 0 | I120: =I50*$D120 -> 0 | J120: =J50*$D120 -> 0 | K120: =K50*$D120 -> 0 | L120: =L50*$D120 -> 0 | ... AS120: =AS50*$D120 -> 0
A121: =A16 -> 0 | B121: =B16 -> 0 | C121: =C16 -> 0 | D121: =D16 -> 0 | E121: =E51*$D121 -> 0 | F121: =F51*$D121 -> 0 | G121: =G51*$D121 -> 0 | H121: =H51*$D121 -> 0 | I121: =I51*$D121 -> 0 | J121: =J51*$D121 -> 0 | K121: =K51*$D121 -> 0 | L121: =L51*$D121 -> 0 | ... AS121: =AS51*$D121 -> 0
A122: Awodeu, Olusola | B122: TechSur | C122: Systems Integration Engineer | D122: 154.94 | E122: =E52*$D122 -> 0 | F122: =F52*$D122 -> 0 | G122: =G52*$D122 -> 0 | H122: =H52*$D122 -> 0 | I122: =I52*$D122 -> 0 | J122: =J52*$D122 -> 0 | K122: =K52*$D122 -> 0 | L122: =L52*$D122 -> 0 | ... AS122: =AS52*$D122 -> 0
A123: =A18 -> 0 | B123: =B18 -> 0 | C123: =C18 -> 0 | D123: =D18 -> 0 | E123: =E53*$D123 -> 0 | F123: =F53*$D123 -> 0 | G123: =G53*$D123 -> 0 | H123: =H53*$D123 -> 0 | I123: =I53*$D123 -> 0 | J123: =J53*$D123 -> 0 | K123: =K53*$D123 -> 0 | L123: =L53*$D123 -> 0 | ... AS123: =AS53*$D123 -> 0
E124: =E54*$D124 -> 0 | F124: =F54*$D124 -> 0 | G124: =G54*$D124 -> 0 | H124: =H54*$D124 -> 0 | I124: =I54*$D124 -> 0 | J124: =J54*$D124 -> 0 | K124: =K54*$D124 -> 0 | L124: =L54*$D124 -> 0 | ... AS124: =AS54*$D124 -> 0
E125: =E55*$D125 -> 0 | F125: =F55*$D125 -> 0 | G125: =G55*$D125 -> 0 | H125: =H55*$D125 -> 0 | I125: =I55*$D125 -> 0 | J125: =J55*$D125 -> 0 | K125: =K55*$D125 -> 0 | L125: =L55*$D125 -> 0 | ... AS125: =AS55*$D125 -> 0
E126: =E56*$D126 -> 0 | F126: =F56*$D126 -> 0 | G126: =G56*$D126 -> 0 | H126: =H56*$D126 -> 0 | I126: =I56*$D126 -> 0 | J126: =J56*$D126 -> 0 | K126: =K56*$D126 -> 0 | L126: =L56*$D126 -> 0 | ... AS126: =AS56*$D126 -> 0
E127: =E57*$D127 -> 0 | F127: =F57*$D127 -> 0 | G127: =G57*$D127 -> 0 | H127: =H57*$D127 -> 0 | I127: =I57*$D127 -> 0 | J127: =J57*$D127 -> 0 | K127: =K57*$D127 -> 0 | L127: =L57*$D127 -> 0 | ... AS127: =AS57*$D127 -> 0
Q128: =Q58*$D128 -> 0 | R128: =R58*$D128 -> 0 | S128: =S58*$D128 -> 0 | T128: =T58*$D128 -> 0 | U128: =U58*$D128 -> 0 | V128: =V58*$D128 -> 0 | W128: =W58*$D128 -> 0 | X128: =X58*$D128 -> 0 | ... AS128: =AS58*$D128 -> 0
Q129: =Q59*$D129 -> 0 | R129: =R59*$D129 -> 0 | S129: =S59*$D129 -> 0 | T129: =T59*$D129 -> 0 | U129: =U59*$D129 -> 0 | V129: =V59*$D129 -> 0 | W129: =W59*$D129 -> 0 | X129: =X59*$D129 -> 0 | ... AS129: =AS59*$D129 -> 0
Q130: =Q60*$D130 -> 0 | R130: =R60*$D130 -> 0 | S130: =S60*$D130 -> 0 | T130: =T60*$D130 -> 0 | U130: =U60*$D130 -> 0 | V130: =V60*$D130 -> 0 | W130: =W60*$D130 -> 0 | X130: =X60*$D130 -> 0 | ... AS130: =AS60*$D130 -> 0
Q131: =Q61*$D131 -> 0 | R131: =R61*$D131 -> 0 | S131: =S61*$D131 -> 0 | T131: =T61*$D131 -> 0 | U131: =U61*$D131 -> 0 | V131: =V61*$D131 -> 0 | W131: =W61*$D131 -> 0 | X131: =X61*$D131 -> 0 | ... AS131: =AS61*$D131 -> 0
Q132: =Q62*$D132 -> 0 | R132: =R62*$D132 -> 0 | S132: =S62*$D132 -> 0 | T132: =T62*$D132 -> 0 | U132: =U62*$D132 -> 0 | V132: =V62*$D132 -> 0 | W132: =W62*$D132 -> 0 | X132: =X62*$D132 -> 0 | ... AS132: =AS62*$D132 -> 0
Q133: =Q63*$D133 -> 0 | R133: =R63*$D133 -> 0 | S133: =S63*$D133 -> 0 | T133: =T63*$D133 -> 0 | U133: =U63*$D133 -> 0 | V133: =V63*$D133 -> 0 | W133: =W63*$D133 -> 0 | X133: =X63*$D133 -> 0 | ... AS133: =AS63*$D133 -> 0
Q134: =Q64*$D134 -> 0 | R134: =R64*$D134 -> 0 | S134: =S64*$D134 -> 0 | T134: =T64*$D134 -> 0 | U134: =U64*$D134 -> 0 | V134: =V64*$D134 -> 0 | W134: =W64*$D134 -> 0 | X134: =X64*$D134 -> 0 | ... AS134: =AS64*$D134 -> 0
Q135: =Q65*$D135 -> 0 | R135: =R65*$D135 -> 0 | S135: =S65*$D135 -> 0 | T135: =T65*$D135 -> 0 | U135: =U65*$D135 -> 0 | V135: =V65*$D135 -> 0 | W135: =W65*$D135 -> 0 | X135: =X65*$D135 -> 0 | ... AS135: =AS65*$D135 -> 0
Q136: =Q66*$D136 -> 0 | R136: =R66*$D136 -> 0 | S136: =S66*$D136 -> 0 | T136: =T66*$D136 -> 0 | U136: =U66*$D136 -> 0 | V136: =V66*$D136 -> 0 | W136: =W66*$D136 -> 0 | X136: =X66*$D136 -> 0 | ... AS136: =AS66*$D136 -> 0
Q137: =Q67*$D137 -> 0 | R137: =R67*$D137 -> 0 | S137: =S67*$D137 -> 0 | T137: =T67*$D137 -> 0 | U137: =U67*$D137 -> 0 | V137: =V67*$D137 -> 0 | W137: =W67*$D137 -> 0 | X137: =X67*$D137 -> 0 | ... AS137: =AS67*$D137 -> 0
Q138: =Q68*$D138 -> 0 | R138: =R68*$D138 -> 0 | S138: =S68*$D138 -> 0 | T138: =T68*$D138 -> 0 | U138: =U68*$D138 -> 0 | V138: =V68*$D138 -> 0 | W138: =W68*$D138 -> 0 | X138: =X68*$D138 -> 0 | ... AS138: =AS68*$D138 -> 0
Q139: =Q69*$D139 -> 0 | R139: =R69*$D139 -> 0 | S139: =S69*$D139 -> 0 | T139: =T69*$D139 -> 0 | U139: =U69*$D139 -> 0 | V139: =V69*$D139 -> 0 | W139: =W69*$D139 -> 0 | X139: =X69*$D139 -> 0 | ... AS139: =AS69*$D139 -> 0
... Q144: =Q74*$D144 -> 0 | R144: =R74*$D144 -> 0 | S144: =S74*$D144 -> 0 | T144: =T74*$D144 -> 0 | U144: =U74*$D144 -> 0 | V144: =V74*$D144 -> 0 | W144: =W74*$D144 -> 0 | X144: =X74*$D144 -> 0 | ... AS144: =AS74*$D144 -> 0
E145: =SUM(E115:E144) -> 0 | F145: =SUM(F115:F144) -> 0 | G145: =SUM(G115:G144) -> 0 | H145: =SUM(H115:H144) -> 0 | I145: =SUM(I115:I144) -> 0 | J145: =SUM(J115:J144) -> 0 | K145: =SUM(K115:K144) -> 0 | L145: =SUM(L115:L144) -> 0 | ... AS145: =SUM(AS115:AS144) -> 0 | AU145: =SUM(E145:AT145) -> 0
A147: Invoice and Revenue Analysis
E148: 2026 | J148: 2027 | V148: 2028 | AH148: 2029
B149: Total | C149: Invoice | D149: Date | E149: 8 | F149: 9 | G149: 10 | H149: 11 | I149: 12 | J149: 1 | K149: 2 | L149: 3 | M149: 4 | N149: 5 | O149: 6 | P149: 7 | Q149: 8 | R149: 9 | S149: 10 | T149: 11 | U149: 12 | V149: 1 | W149: 2 | X149: 3 | Y149: 4 | Z149: 5 | AA149: 6 | AB149: 7 | AC149: 8 | AD149: 9 | AE149: 10 | AF149: 11 | AG149: 12 | AH149: 1 | AI149: 2 | AJ149: 3 | AK149: 4 | AL149: 5 | AM149: 6 | AN149: 7 | AO149: 8 | AP149: 9 | AQ149: 10 | AR149: 11 | AS149: 12
B163: =SUM(B150:B162) -> 0 | D163: Revenue | E163: =SUM(E150:E162) -> 0 | F163: =SUM(F150:F162) -> 0 | G163: =SUM(G150:G162) -> 0 | H163: =SUM(H150:H162) -> 0 | I163: =SUM(I150:I162) -> 0 | J163: =SUM(J150:J162) -> 0 | K163: =SUM(K150:K162) -> 0 | L163: =SUM(L150:L162) -> 0 | ... AS163: =SUM(AS150:AS162) -> 0 | AU163: =SUM(E163:AT163) -> 0
F166: 9 | G166: 10 | H166: 11 | I166: 12 | J166: 1 | K166: 2 | L166: 3 | M166: 4 | N166: 5 | O166: 6 | P166: 7 | Q166: 8 | R166: 9
E167: Forecast Rev | F167: =F110 -> 73208 | G167: =F167+G110 -> 219624 | H167: =G167+H110 -> 292832 | I167: =H167+I110 -> 439248 | J167: =I167+J110 -> 585664 | K167: =J167+K110 -> 724759.2 | L167: =K167+L110 -> 871175.2 | M167: =L167+M110 -> 1024912 | N167: =M167+N110 -> 1185969.6 | ... R167: =Q167+R110 -> 1698425.6
E168: Actual Rev | F168: =F163 -> 0 | G168: =G163+F168 -> 0 | H168: =G168+H163 -> 0 | I168: =H168+I163 -> 0 | J168: =I168+J163 -> 0 | K168: =J168+K163 -> 0 | L168: =K168+L163 -> 0 | M168: =L168+M163 -> 0 | N168: =M168+N163 -> 0 | O168: =N168+O163 -> 0 | ... Q168: =P168+Q163 -> 0 | R168: =Q168+P163 -> 0
E169: Funding | F169: =B4 -> 1756992 | G169: =F169 -> 1756992 | H169: =G169 -> 1756992 | I169: =H169 -> 1756992 | J169: =I169 -> 1756992 | K169: =J169 -> 1756992 | L169: =K169 -> 1756992 | M169: =L169 -> 1756992 | N169: =M169 -> 1756992 | ... R169: =Q169 -> 1756992
E170: Variance $ | F170: =F167-F168 -> 73208 | G170: =G167-G168 -> 219624 | H170: =H167-H168 -> 292832 | I170: =I167-I168 -> 439248 | J170: =J167-J168 -> 585664 | K170: =K167-K168 -> 724759.2 | L170: =L167-L168 -> 871175.2 | M170: =M167-M168 -> 1024912 | ... R170: =R167-R168 -> 1698425.6
E171: Variance % | F171: =F168/F167 -> 0 | G171: =G168/G167 -> 0 | H171: =H168/H167 -> 0 | I171: =I168/I167 -> 0 | J171: =J168/J167 -> 0 | K171: =K168/K167 -> 0 | L171: =L168/L167 -> 0 | M171: =M168/M167 -> 0 | ... R171: =R168/R167 -> 0
R174: =R167-R169 -> -58566.4
I183: =SUM(F163:K163) -> 0
I184: =SUM(L110:R110) -> 973666.4
I185: =SUM(I183:I184) -> 973666.4

Sheet AO Call 15.1
A2: Project: | B2: Call 15 - I&R
A3: PoP: | B3: 9/25/25 - 9/24/26 | C3: OP2: 9/25/26 - 9/24/27
A4: Funded Ceiling: | B4: 1853995.9
A6: Hours Forecast
D7: Working Days | E7: 22 | F7: 18 | G7: 21 | H7: 20 | I7: 20 | J7: 21 | K7: 20 | L7: 21 | M7: 22 | N7: 23 | O7: 19 | P7: 23 | Q7: 22 | R7: 18 | S7: 21 | T7: 20 | U7: 20 | V7: 21 | W7: 20 | X7: 21 | Y7: 22 | Z7: 23 | AA7: 19 | AB7: 23 | AC7: 22 | AD7: 18 | AE7: 21 | AF7: 20 | AG7: 20 | AH7: 21 | AI7: 20 | AJ7: 21 | AK7: 22 | AL7: 23 | AM7: 19 | AN7: 23 | AO7: 22 | AP7: 18 | AQ7: 21 | AR7: 20 | AS7: 20
E8: 2025 | J8: 2026 | V8: 2026 | AH8: 2027
A9: Name | B9: Company | C9: LCAT | D9: Rate | E9: 8 | F9: 9 | G9: 10 | H9: 11 | I9: 12 | J9: 1 | K9: 2 | L9: 3 | M9: 4 | N9: 5 | O9: 6 | P9: 7 | Q9: 8 | R9: 9 | S9: 10 | T9: 11 | U9: 12 | V9: 1 | W9: 2 | X9: 3 | Y9: 4 | Z9: 5 | AA9: 6 | AB9: 7 | AC9: 8 | AD9: 9 | AE9: 10 | AF9: 11 | AG9: 12 | AH9: 1 | AI9: 2 | AJ9: 3 | AK9: 4 | AL9: 5 | AM9: 6 | AN9: 7 | AO9: 8 | AP9: 9 | AQ9: 10 | AR9: 11 | AS9: 12
A10: Sourcing | B10: TechSur | C10: Artificial Intelligence (AI) Engineer | D10: 120.05 | E10: =D10*0.9 -> 108.045 | H10: 160 | I10: 160 | J10: =(J$7-1)*8 -> 160 | S10: =(S$7-1)*8 -> 160 | T10: =(T$7-1)*8 -> 152 | U10: =(U$7-1)*8 -> 152 | V10: =(V$7-1)*8 -> 160 | W10: =(W$7-1)*8 -> 152 | X10: =(X$7-1)*8 -> 160 | Y10: =(Y$7-1)*8 -> 168 | Z10: =(Z$7-1)*8 -> 176 | ... AP10: =(AP$7-1)*8 -> 136
A11: Louie Chen | B11: TechSur | C11: Artificial Intelligence (AI) Engineer | D11: 122.45 | H11: 160 | I11: 160 | J11: =(J$7-1)*8 -> 160 | K11: =(K$7-1)*8 -> 152 | L11: =(L$7-1)*8 -> 160 | M11: =(M$7-1)*8 -> 168 | N11: =(N$7-1)*8 -> 176 | O11: =(O$7-1)*8 -> 144 | P11: =(P$7-1)*8 -> 176 | Q11: =(Q$7-1)*8 -> 168 | ... AP11: =(AP$7-1)*8 -> 136
A12: Murali Konathala | B12: TechSur | C12: Software Engineer | D12: 141.14 | F12: 32 | G12: 160 | H12: 160 | I12: 160 | J12: =(J$7-1)*8 -> 160 | K12: =(K$7-1)*8 -> 152 | S12: =(S$7-1)*8 -> 160 | T12: =(T$7-1)*8 -> 152 | U12: =(U$7-1)*8 -> 152 | V12: =(V$7-1)*8 -> 160 | W12: =(W$7-1)*8 -> 152 | X12: =(X$7-1)*8 -> 160 | Y12: =(Y$7-1)*8 -> 168 | Z12: =(Z$7-1)*8 -> 176 | ... AP12: =(AP$7-1)*8 -> 136
A13: Nathan Moore | B13: TechSur | C13: Software Developer | D13: 105.06 | G13: 80 | H13: 160 | I13: 160 | J13: =(J$7-1)*8 -> 160 | K13: =(K$7-1)*8 -> 152 | L13: =(L$7-1)*8 -> 160 | M13: =(M$7-1)*8 -> 168 | N13: =(N$7-1)*8 -> 176 | O13: =(O$7-1)*8 -> 144 | P13: =(P$7-1)*8 -> 176 | Q13: =(Q$7-1)*8 -> 168 | ... AP13: =(AP$7-1)*8 -> 136
A14: Kenneth Megill (Transitioned TechSur Employee) | B14: TechSur | C14: Business Analyst - Senior | D14: 122.45 | G14: 80 | H14: 160 | I14: 160 | J14: =(J$7-1)*8 -> 160 | K14: =(K$7-1)*8 -> 152 | L14: =(L$7-1)*8 -> 160 | M14: =(M$7-1)*8 -> 168 | N14: =(N$7-1)*8 -> 176 | O14: =(O$7-1)*8 -> 144 | P14: =(P$7-1)*8 -> 176 | Q14: =(Q$7-1)*8 -> 168 | ... AP14: =(AP$7-1)*8 -> 136
A15: Nick Sundar | B15: TechSur | C15: Enterprise Architect | D15: 113.21
A16: Jason De Kock (Start 10/7) | B16: TechSur | C16: Systems Integration Engineer | D16: 154.94 | G16: 80 | H16: 160 | I16: 160 | J16: =(J$7-1)*8 -> 160 | K16: =(K$7-1)*8 -> 152 | L16: =(L$7-1)*8 -> 160 | M16: =(M$7-1)*8 -> 168 | N16: =(N$7-1)*8 -> 176 | O16: =(O$7-1)*8 -> 144 | P16: =(P$7-1)*8 -> 176 | Q16: =(Q$7-1)*8 -> 168 | ... AP16: =(AP$7-1)*8 -> 136
A17: Muthukrishna (Muthu) Krishnakumar | B17: TechSur | C17: Information Assurance Engineer | D17: 84.03 | G17: 80 | H17: 160 | I17: 160 | J17: =(J$7-1)*8 -> 160
A18: Neel Bhagwat | B18: TechSur | C18: Information Assurance Engineer | D18: 84.03 | K18: =(K$7-1)*8 -> 152
A19: Michael Brown | B19: TechSur | C19: Artificial Intelligence (AI) Engineer | D19: 120.05
A20: Shailendra Gohil | B20: TechSur | C20: Solutions Architect - Level III | D20: 148.92
A21: Angadveer Singh | B21: TechSur | C21: Task Manager | D21: 97.92
A22: Louden Motina | B22: TechSur | C22: Enterprise Architect | D22: 115.47 | L22: =(L$7-1)*8 -> 160 | M22: =(M$7-1)*8 -> 168 | N22: =(N$7-1)*8 -> 176 | O22: =(O$7-1)*8 -> 144 | P22: =(P$7-1)*8 -> 176 | Q22: =(Q$7-1)*8 -> 168 | R22: =(R$7-1)*8 -> 136
A23: Dhruvi Rathod | B23: TechSur | C23: Information Assurance Engineer | D23: 85.71 | L23: =(L$7-1)*8 -> 160 | M23: =(M$7-1)*8 -> 168 | N23: =(N$7-1)*8 -> 176 | O23: =(O$7-1)*8 -> 144 | P23: =(P$7-1)*8 -> 176 | Q23: =(Q$7-1)*8 -> 168 | R23: =(R$7-1)*8 -> 136
A24: Syed Abbas | B24: TechSur | C24: Information Assurance Engineer | D24: 85.71 | L24: =(L$7-1)*8 -> 160 | M24: =(M$7-1)*8 -> 168 | N24: =(N$7-1)*8 -> 176 | O24: =(O$7-1)*8 -> 144 | P24: =(P$7-1)*8 -> 176 | Q24: =(Q$7-1)*8 -> 168 | R24: =(R$7-1)*8 -> 136
E40: =SUM(E10:E39) -> 108.045 | F40: =SUM(F10:F39) -> 32 | G40: =SUM(G10:G39) -> 480 | H40: =SUM(H10:H39) -> 1120 | I40: =SUM(I10:I39) -> 1120 | J40: =SUM(J10:J39) -> 1120 | K40: =SUM(K10:K39) -> 912 | L40: =SUM(L10:L39) -> 1120 | ... AS40: =SUM(AS10:AS39) -> 0
A42: Hours Actual
E43: 2025 | J43: 2026 | V43: 2026 | AH43: 2027
A44: Name | B44: Company | C44: LCAT | D44: Rate | E44: 8 | F44: 9 | G44: 10 | H44: 11 | I44: 12 | J44: 1 | K44: 2 | L44: 3 | M44: 4 | N44: 5 | O44: 6 | P44: 7 | Q44: 8 | R44: 9 | S44: 10 | T44: 11 | U44: 12 | V44: 1 | W44: 2 | X44: 3 | Y44: 4 | Z44: 5 | AA44: 6 | AB44: 7 | AC44: 8 | AD44: 9 | AE44: 10 | AF44: 11 | AG44: 12 | AH44: 1 | AI44: 2 | AJ44: 3 | AK44: 4 | AL44: 5 | AM44: 6 | AN44: 7 | AO44: 8 | AP44: 9 | AQ44: 10 | AR44: 11 | AS44: 12
A45: =A10 -> Sourcing | B45: =B10 -> TechSur | C45: =C10 -> Artificial Intelligence (AI) Engineer | D45: =D10 -> 120.05 | F45: 0 | G45: 0 | H45: 0 | I45: 0 | J45: 0 | K45: 0 | L45: 0 | M45: 0 | N45: 0 | O45: 0 | P45: 0
A46: Louie Chen | B46: =B11 -> TechSur | C46: =C11 -> Artificial Intelligence (AI) Engineer | D46: =D11 -> 122.45 | F46: 24 | G46: 96 | H46: 80 | I46: 157 | J46: 132 | K46: 152 | L46: 176 | M46: 172 | N46: 108 | O46: 168 | P46: 176
A47: =A12 -> Murali Konathala | B47: =B12 -> TechSur | C47: =C12 -> Software Engineer | D47: =D12 -> 141.14 | F47: 32 | G47: 96 | H47: 80 | I47: 152 | J47: 0 | K47: 0 | L47: 0 | M47: 0 | N47: 0 | O47: 0 | P47: 0
A48: =A13 -> Nathan Moore | B48: =B13 -> TechSur | C48: =C13 -> Software Developer | D48: =D13 -> 105.06 | F48: 32 | G48: 96 | H48: 80 | I48: 80 | J48: 0 | K48: 0 | L48: 0 | M48: 0 | N48: 0 | O48: 0 | P48: 0
A49: =A14 -> Kenneth Megill (Transitioned TechSur Employee) | B49: =B14 -> TechSur | C49: =C14 -> Business Analyst - Senior | D49: =D14 -> 122.45 | F49: 32 | G49: 96 | H49: 72 | I49: 173 | J49: 143 | K49: 152 | L49: 176 | M49: 168 | N49: 160 | O49: 168 | P49: 176
A50: =A15 -> Nick Sundar | B50: =B15 -> TechSur | C50: =C15 -> Enterprise Architect | D50: =D15 -> 113.21 | F50: 0 | G50: 0 | H50: 0 | I50: 0 | J50: 0 | K50: 0 | L50: 0 | M50: 0 | N50: 0 | O50: 0 | P50: 0
A51: =A16 -> Jason De Kock (Start 10/7) | B51: =B16 -> TechSur | C51: =C16 -> Systems Integration Engineer | D51: =D16 -> 154.94 | F51: 32 | G51: 96 | H51: 80 | I51: 176 | J51: 160 | K51: 152 | L51: 176 | M51: 176 | N51: 136 | O51: 128 | P51: 176
A52: =A17 -> Muthukrishna (Muthu) Krishnakumar | B52: =B17 -> TechSur | C52: =C17 -> Information Assurance Engineer | D52: =D17 -> 84.03 | F52: 0 | G52: 0 | H52: 0 | I52: 0 | J52: 0 | K52: 0 | L52: 0 | M52: 0 | N52: 0 | O52: 0 | P52: 0
A53: =A18 -> Neel Bhagwat | B53: =B18 -> TechSur | C53: =C18 -> Information Assurance Engineer | D53: =D18 -> 84.03 | F53: 0 | G53: 0 | H53: 0 | I53: 0 | J53: 0 | K53: 0 | L53: 0 | M53: 0 | N53: 0 | O53: 0 | P53: 0
A54: =A19 -> Michael Brown | B54: =B19 -> TechSur | C54: =C19 -> Artificial Intelligence (AI) Engineer | D54: =D19 -> 120.05 | F54: 0 | G54: 0 | H54: 0 | I54: 0 | J54: 0 | K54: 0 | L54: 0 | M54: 0 | N54: 0 | O54: 0 | P54: 0
A55: =A20 -> Shailendra Gohil | B55: =B20 -> TechSur | C55: =C20 -> Solutions Architect - Level III | D55: =D20 -> 148.92 | F55: 0 | G55: 0 | H55: 0 | I55: 0 | J55: 0 | K55: 0 | L55: 0 | M55: 0 | N55: 0 | O55: 0 | P55: 0
A56: =A21 -> Angadveer Singh | B56: =B21 -> TechSur | C56: =C21 -> Task Manager | D56: =D21 -> 97.92 | F56: 0 | G56: 0 | H56: 0 | I56: 0 | J56: 0 | K56: 0 | L56: 0 | M56: 0 | N56: 0 | O56: 0 | P56: 0
A57: Louden Motina | C57: Enterprise Architect | D57: 113.21 | F57: 32 | G57: 96 | H57: 80 | I57: 176 | J57: 160 | K57: 152 | L57: 176 | M57: 176 | N57: 160 | O57: 168 | P57: 176
A58: =A23 -> Dhruvi Rathod | B58: =B23 -> TechSur | C58: =C23 -> Information Assurance Engineer | D58: =D23 -> 85.71 | F58: 16 | G58: 48 | H58: 0 | I58: 68 | J58: 136 | K58: 152 | L58: 176 | M58: 176 | N58: 144 | O58: 168 | P58: 172
A59: =A24 -> Syed Abbas | B59: =B24 -> TechSur | C59: =C24 -> Information Assurance Engineer | D59: =D24 -> 85.71 | G59: 48 | H59: 40 | I59: 88 | J59: 69 | K59: 152 | L59: 176 | M59: 176 | N59: 160 | O59: 168 | P59: 176
E75: =SUM(E45:E74) -> 0 | F75: =SUM(F45:F74) -> 200 | G75: =SUM(G45:G74) -> 672 | H75: =SUM(H45:H74) -> 512 | I75: =SUM(I45:I74) -> 1070 | J75: =SUM(J45:J74) -> 800 | K75: =SUM(K45:K74) -> 912 | L75: =SUM(L45:L74) -> 1056 | ... AS75: =SUM(AS45:AS74) -> 0
A77: Forecast Revenue by Resource
E78: 2025 | J78: 2026 | V78: 2026 | AH78: 2027
A79: Name | B79: Company | C79: LCAT | D79: Rate | E79: 8 | F79: 9 | G79: 10 | H79: 11 | I79: 12 | J79: 1 | K79: 2 | L79: 3 | M79: 4 | N79: 5 | O79: 6 | P79: 7 | Q79: 8 | R79: 9 | S79: 10 | T79: 11 | U79: 12 | V79: 1 | W79: 2 | X79: 3 | Y79: 4 | Z79: 5 | AA79: 6 | AB79: 7 | AC79: 8 | AD79: 9 | AE79: 10 | AF79: 11 | AG79: 12 | AH79: 1 | AI79: 2 | AJ79: 3 | AK79: 4 | AL79: 5 | AM79: 6 | AN79: 7 | AO79: 8 | AP79: 9 | AQ79: 10 | AR79: 11 | AS79: 12
A80: =A10 -> Sourcing | B80: =B10 -> TechSur | C80: =C10 -> Artificial Intelligence (AI) Engineer | D80: =D10 -> 120.05 | E80: =E10*$D10 -> 12970.802 | F80: =F10*$D10 -> 0 | G80: =G10*$D10 -> 0 | H80: =H10*$D10 -> 19208 | I80: =I10*$D10 -> 19208 | J80: =J10*$D10 -> 19208 | K80: =K10*$D10 -> 0 | L80: =L10*$D10 -> 0 | ... AS80: =AS10*$D10 -> 0
A81: =A11 -> Louie Chen | B81: =B11 -> TechSur | C81: =C11 -> Artificial Intelligence (AI) Engineer | D81: =D11 -> 122.45 | E81: =E11*$D11 -> 0 | F81: =F11*$D11 -> 0 | G81: =G11*$D11 -> 0 | H81: =H11*$D11 -> 19592 | I81: =I11*$D11 -> 19592 | J81: =J11*$D11 -> 19592 | K81: =K11*$D11 -> 18612.4 | L81: =L11*$D11 -> 19592 | ... AS81: =AS11*$D11 -> 0
A82: =A12 -> Murali Konathala | B82: =B12 -> TechSur | C82: =C12 -> Software Engineer | D82: =D12 -> 141.14 | E82: =E12*$D12 -> 0 | F82: =F12*$D12 -> 4516.48 | G82: =G12*$D12 -> 22582.4 | H82: =H12*$D12 -> 22582.4 | I82: =I12*$D12 -> 22582.4 | J82: =J12*$D12 -> 22582.4 | K82: =K12*$D12 -> 21453.28 | L82: =L12*$D12 -> 0 | ... AS82: =AS12*$D12 -> 0
A83: =A13 -> Nathan Moore | B83: =B13 -> TechSur | C83: =C13 -> Software Developer | D83: =D13 -> 105.06 | E83: =E13*$D13 -> 0 | F83: =F13*$D13 -> 0 | G83: =G13*$D13 -> 8404.8 | H83: =H13*$D13 -> 16809.6 | I83: =I13*$D13 -> 16809.6 | J83: =J13*$D13 -> 16809.6 | K83: =K13*$D13 -> 15969.12 | L83: =L13*$D13 -> 16809.6 | ... AS83: =AS13*$D13 -> 0
A84: =A14 -> Kenneth Megill (Transitioned TechSur Employee) | B84: =B14 -> TechSur | C84: =C14 -> Business Analyst - Senior | D84: =D14 -> 122.45 | E84: =E14*$D14 -> 0 | F84: =F14*$D14 -> 0 | G84: =G14*$D14 -> 9796 | H84: =H14*$D14 -> 19592 | I84: =I14*$D14 -> 19592 | J84: =J14*$D14 -> 19592 | K84: =K14*$D14 -> 18612.4 | L84: =L14*$D14 -> 19592 | ... AS84: =AS14*$D14 -> 0
A85: =A15 -> Nick Sundar | B85: =B15 -> TechSur | C85: =C15 -> Enterprise Architect | D85: =D15 -> 113.21 | E85: =E15*$D15 -> 0 | F85: =F15*$D15 -> 0 | G85: =G15*$D15 -> 0 | H85: =H15*$D15 -> 0 | I85: =I15*$D15 -> 0 | J85: =J15*$D15 -> 0 | K85: =K15*$D15 -> 0 | L85: =L15*$D15 -> 0 | ... AS85: =AS15*$D15 -> 0
A86: =A16 -> Jason De Kock (Start 10/7) | B86: =B16 -> TechSur | C86: =C16 -> Systems Integration Engineer | D86: =D16 -> 154.94 | E86: =E16*$D16 -> 0 | F86: =F16*$D16 -> 0 | G86: =G16*$D16 -> 12395.2 | H86: =H16*$D16 -> 24790.4 | I86: =I16*$D16 -> 24790.4 | J86: =J16*$D16 -> 24790.4 | K86: =K16*$D16 -> 23550.88 | L86: =L16*$D16 -> 24790.4 | ... AS86: =AS16*$D16 -> 0
A87: =A17 -> Muthukrishna (Muthu) Krishnakumar | B87: =B17 -> TechSur | C87: =C17 -> Information Assurance Engineer | D87: =D17 -> 84.03 | E87: =E17*$D17 -> 0 | F87: =F17*$D17 -> 0 | G87: =G17*$D17 -> 6722.4 | H87: =H17*$D17 -> 13444.8 | I87: =I17*$D17 -> 13444.8 | J87: =J17*$D17 -> 13444.8 | K87: =K18*$D17 -> 12772.56 | L87: =L17*$D17 -> 0 | M87: =M17*$D17 -> 0 | N87: =N17*$D17 -> 0 | O87: =O17*$D17 -> 0 | P87: =P17*$D17 -> 0 | Q87: =Q17*$D17 -> 0 | R87: =R17*$D17 -> 0 | S87: =S17*$D17 -> 0 | ... AS87: =AS17*$D17 -> 0
A88: =A18 -> Neel Bhagwat | B88: =B18 -> TechSur | C88: =C18 -> Information Assurance Engineer | D88: =D18 -> 84.03 | J88: =J18*$D18 -> 0 | K88: =K18*$D18 -> 12772.56 | L88: =L18*$D18 -> 0 | M88: =M18*$D18 -> 0 | N88: =N18*$D18 -> 0 | O88: =O18*$D18 -> 0 | P88: =P18*$D18 -> 0 | Q88: =Q18*$D18 -> 0 | ... AJ88: =AJ18*$D18 -> 0 | AK88: =#REF!*$D18 -> #REF! | AL88: =#REF!*$D18 -> #REF! | AM88: =#REF!*$D18 -> #REF! | AN88: =#REF!*$D18 -> #REF! | AO88: =#REF!*$D18 -> #REF! | AP88: =#REF!*$D18 -> #REF! | AQ88: =AQ18*$D18 -> 0 | AR88: =AR18*$D18 -> 0 | AS88: =AS18*$D18 -> 0
A89: =A19 -> Michael Brown | B89: =B19 -> TechSur | C89: =C19 -> Artificial Intelligence (AI) Engineer | D89: =D19 -> 120.05 | J89: =J19*$D19 -> 0 | K89: =K19*$D19 -> 0 | L89: =L19*$D19 -> 0 | M89: =M19*$D19 -> 0 | N89: =N19*$D19 -> 0 | O89: =O19*$D19 -> 0 | P89: =P19*$D19 -> 0 | Q89: =Q19*$D19 -> 0 | ... AS89: =AS19*$D19 -> 0
A90: =A20 -> Shailendra Gohil | B90: =B20 -> TechSur | C90: =C20 -> Solutions Architect - Level III | D90: =D20 -> 148.92 | J90: =J20*$D20 -> 0 | K90: =K20*$D20 -> 0 | L90: =L20*$D20 -> 0 | M90: =M20*$D20 -> 0 | N90: =N20*$D20 -> 0 | O90: =O20*$D20 -> 0 | P90: =P20*$D20 -> 0 | Q90: =Q20*$D20 -> 0 | ... AS90: =AS20*$D20 -> 0
A91: =A21 -> Angadveer Singh | B91: =B21 -> TechSur | C91: =C21 -> Task Manager | D91: =D21 -> 97.92 | J91: =J21*$D21 -> 0 | K91: =K21*$D21 -> 0 | L91: =L21*$D21 -> 0 | M91: =M21*$D21 -> 0 | N91: =N21*$D21 -> 0 | O91: =O21*$D21 -> 0 | P91: =P21*$D21 -> 0 | Q91: =Q21*$D21 -> 0 | ... AS91: =AS21*$D21 -> 0
A92: =A22 -> Louden Motina | B92: =B22 -> TechSur | C92: =C22 -> Enterprise Architect | D92: =D22 -> 115.47 | J92: =J22*$D22 -> 0 | K92: =K22*$D22 -> 0 | L92: =L22*$D22 -> 18475.2 | M92: =M22*$D22 -> 19398.96 | N92: =N22*$D22 -> 20322.72 | O92: =O22*$D22 -> 16627.68 | P92: =P22*$D22 -> 20322.72 | Q92: =Q22*$D22 -> 19398.96 | ... AS92: =AS22*$D22 -> 0
A93: =A23 -> Dhruvi Rathod | B93: =B23 -> TechSur | C93: =C23 -> Information Assurance Engineer | D93: =D23 -> 85.71 | J93: =J23*$D23 -> 0 | K93: =K23*$D23 -> 0 | L93: =L23*$D23 -> 13713.6 | M93: =M23*$D23 -> 14399.28 | N93: =N23*$D23 -> 15084.96 | O93: =O23*$D23 -> 12342.24 | P93: =P23*$D23 -> 15084.96 | Q93: =Q23*$D23 -> 14399.28 | ... AS93: =AS23*$D23 -> 0
A94: =A24 -> Syed Abbas | B94: =B24 -> TechSur | C94: =C24 -> Information Assurance Engineer | D94: =D24 -> 85.71 | J94: =J24*$D24 -> 0 | K94: =K24*$D24 -> 0 | L94: =L24*$D24 -> 13713.6 | M94: =M24*$D24 -> 14399.28 | N94: =N24*$D24 -> 15084.96 | O94: =O24*$D24 -> 12342.24 | P94: =P24*$D24 -> 15084.96 | Q94: =Q24*$D24 -> 14399.28 | ... AS94: =AS24*$D24 -> 0
E110: =SUM(E80:E109) -> 12970.802 | F110: =SUM(F80:F109) -> 4516.48 | G110: =SUM(G80:G109) -> 59900.8 | H110: =SUM(H80:H109) -> 136019.2 | I110: =SUM(I80:I109) -> 136019.2 | J110: =SUM(J80:J109) -> 136019.2 | K110: =SUM(K80:K109) -> 123743.2 | L110: =SUM(L80:L109) -> 126686.4 | ... AP110: =SUM(AP80:AP109) -> #REF!
A112: T&M Revenue by Resource
E113: 2025 | J113: 2026 | V113: 2026 | AH113: 2027
A114: Name | B114: Company | C114: LCAT | D114: Rate | E114: 8 | F114: 9 | G114: 10 | H114: 11 | I114: 12 | J114: 1 | K114: 2 | L114: 3 | M114: 4 | N114: 5 | O114: 6 | P114: 7 | Q114: 8 | R114: 9 | S114: 10 | T114: 11 | U114: 12 | V114: 1 | W114: 2 | X114: 3 | Y114: 4 | Z114: 5 | AA114: 6 | AB114: 7 | AC114: 8 | AD114: 9 | AE114: 10 | AF114: 11 | AG114: 12 | AH114: 1 | AI114: 2 | AJ114: 3 | AK114: 4 | AL114: 5 | AM114: 6 | AN114: 7 | AO114: 8 | AP114: 9 | AQ114: 10 | AR114: 11 | AS114: 12
A115: =A10 -> Sourcing | B115: =B10 -> TechSur | C115: =C10 -> Artificial Intelligence (AI) Engineer | D115: =D10 -> 120.05 | E115: =$D115*E45 -> 0 | F115: =$D115*F45 -> 0 | G115: =$D115*G45 -> 0 | H115: =$D115*H45 -> 0 | I115: =$D115*I45 -> 0 | J115: =$D115*J45 -> 0 | K115: =$D115*K45 -> 0 | L115: =$D115*L45 -> 0 | ... R115: =$D115*R45 -> 0
A116: =A11 -> Louie Chen | B116: =B11 -> TechSur | C116: =C11 -> Artificial Intelligence (AI) Engineer | D116: =D11 -> 122.45 | E116: =$D116*E46 -> 0 | F116: =$D116*F46 -> 2938.8 | G116: =$D116*G46 -> 11755.2 | H116: =$D116*H46 -> 9796 | I116: =$D116*I46 -> 19224.65 | J116: =$D116*J46 -> 16163.4 | K116: =$D116*K46 -> 18612.4 | L116: =$D116*L46 -> 21551.2 | ... R116: =$D116*R46 -> 0
A117: =A12 -> Murali Konathala | B117: =B12 -> TechSur | C117: =C12 -> Software Engineer | D117: =D12 -> 141.14 | E117: =$D117*E47 -> 0 | F117: =$D117*F47 -> 4516.48 | G117: =$D117*G47 -> 13549.44 | H117: =$D117*H47 -> 11291.2 | I117: =$D117*I47 -> 21453.28 | J117: =$D117*J47 -> 0 | K117: =$D117*K47 -> 0 | L117: =$D117*L47 -> 0 | ... R117: =$D117*R47 -> 0
A118: =A13 -> Nathan Moore | B118: =B13 -> TechSur | C118: =C13 -> Software Developer | D118: =D13 -> 105.06 | E118: =$D118*E48 -> 0 | F118: =$D118*F48 -> 3361.92 | G118: =$D118*G48 -> 10085.76 | H118: =$D118*H48 -> 8404.8 | I118: =$D118*I48 -> 8404.8 | J118: =$D118*J48 -> 0 | K118: =$D118*K48 -> 0 | L118: =$D118*L48 -> 0 | ... R118: =$D118*R48 -> 0
A119: =A14 -> Kenneth Megill (Transitioned TechSur Employee) | B119: =B14 -> TechSur | C119: =C14 -> Business Analyst - Senior | D119: =D14 -> 122.45 | E119: =$D119*E49 -> 0 | F119: =$D119*F49 -> 3918.4 | G119: =$D119*G49 -> 11755.2 | H119: =$D119*H49 -> 8816.4 | I119: =$D119*I49 -> 21183.85 | J119: =$D119*J49 -> 17510.35 | K119: =$D119*K49 -> 18612.4 | L119: =$D119*L49 -> 21551.2 | ... R119: =$D119*R49 -> 0
A120: =A15 -> Nick Sundar | B120: =B15 -> TechSur | C120: =C15 -> Enterprise Architect | D120: =D15 -> 113.21 | E120: =$D120*E50 -> 0 | F120: =$D120*F50 -> 0 | G120: =$D120*G50 -> 0 | H120: =$D120*H50 -> 0 | I120: =$D120*I50 -> 0 | J120: =$D120*J50 -> 0 | K120: =$D120*K50 -> 0 | L120: =$D120*L50 -> 0 | ... R120: =$D120*R50 -> 0
A121: =A16 -> Jason De Kock (Start 10/7) | B121: =B16 -> TechSur | C121: =C16 -> Systems Integration Engineer | D121: =D16 -> 154.94 | E121: =$D121*E51 -> 0 | F121: =$D121*F51 -> 4958.08 | G121: =$D121*G51 -> 14874.24 | H121: =$D121*H51 -> 12395.2 | I121: =$D121*I51 -> 27269.44 | J121: =$D121*J51 -> 24790.4 | K121: =$D121*K51 -> 23550.88 | L121: =$D121*L51 -> 27269.44 | ... R121: =$D121*R51 -> 0
A122: =A17 -> Muthukrishna (Muthu) Krishnakumar | B122: =B17 -> TechSur | C122: =C17 -> Information Assurance Engineer | D122: =D17 -> 84.03 | E122: =$D122*E52 -> 0 | F122: =$D122*F52 -> 0 | G122: =$D122*G52 -> 0 | H122: =$D122*H52 -> 0 | I122: =$D122*I52 -> 0 | J122: =$D122*J52 -> 0 | K122: =$D122*K52 -> 0 | L122: =$D122*L52 -> 0 | ... R122: =$D122*R52 -> 0
A123: =A18 -> Neel Bhagwat | B123: =B18 -> TechSur | C123: =C18 -> Information Assurance Engineer | D123: =D18 -> 84.03 | E123: =$D123*E53 -> 0 | F123: =$D123*F53 -> 0 | G123: =$D123*G53 -> 0 | H123: =$D123*H53 -> 0 | I123: =$D123*I53 -> 0 | J123: =$D123*J53 -> 0 | K123: =$D123*K53 -> 0 | L123: =$D123*L53 -> 0 | ... R123: =$D123*R53 -> 0
A124: =A19 -> Michael Brown | B124: =B19 -> TechSur | C124: =C19 -> Artificial Intelligence (AI) Engineer | D124: =D19 -> 120.05 | E124: =$D124*E54 -> 0 | F124: =$D124*F54 -> 0 | G124: =$D124*G54 -> 0 | H124: =$D124*H54 -> 0 | I124: =$D124*I54 -> 0 | J124: =$D124*J54 -> 0 | K124: =$D124*K54 -> 0 | L124: =$D124*L54 -> 0 | ... R124: =$D124*R54 -> 0
A125: =A20 -> Shailendra Gohil | B125: =B20 -> TechSur | C125: =C20 -> Solutions Architect - Level III | D125: =D20 -> 148.92 | E125: =$D125*E55 -> 0 | F125: =$D125*F55 -> 0 | G125: =$D125*G55 -> 0 | H125: =$D125*H55 -> 0 | I125: =$D125*I55 -> 0 | J125: =$D125*J55 -> 0 | K125: =$D125*K55 -> 0 | L125: =$D125*L55 -> 0 | ... R125: =$D125*R55 -> 0
A126: =A21 -> Angadveer Singh | B126: =B21 -> TechSur | C126: =C21 -> Task Manager | D126: =D21 -> 97.92 | E126: =$D126*E56 -> 0 | F126: =$D126*F56 -> 0 | G126: =$D126*G56 -> 0 | H126: =$D126*H56 -> 0 | I126: =$D126*I56 -> 0 | J126: =$D126*J56 -> 0 | K126: =$D126*K56 -> 0 | L126: =$D126*L56 -> 0 | ... R126: =$D126*R56 -> 0
... A137: =A32 -> 0 | B137: =B32 -> 0 | C137: =C32 -> 0 | D137: =D32 -> 0 | E137: =$D137*E67 -> 0 | F137: =$D137*F67 -> 0 | G137: =$D137*G67 -> 0 | H137: =$D137*H67 -> 0 | I137: =$D137*I67 -> 0 | J137: =$D137*J67 -> 0 | K137: =$D137*K67 -> 0 | L137: =$D137*L67 -> 0 | ... R137: =$D137*R67 -> 0
E145: =SUM(E115:E144) -> 0 | F145: =SUM(F115:F144) -> 24760.08 | G145: =SUM(G115:G144) -> 81333.12 | H145: =SUM(H115:H144) -> 63369.6 | I145: =SUM(I115:I144) -> 131229.5 | J145: =SUM(J115:J144) -> 94509.9 | K145: =SUM(K115:K144) -> 104382.96 | L145: =SUM(L115:L144) -> 120864.48 | ... AS145: =SUM(AS115:AS144) -> 0 | AU145: =SUM(E145:AT145) -> 1067958.9
A147: Invoice and Revenue Analysis | E147: 2025 | J147: 2026 | V147: 2026 | AH147: 2027
C148: Invoice | D148: Date | E148: 8 | F148: 9 | G148: 10 | H148: 11 | I148: 12 | J148: 1 | K148: 2 | L148: 3 | M148: 4 | N148: 5 | O148: 6 | P148: 7 | Q148: 8 | R148: 9 | S148: 10 | T148: 11 | U148: 12 | V148: 1 | W148: 2 | X148: 3 | Y148: 4 | Z148: 5 | AA148: 6 | AB148: 7 | AC148: 8 | AD148: 9 | AE148: 10 | AF148: 11 | AG148: 12 | AH148: 1 | AI148: 2 | AJ148: 3 | AK148: 4 | AL148: 5 | AM148: 6 | AN148: 7 | AO148: 8 | AP148: 9 | AQ148: 10 | AR148: 11 | AS148: 12
C149: I01188 - Sept | D149: 45937 | F149: 26131.44
C150: I01207 - Oct | D150: 45968 | G150: 81333.12
C151: I01233 - Nov | D151: 46000 | H151: 63369.6
C152: I01260 - Dec | D152: 46028 | I152: 131229.5
C153: I01288 - Jan | D153: 46059 | J153: 94509.9
C154: I01308 - Feb | D154: 46086 | K154: 104382.96
C155: I01346 - Mar | D155: 46116 | L155: 120864.48
C156: I01372 - April | D156: 46146 | M156: 119395.08
C157: I01401 - May | D157: 46176 | N157: 98419.48
C158: I01434 - June | D158: 46209 | O158: 109173.04
C159: I01480 - July | D159: 46238 | P159: 120521.64
D162: Revenue | E162: =SUM(E149:E161) -> 0 | F162: =SUM(F149:F161) -> 26131.44 | G162: =SUM(G149:G161) -> 81333.12 | H162: =SUM(H149:H161) -> 63369.6 | I162: =SUM(I149:I161) -> 131229.5 | J162: =SUM(J149:J161) -> 94509.9 | K162: =SUM(K149:K161) -> 104382.96 | L162: =SUM(L149:L161) -> 120864.48 | ... Q162: =SUM(Q149:Q161) -> 0
E166: 8 | F166: 9 | G166: 10 | H166: 11 | I166: 12 | J166: 1 | K166: 2 | L166: 3 | M166: 4 | N166: 5 | O166: 6 | P166: 7 | Q166: 8
D167: Forecast Rev | E167: =E110 -> 12970.802 | F167: =E167+F110 -> 17487.282 | G167: =F167+G110 -> 77388.082 | H167: =G167+H110 -> 213407.28 | I167: =H167+I110 -> 349426.48 | J167: =I167+J110 -> 485445.68 | K167: =J167+K110 -> 609188.88 | L167: =K167+L110 -> 735875.28 | M167: =L167+M110 -> 868896 | ... Q167: =P167+Q110 -> 1394644.6
D168: Actual Rev | E168: =E162 -> 0 | F168: =E168+F162 -> 26131.44 | G168: =F168+G162 -> 107464.56 | H168: =G168+H162 -> 170834.16 | I168: =H168+I162 -> 302063.66 | J168: =I168+J162 -> 396573.56 | K168: =J168+K162 -> 500956.52 | L168: =K168+L162 -> 621821 | M168: =L168+M162 -> 741216.08 | ... P168: =O168+P162 -> 1069330.2
D169: Funding | E169: =$B$4 -> 1853995.9 | F169: =$B$4 -> 1853995.9 | G169: =$B$4 -> 1853995.9 | H169: =$B$4 -> 1853995.9 | I169: =$B$4 -> 1853995.9 | J169: =$B$4 -> 1853995.9 | K169: =$B$4 -> 1853995.9 | L169: =$B$4 -> 1853995.9 | ... Q169: =$B$4 -> 1853995.9
D170: Variance $ | E170: =E167-E168 -> 12970.802 | F170: =F167-F168 -> -8644.1577 | G170: =G167-G168 -> -30076.478 | H170: =H167-H168 -> 42573.122 | I170: =I167-I168 -> 47362.822 | J170: =J167-J168 -> 88872.122 | K170: =K167-K168 -> 108232.36 | L170: =L167-L168 -> 114054.28 | ... Q170: =Q167-Q168 -> 1394644.6
D171: Variance % | F171: =F168/F167 -> 1.4943111 | G171: =G168/G167 -> 1.3886448 | H171: =H168/H167 -> 0.80050764 | I171: =I168/I167 -> 0.86445554 | J171: =J168/J167 -> 0.81692674 | K171: =K168/K167 -> 0.82233365 | L171: =L168/L167 -> 0.84500868 | M171: =M168/M167 -> 0.853055 | ... Q171: =Q168/Q167 -> 0

Sheet BPA Spending
B1: PoP | C1: Funds Obligated | D1: Funds Expended to Date* | E1: % of Services SubContracted | F1: Avg Monthly Spend | G1: Funds Remaining | H1: Estimate at Completion | I1: Over/Under | J1: %
A2: Call 1 - RAE | B2: ='AO Call 1'!B3 -> 2/26/23-8/25/23 | C2: ='AO Call 1'!B4 -> 2041574.4 | D2: =SUM('AO Call 1'!E113:Q113) -> 3069951.5 | E2: =7/21 -> 0.33333333 | F2: =D2/6 -> 511658.58
A3: Call 1.2 - RAE | B3: ='AO Call 1.2'!B3 -> 8/26/23-2/25/24 | C3: ='AO Call 1.2'!B4 -> 2645784 | D3: =SUM('AO Call 1.2'!E188:K188) -> 1897381.5 | E3: =3/24 -> 0.125 | F3: =D3/6 -> 316230.25
A4: Call 1.3 - RAE | B4: ='AO Call 1.3'!B3 -> 2/26/24-8/25/24 | C4: ='AO Call 1.3'!B4 -> 2714870.4 | D4: =SUM('AO Call 1.3'!F193:L193) -> 2316712.6 | E4: =4/26 -> 0.15384615 | F4: =D4/6 -> 386118.77
A5: Call 1.4 - RAE | B5: ='AO Call 1.4'!B3 -> 8/26/24-2/25/25 | C5: ='AO Call 1.4'!B4 -> 2539315.2 | D5: =SUM('AO Call 1.4'!E178:K178) -> 2199776.4 | E5: =4/20 -> 0.2 | F5: =D5/6 -> 366629.4
A6: Call 2 - EA | B6: ='AO Call 2'!B3 -> 9/26/22 - 9/25/23 | C6: ='AO Call 2'!B4 -> 951925.9 | D6: =SUM('AO Call 2'!E95:Q95) -> 761448.52 | E6: 0 | F6: =D6/12 -> 63454.043
A7: Call 2.1 - EA | B7: ='AO Call 2.1'!B3 -> 9/26/23 - 9/25/24 | C7: ='AO Call 2.1'!B4 -> 1549632 | D7: =SUM('AO Call 2.1'!F158:Q158) -> 1323896.8 | E7: 0 | F7: =D7/12 -> 110324.73
A8: Call 2.2 - EA | B8: ='AO Call 2.2'!B3 -> 9/26/24 - 9/25/25 | C8: ='AO Call 2.2'!B4 -> 3162581.8 | D8: =SUM('AO Call 2.2'!F159:R159) -> 2726776 | E8: 0 | F8: =D8/12 -> 227231.33
A9: Call 2.3 - EA | B9: 9/26/25 – 9/25/26 | C9: ='AO Call 2.3'!B4 -> 3225811.7 | D9: =SUM('AO Call 2.3'!F159:R159) -> 2575020.4 | E9: 0 | F9: =D9/12 -> 214585.03 | G9: =C9-D9 -> 650791.31 | H9: =SUM('AO Call 2.3'!F159:R159)+SUM('AO Call 2.3'!N104:R104) -> 4074504.4 | I9: =C9-H9 -> -848692.69
A10: Call 3 - ICAM | B10: ='AO Call 3'!B3 -> 3/13/23-3/12/24 | C10: ='AO Call 3'!B4 -> 740213.85 | D10: =SUM('AO Call 3'!F128:N128) -> 740213.82 | E10: 0.5 | F10: =D10/12 -> 61684.485
A11: Call 4 - MFA | B11: ='AO Call 4'!B3 -> 4/10/23-4/9/24 | C11: ='AO Call 4'!B4 -> 954417.6 | D11: =SUM('AO Call 4'!F165:R165) -> 755735.68 | E11: 0 | F11: =D11/12 -> 62977.973
A12: Call 4.1 - MFA | B12: ='AO Call 4.1'!B3 -> 4/10/24-4/9/25 | C12: ='AO Call 4.1'!B4 -> 1723238.4 | D12: =SUM('AO Call 4.1'!E163:Q163) -> 1450735.7 | E12: 0 | F12: =D12/12 -> 120894.64
A13: Call 4.2 - MFA | B13: 4/10/25 - 4/9/26 | C13: ='AO Call 4.2'!B4 -> 1903545.6 | D13: =SUM('AO Call 4.2'!E163:Q163) -> 1483875.7 | E13: 0 | F13: =D13/12 -> 123656.31 | G13: =C13-D13 -> 419669.89 | H13: =SUM('AO Call 4.2'!E163:P163)+SUM('AO Call 4.2'!Q110) -> 1510035.2 | I13: =C13-H13 -> 393510.45
A14: Call 4.3 - MFA | B14: 4/10/26 - 4/9/27 | C14: ='AO Call 4.3'!B4 -> 1941638.4 | D14: =SUM('AO Call 4.3'!E164:Q164) -> 520681.92 | E14: 0 | F14: =D14/12 -> 43390.16 | G14: =C14-D14 -> 1420956.5 | H14: N/A | I14: N/A
A15: Call 5 - Cloud Eng | B15: ='AO Call 5'!B3 -> 5/1/23 - 4/30/24 | C15: ='AO Call 5'!B4 -> 1051922 | D15: =SUM('AO Call 5'!F144:Q144) -> 687212.4 | E15: =2/6 -> 0.33333333 | F15: =D15/12 -> 57267.7
A16: Call 5.1 - Cloud Eng | B16: ='AO Call 5.1'!B3 -> 5/1/24 - 4/30/25 | C16: ='AO Call 5.1'!B4 -> 2003328 | D16: =SUM('AO Call 5.1'!E165:P165) -> 1989024 | E16: =3/6 -> 0.5 | F16: =D16/12 -> 165752
A17: Call 6 - Cloud DevSecOps | B17: ='AO Call 6'!B3 -> 5/25/23 - 5/24/24 | C17: ='AO Call 6'!B4 -> 1028368 | D17: =SUM('AO Call 6'!F163:R163) -> 886516.8 | E17: 0 | F17: =D17/12 -> 73876.4
A18: Call 6.1 - Cloud DevSecOps | B18: ='AO Call 6.1'!C3 -> 5/15/25-5/24/26 | C18: ='AO Call 6.1'!C4 -> 886516.8 | D18: =SUM('AO Call 6.1'!F164:R164) -> 747057.56 | E18: 0 | F18: =D18/12 -> 62254.797
A19: Call 7 - Facilitation Services | B19: ='AO Call 7'!B3 -> 7/14/23 - 11/13/23 | C19: ='AO Call 7'!B4 -> 72030.4 | D19: =C19 -> 72030.4 | E19: =2/3 -> 0.66666667 | F19: =D19/12 -> 6002.5333
A20: Call 8 - IT Gov Boards | B20: ='AO Call 8'!B3 -> 1/31/24 - 1/30/25 | C20: ='AO Call 8'!B4 -> 173114.4 | D20: =SUM('AO Call 8'!E147:P147) -> 158688.2 | E20: 0 | F20: =D20/12 -> 13224.017
A21: Call 9 - ZTA | B21: ='AO Call 9'!B3 -> 3/12/24 - 3/11/25 | C21: ='AO Call 9'!B4 -> 2066204.7 | D21: =SUM('AO Call 9'!E147:P147) -> 838858.34 | E21: =1/8 -> 0.125 | F21: =D21/12 -> 69904.862
A22: Call 10 - External File Sharing | B22: ='AO Call 10'!B3 -> 3/12/24 - 9/11/24 | C22: ='AO Call 10'!B4 -> 339782.4 | D22: =SUM('AO Call 10'!E163:P163) -> 311026.56 | E22: 0 | F22: =D22/12 -> 25918.88
A23: Call 10.1 - External File Sharing | B23: ='AO Call 10.1'!B3 -> 9/12/24 - 3/11/25 | C23: ='AO Call 10.1'!B4 -> 339782.4 | D23: =SUM('AO Call 10.1'!E163:K163) -> 181390.68 | E23: 0 | F23: =D23/12 -> 15115.89
A24: Call 11 - Strategic Portfolio Mgmt | B24: ='AO Call 11'!B3 -> 9/2/24 - 9/1/25 | C24: ='AO Call 11'!B4 -> 1114155 | D24: =SUM('AO Call 11'!E189:I189) -> 162721.65 | E24: 0 | F24: =D24/12 -> 13560.137
A25: Call 12 - EITPM | B25: ='AO Call 12'!B3 -> 9/2/24 - 9/1/25 | C25: ='AO Call 12'!B4 -> 1121708.9 | D25: =SUM('AO Call 12'!E197:Q197) -> 1100318.9 | E25: =1/7 -> 0.14285714 | F25: =D25/12 -> 91693.238
A26: Call 13 - DevSecOps | B26: ='AO Call 13'!B3 -> 9/13/24 - 9/12/25 | C26: ='AO Call 13'!B4 -> 1397088 | D26: =SUM('AO Call 13'!E163:R163) -> 1214185.7 | E26: =1/6 -> 0.16666667 | F26: =D26/12 -> 101182.14
A27: Call 13.1 - DevSecOps | B27: ='AO Call 13.1'!B3 -> 9/13/25 - 9/12/26 | C27: ='AO Call 13.1'!B4 -> 1491977.3 | D27: =SUM('AO Call 13.1'!E163:L163) -> 744032.29 | E27: =1/7 -> 0.14285714 | G27: =C27-D27 -> 747944.99 | H27: =SUM('AO Call 13.1'!N110:R110)+SUM('AO Call 13.1'!E163:R163) -> 1837610.1 | I27: =C27-H27 -> -345632.87
A28: Call 14 - ICAM | B28: ='AO Call 14'!B3 -> 9/13/24 - 9/12/25 | C28: ='AO Call 14'!B4 -> 1248088.4 | D28: =SUM('AO Call 14'!E200:Q200) -> 1084825.8 | E28: =1/3 -> 0.33333333 | F28: =D28/12 -> 90402.154
A29: Call 15 - I&R | B29: ='AO Call 15'!B3 -> 9/25/24 - 9/24/25 | C29: ='AO Call 15'!B4 -> 1817640 | D29: =SUM('AO Call 15'!E162:Q162) -> 1288439.5 | E29: 0 | F29: =D29/12 -> 107369.96
A30: Call 15.1 - I&R | B30: ='AO Call 15.1'!B3 -> 9/25/25 - 9/24/26 | C30: ='AO Call 15.1'!B4 -> 1853995.9 | D30: =SUM('AO Call 15.1'!E162:O162) -> 948808.6 | E30: 0 | G30: =C30-D30 -> 905187.27 | H30: =SUM('AO Call 15.1'!E162:R162)+SUM('AO Call 15.1'!N110:R110) -> 1702762.2 | I30: =C30-H30 -> 151233.63
A31: Call 16 - RAE | B31: ='AO Call 16'!B3 -> 2/26/25 - 2/25/26 | C31: ='AO Call 16'!B4 -> 4578624 | D31: =SUM('AO Call 16'!E174:Q174) -> 3451621.7 | E31: =3/18 -> 0.16666667 | F31: =D31/12 -> 287635.14
A32: Call 16.1 - RAE | B32: ='AO Call 16.1'!B3 -> 2/26/26 - 2/25/27 | C32: ='AO Call 16.1'!B4 -> 3383404.8 | D32: =SUM('AO Call 16.1'!E174:Q174) -> 1270961.2 | E32: =3/15 -> 0.2 | G32: =C32-D32 -> 2112443.6 | H32: =D32+SUM('AO Call 16.1'!H113:R113) -> 3998245 | I32: =C32-H32 -> -614840.18
A33: Call 17 - EITPM | B33: ='AO Call 17'!B3 -> 9/1/25 - 8/31/26 | C33: ='AO Call 17'!B4 -> 1681420.8 | D33: =SUM('AO Call 17'!E174:U174) -> 1452328.7 | E33: =1/8 -> 0.125 | G33: =C33-D33 -> 229092.14 | H33: =D33+SUM('AO Call 17'!M113:P113) -> 2096241.9 | I33: =C33-H33 -> -414821.06
A34: Call 18 - Zero Trust | B34: ='AO Call 18'!B3 -> 9/15/25 - 9/14/26 | C34: ='AO Call 18'!B4 -> 2000000 | D34: =SUM('AO Call 18'!E175:T175) -> 1469174.5 | E34: =4/9 -> 0.44444444 | G34: =C34-D34 -> 530825.52 | H34: =D34+SUM('AO Call 18'!M113:R113) -> 2328406.6 | I34: =C34-H34 -> -328406.56
B35: Total | C35: =SUM(C2:C34) -> 55743701 | D35: =SUM(D2:D34) -> 41881430 | G35: =SUM(G9:G34) -> 7016911.2 | H35: =SUM(H9:H34) -> 17547805 | I35: =SUM(I9:I34) -> -2007649.3

Sheet AO Call 16.1
A2: Project: | B2: Call 16 - RAE Support
A3: PoP: | B3: 2/26/26 - 2/25/27
A4: Funded Ceiling: | B4: 3383404.8
A6: Hours Forecast
E7: 2026 | P7: 2027
D8: Working Days | E8: 19 | F8: 21 | G8: 22 | H8: 23 | I8: 19 | J8: 23 | K8: 22 | L8: 18 | M8: 21 | N8: 20 | O8: 20 | P8: 21 | Q8: N/A
A9: Name | B9: Company | C9: LCAT | D9: Rate | E9: 2 | F9: 3 | G9: 4 | H9: 5 | I9: 6 | J9: 7 | K9: 8 | L9: 9 | M9: 10 | N9: 11 | O9: 12 | P9: 1 | Q9: 2 | R9: 3 | S9: 4 | T9: 5 | U9: 6 | V9: 7 | W9: 8 | X9: 9 | Y9: 10 | Z9: 11 | AA9: 12
A10: Boykin, Darren | B10: TechSur | C10: Information Systems Engineer | D10: 122.45 | E10: =(E$8*8)-8 -> 144 | F10: =(F$8*8)-8 -> 160 | G10: =(G$8*8)-8 -> 168 | H10: =(H$8*8)-8 -> 176 | I10: =(I$8*8)-8 -> 144 | J10: =(J$8*8)-8 -> 176 | K10: =(K$8*8)-8 -> 168 | L10: =(L$8*8)-8 -> 136 | ... P10: =(P$8*8)-8 -> 160 | Q10: =19*8 -> 152
A11: Camp, Andrew | B11: TechSur | C11: Project Manager | D11: 81.63 | E11: =(E$8*8)-8 -> 144 | F11: =(F$8*8)-8 -> 160 | G11: =(G$8*8)-8 -> 168 | H11: =(H$8*8)-8 -> 176 | I11: =(I$8*8)-8 -> 144 | J11: =(J$8*8)-8 -> 176 | K11: =(K$8*8)-8 -> 168 | L11: =(L$8*8)-8 -> 136 | ... P11: =(P$8*8)-8 -> 160 | Q11: =19*8 -> 152
A12: De La Salle, Jessica | B12: TechSur | C12: Communications Specialist | D12: 75.92 | E12: =(E$8*8)-8 -> 144 | F12: =(F$8*8)-8 -> 160 | G12: =(G$8*8)-8 -> 168 | H12: =(H$8*8)-8 -> 176 | I12: =(I$8*8)-8 -> 144 | J12: =(J$8*8)-8 -> 176 | K12: =(K$8*8)-8 -> 168 | L12: =(L$8*8)-8 -> 136 | ... P12: =(P$8*8)-8 -> 160 | Q12: =19*8 -> 152
A13: Duong, Hao (Ray) | B13: JB Mgmt Solutions | C13: Software Engineer | D13: 141.14 | E13: =(E$8*8)-8 -> 144 | F13: =(F$8*8)-8 -> 160 | G13: =(G$8*8)-8 -> 168 | H13: =(H$8*8)-8 -> 176 | I13: =(I$8*8)-8 -> 144 | J13: =(J$8*8)-8 -> 176 | K13: =(K$8*8)-8 -> 168 | L13: =(L$8*8)-8 -> 136 | ... P13: =(P$8*8)-8 -> 160 | Q13: =19*8 -> 152
A14: Eseku, Benjamin | B14: TechSur | C14: Cyber Threat Analyst | D14: 96.18 | E14: =(E$8*8)-8 -> 144 | F14: =(F$8*8)-8 -> 160 | G14: =(G$8*8)-8 -> 168 | H14: =(H$8*8)-8 -> 176 | I14: =(I$8*8)-8 -> 144 | J14: =(J$8*8)-8 -> 176 | K14: =(K$8*8)-8 -> 168 | L14: =(L$8*8)-8 -> 136 | ... P14: =(P$8*8)-8 -> 160 | Q14: =19*8 -> 152
A15: Gaddam, Prathyusha | B15: TechSur | C15: Information Systems Engineer | D15: 122.45 | E15: =(E$8*8)-8 -> 144 | F15: =(F$8*8)-8 -> 160 | G15: =(G$8*8)-8 -> 168 | H15: =(H$8*8)-8 -> 176 | I15: =(I$8*8)-8 -> 144 | J15: =(J$8*8)-8 -> 176 | K15: =(K$8*8)-8 -> 168 | L15: =(L$8*8)-8 -> 136 | ... P15: =(P$8*8)-8 -> 160 | Q15: =19*8 -> 152
A16: Johnson, Deloy | B16: Guidehouse | C16: Systems Engineer | D16: 111.43 | E16: =(E$8*8)-8 -> 144 | F16: =(F$8*8)-8 -> 160 | G16: =(G$8*8)-8 -> 168 | H16: =(H$8*8)-8 -> 176 | I16: =(I$8*8)-8 -> 144 | J16: =(J$8*8)-8 -> 176 | K16: =(K$8*8)-8 -> 168 | L16: =(L$8*8)-8 -> 136 | ... P16: =(P$8*8)-8 -> 160 | Q16: =19*8 -> 152
A17: Lee, Joseph | B17: TechSur | C17: Systems Engineer | D17: 111.43 | E17: =(E$8*8)-8 -> 144 | F17: =(F$8*8)-8 -> 160 | G17: =(G$8*8)-8 -> 168 | H17: =(H$8*8)-8 -> 176 | I17: =(I$8*8)-8 -> 144 | J17: =(J$8*8)-8 -> 176 | K17: =(K$8*8)-8 -> 168 | L17: =(L$8*8)-8 -> 136 | ... P17: =(P$8*8)-8 -> 160 | Q17: =19*8 -> 152
A18: Matalia, Parag | B18: TechSur | C18: Agile Coach | D18: 143.11 | E18: =(E$8*8)-8 -> 144 | F18: =(F$8*8)-8 -> 160 | G18: =(G$8*8)-8 -> 168 | H18: =(H$8*8)-8 -> 176 | I18: =(I$8*8)-8 -> 144 | J18: =(J$8*8)-8 -> 176 | K18: =(K$8*8)-8 -> 168 | L18: =(L$8*8)-8 -> 136 | ... P18: =(P$8*8)-8 -> 160 | Q18: =19*8 -> 152
A19: Mensah, Dora | B19: TechSur | C19: Cyber Threat Analyst | D19: 96.18 | E19: =(E$8*8)-8 -> 144 | F19: =(F$8*8)-8 -> 160 | G19: =(G$8*8)-8 -> 168 | H19: =(H$8*8)-8 -> 176 | I19: =(I$8*8)-8 -> 144 | J19: =(J$8*8)-8 -> 176 | K19: =(K$8*8)-8 -> 168 | L19: =(L$8*8)-8 -> 136 | ... P19: =(P$8*8)-8 -> 160 | Q19: =19*8 -> 152
A20: Niazi, Shamroze | B20: NMA Consulting | C20: Enterprise Architect | D20: 115.47 | E20: =(E$8*8)-8 -> 144 | F20: =(F$8*8)-8 -> 160 | G20: =(G$8*8)-8 -> 168 | H20: =(H$8*8)-8 -> 176 | I20: =(I$8*8)-8 -> 144 | J20: =(J$8*8)-8 -> 176 | K20: =(K$8*8)-8 -> 168 | L20: =(L$8*8)-8 -> 136 | ... P20: =(P$8*8)-8 -> 160 | Q20: =19*8 -> 152
A21: Schomburg, Paul | B21: TechSur | C21: Agile Coach | D21: 143.11 | E21: =(E$8*8)-8 -> 144 | F21: =(F$8*8)-8 -> 160 | G21: =(G$8*8)-8 -> 168 | H21: =(H$8*8)-8 -> 176 | I21: =(I$8*8)-8 -> 144 | J21: =(J$8*8)-8 -> 176 | K21: =(K$8*8)-8 -> 168 | L21: =(L$8*8)-8 -> 136 | ... P21: =(P$8*8)-8 -> 160 | Q21: =19*8 -> 152
